Workbook

Sheet Low-price monthly forecast
A1: Low-price monthly forecast
A2: NightWatch — Forecast · Base
A4: Variable / dimension | B4: 2026-10 | C4: 2026-11 | D4: 2026-12 | E4: 2027-01 | F4: 2027-02 | G4: 2027-03 | H4: 2027-04 | I4: 2027-05 | J4: 2027-06 | K4: 2027-07 | L4: 2027-08 | M4: 2027-09 | N4: 2027-10 | O4: 2027-11 | P4: 2027-12 | Q4: 2028-01 | R4: 2028-02 | S4: 2028-03
A5: NW Opening customers | B5: =SUM('Low-price monthly forecast'!B6,'Low-price monthly forecast'!B7,'Low-price monthly forecast'!B8,'Low-price monthly forecast'!B9) -> 0 | C5: =SUM('Low-price monthly forecast'!C6,'Low-price monthly forecast'!C7,'Low-price monthly forecast'!C8,'Low-price monthly forecast'!C9) -> 40 | D5: =SUM('Low-price monthly forecast'!D6,'Low-price monthly forecast'!D7,'Low-price monthly forecast'!D8,'Low-price monthly forecast'!D9) -> 78.4 | E5: =SUM('Low-price monthly forecast'!E6,'Low-price monthly forecast'!E7,'Low-price monthly forecast'!E8,'Low-price monthly forecast'!E9) -> 115.264 | F5: =SUM('Low-price monthly forecast'!F6,'Low-price monthly forecast'!F7,'Low-price monthly forecast'!F8,'Low-price monthly forecast'!F9) -> 150.65344 | G5: =SUM('Low-price monthly forecast'!G6,'Low-price monthly forecast'!G7,'Low-price monthly forecast'!G8,'Low-price monthly forecast'!G9) -> 184.6273 | H5: =SUM('Low-price monthly forecast'!H6,'Low-price monthly forecast'!H7,'Low-price monthly forecast'!H8,'Low-price monthly forecast'!H9) -> 217.24221 | I5: =SUM('Low-price monthly forecast'!I6,'Low-price monthly forecast'!I7,'Low-price monthly forecast'!I8,'Low-price monthly forecast'!I9) -> 248.55252 | ... S5: =SUM('Low-price monthly forecast'!S6,'Low-price monthly forecast'!S7,'Low-price monthly forecast'!S8,'Low-price monthly forecast'!S9) -> 500.41319
A6: Business | B6: =IF(IF(IF(ISERROR(DATE(2026,10,1)='Model inputs'!B33),DATE(2026,10,1)='Model inputs'!B33,IF('Model inputs'!B33="","",DATE(2026,10,1)='Model inputs'!B33))="",FALSE,IF(ISERROR(DATE(2026,10,1)='Model inputs'!B33),DATE(2026,10,1)='Model inputs'!B33,IF('Model inputs'!B33="","",DATE(2026,10,1)='Model inputs'!B33))),'Model inputs'!B91*'Model inputs'!B22,IF('Model inputs'!K78="","",'Model inputs'!K78)) -> 0 | C6: =IF(IF(IF(ISERROR(DATE(2026,11,1)='Model inputs'!B33),DATE(2026,11,1)='Model inputs'!B33,IF('Model inputs'!B33="","",DATE(2026,11,1)='Model inputs'!B33))="",FALSE,IF(ISERROR(DATE(2026,11,1)='Model inputs'!B33),DATE(2026,11,1)='Model inputs'!B33,IF('Model inputs'!B33="","",DATE(2026,11,1)='Model inputs'!B33))),'Model inputs'!B91*'Model inputs'!B22,IF('Low-price monthly forecast'!B21="","",'Low-price monthly forecast'!B21)) -> 4 | D6: =IF(IF(IF(ISERROR(DATE(2026,12,1)='Model inputs'!B33),DATE(2026,12,1)='Model inputs'!B33,IF('Model inputs'!B33="","",DATE(2026,12,1)='Model inputs'!B33))="",FALSE,IF(ISERROR(DATE(2026,12,1)='Model inputs'!B33),DATE(2026,12,1)='Model inputs'!B33,IF('Model inputs'!B33="","",DATE(2026,12,1)='Model inputs'!B33))),'Model inputs'!B91*'Model inputs'!B22,IF('Low-price monthly forecast'!C21="","",'Low-price monthly forecast'!C21)) -> 7.84 | E6: =IF(IF(IF(ISERROR(DATE(2027,1,1)='Model inputs'!B33),DATE(2027,1,1)='Model inputs'!B33,IF('Model inputs'!B33="","",DATE(2027,1,1)='Model inputs'!B33))="",FALSE,IF(ISERROR(DATE(2027,1,1)='Model inputs'!B33),DATE(2027,1,1)='Model inputs'!B33,IF('Model inputs'!B33="","",DATE(2027,1,1)='Model inputs'!B33))),'Model inputs'!B91*'Model inputs'!B22,IF('Low-price monthly forecast'!D21="","",'Low-price monthly forecast'!D21)) -> 11.5264 | F6: =IF(IF(IF(ISERROR(DATE(2027,2,1)='Model inputs'!B33),DATE(2027,2,1)='Model inputs'!B33,IF('Model inputs'!B33="","",DATE(2027,2,1)='Model inputs'!B33))="",FALSE,IF(ISERROR(DATE(2027,2,1)='Model inputs'!B33),DATE(2027,2,1)='Model inputs'!B33,IF('Model inputs'!B33="","",DATE(2027,2,1)='Model inputs'!B33))),'Model inputs'!B91*'Model inputs'!B22,IF('Low-price monthly forecast'!E21="","",'Low-price monthly forecast'!E21)) -> 15.065344 | G6: =IF(IF(IF(ISERROR(DATE(2027,3,1)='Model inputs'!B33),DATE(2027,3,1)='Model inputs'!B33,IF('Model inputs'!B33="","",DATE(2027,3,1)='Model inputs'!B33))="",FALSE,IF(ISERROR(DATE(2027,3,1)='Model inputs'!B33),DATE(2027,3,1)='Model inputs'!B33,IF('Model inputs'!B33="","",DATE(2027,3,1)='Model inputs'!B33))),'Model inputs'!B91*'Model inputs'!B22,IF('Low-price monthly forecast'!F21="","",'Low-price monthly forecast'!F21)) -> 18.46273 | H6: =IF(IF(IF(ISERROR(DATE(2027,4,1)='Model inputs'!B33),DATE(2027,4,1)='Model inputs'!B33,IF('Model inputs'!B33="","",DATE(2027,4,1)='Model inputs'!B33))="",FALSE,IF(ISERROR(DATE(2027,4,1)='Model inputs'!B33),DATE(2027,4,1)='Model inputs'!B33,IF('Model inputs'!B33="","",DATE(2027,4,1)='Model inputs'!B33))),'Model inputs'!B91*'Model inputs'!B22,IF('Low-price monthly forecast'!G21="","",'Low-price monthly forecast'!G21)) -> 21.724221 | I6: =IF(IF(IF(ISERROR(DATE(2027,5,1)='Model inputs'!B33),DATE(2027,5,1)='Model inputs'!B33,IF('Model inputs'!B33="","",DATE(2027,5,1)='Model inputs'!B33))="",FALSE,IF(ISERROR(DATE(2027,5,1)='Model inputs'!B33),DATE(2027,5,1)='Model inputs'!B33,IF('Model inputs'!B33="","",DATE(2027,5,1)='Model inputs'!B33))),'Model inputs'!B91*'Model inputs'!B22,IF('Low-price monthly forecast'!H21="","",'Low-price monthly forecast'!H21)) -> 24.855252 | J6: =IF(IF(IF(ISERROR(DATE(2027,6,1)='Model inputs'!B33),DATE(2027,6,1)='Model inputs'!B33,IF('Model inputs'!B33="","",DATE(2027,6,1)='Model inputs'!B33))="",FALSE,IF(ISERROR(DATE(2027,6,1)='Model inputs'!B33),DATE(2027,6,1)='Model inputs'!B33,IF('Model inputs'!B33="","",DATE(2027,6,1)='Model inputs'!B33))),'Model inputs'!B91*'Model inputs'!B22,IF('Low-price monthly forecast'!I21="","",'Low-price monthly forecast'!I21)) -> 27.861042 | K6: =IF(IF(IF(ISERROR(DATE(2027,7,1)='Model inputs'!B33),DATE(2027,7,1)='Model inputs'!B33,IF('Model inputs'!B33="","",DATE(2027,7,1)='Model inputs'!B33))="",FALSE,IF(ISERROR(DATE(2027,7,1)='Model inputs'!B33),DATE(2027,7,1)='Model inputs'!B33,IF('Model inputs'!B33="","",DATE(2027,7,1)='Model inputs'!B33))),'Model inputs'!B91*'Model inputs'!B22,IF('Low-price monthly forecast'!J21="","",'Low-price monthly forecast'!J21)) -> 30.7466 | L6: =IF(IF(IF(ISERROR(DATE(2027,8,1)='Model inputs'!B33),DATE(2027,8,1)='Model inputs'!B33,IF('Model inputs'!B33="","",DATE(2027,8,1)='Model inputs'!B33))="",FALSE,IF(ISERROR(DATE(2027,8,1)='Model inputs'!B33),DATE(2027,8,1)='Model inputs'!B33,IF('Model inputs'!B33="","",DATE(2027,8,1)='Model inputs'!B33))),'Model inputs'!B91*'Model inputs'!B22,IF('Low-price monthly forecast'!K21="","",'Low-price monthly forecast'!K21)) -> 33.516736 | M6: =IF(IF(IF(ISERROR(DATE(2027,9,1)='Model inputs'!B33),DATE(2027,9,1)='Model inputs'!B33,IF('Model inputs'!B33="","",DATE(2027,9,1)='Model inputs'!B33))="",FALSE,IF(ISERROR(DATE(2027,9,1)='Model inputs'!B33),DATE(2027,9,1)='Model inputs'!B33,IF('Model inputs'!B33="","",DATE(2027,9,1)='Model inputs'!B33))),'Model inputs'!B91*'Model inputs'!B22,IF('Low-price monthly forecast'!L21="","",'Low-price monthly forecast'!L21)) -> 36.176067 | N6: =IF(IF(IF(ISERROR(DATE(2027,10,1)='Model inputs'!B33),DATE(2027,10,1)='Model inputs'!B33,IF('Model inputs'!B33="","",DATE(2027,10,1)='Model inputs'!B33))="",FALSE,IF(ISERROR(DATE(2027,10,1)='Model inputs'!B33),DATE(2027,10,1)='Model inputs'!B33,IF('Model inputs'!B33="","",DATE(2027,10,1)='Model inputs'!B33))),'Model inputs'!B91*'Model inputs'!B22,IF('Low-price monthly forecast'!M21="","",'Low-price monthly forecast'!M21)) -> 38.729024 | O6: =IF(IF(IF(ISERROR(DATE(2027,11,1)='Model inputs'!B33),DATE(2027,11,1)='Model inputs'!B33,IF('Model inputs'!B33="","",DATE(2027,11,1)='Model inputs'!B33))="",FALSE,IF(ISERROR(DATE(2027,11,1)='Model inputs'!B33),DATE(2027,11,1)='Model inputs'!B33,IF('Model inputs'!B33="","",DATE(2027,11,1)='Model inputs'!B33))),'Model inputs'!B91*'Model inputs'!B22,IF('Low-price monthly forecast'!N21="","",'Low-price monthly forecast'!N21)) -> 41.179863 | P6: =IF(IF(IF(ISERROR(DATE(2027,12,1)='Model inputs'!B33),DATE(2027,12,1)='Model inputs'!B33,IF('Model inputs'!B33="","",DATE(2027,12,1)='Model inputs'!B33))="",FALSE,IF(ISERROR(DATE(2027,12,1)='Model inputs'!B33),DATE(2027,12,1)='Model inputs'!B33,IF('Model inputs'!B33="","",DATE(2027,12,1)='Model inputs'!B33))),'Model inputs'!B91*'Model inputs'!B22,IF('Low-price monthly forecast'!O21="","",'Low-price monthly forecast'!O21)) -> 43.532669 | Q6: =IF(IF(IF(ISERROR(DATE(2028,1,1)='Model inputs'!B33),DATE(2028,1,1)='Model inputs'!B33,IF('Model inputs'!B33="","",DATE(2028,1,1)='Model inputs'!B33))="",FALSE,IF(ISERROR(DATE(2028,1,1)='Model inputs'!B33),DATE(2028,1,1)='Model inputs'!B33,IF('Model inputs'!B33="","",DATE(2028,1,1)='Model inputs'!B33))),'Model inputs'!B91*'Model inputs'!B22,IF('Low-price monthly forecast'!P21="","",'Low-price monthly forecast'!P21)) -> 45.791362 | R6: =IF(IF(IF(ISERROR(DATE(2028,2,1)='Model inputs'!B33),DATE(2028,2,1)='Model inputs'!B33,IF('Model inputs'!B33="","",DATE(2028,2,1)='Model inputs'!B33))="",FALSE,IF(ISERROR(DATE(2028,2,1)='Model inputs'!B33),DATE(2028,2,1)='Model inputs'!B33,IF('Model inputs'!B33="","",DATE(2028,2,1)='Model inputs'!B33))),'Model inputs'!B91*'Model inputs'!B22,IF('Low-price monthly forecast'!Q21="","",'Low-price monthly forecast'!Q21)) -> 47.959708 | S6: =IF(IF(IF(ISERROR(DATE(2028,3,1)='Model inputs'!B33),DATE(2028,3,1)='Model inputs'!B33,IF('Model inputs'!B33="","",DATE(2028,3,1)='Model inputs'!B33))="",FALSE,IF(ISERROR(DATE(2028,3,1)='Model inputs'!B33),DATE(2028,3,1)='Model inputs'!B33,IF('Model inputs'!B33="","",DATE(2028,3,1)='Model inputs'!B33))),'Model inputs'!B91*'Model inputs'!B22,IF('Low-price monthly forecast'!R21="","",'Low-price monthly forecast'!R21)) -> 50.041319
A7: Community | B7: =IF(IF(IF(ISERROR(DATE(2026,10,1)='Model inputs'!B33),DATE(2026,10,1)='Model inputs'!B33,IF('Model inputs'!B33="","",DATE(2026,10,1)='Model inputs'!B33))="",FALSE,IF(ISERROR(DATE(2026,10,1)='Model inputs'!B33),DATE(2026,10,1)='Model inputs'!B33,IF('Model inputs'!B33="","",DATE(2026,10,1)='Model inputs'!B33))),'Model inputs'!B91*'Model inputs'!B23,IF('Model inputs'!K79="","",'Model inputs'!K79)) -> 0 | C7: =IF(IF(IF(ISERROR(DATE(2026,11,1)='Model inputs'!B33),DATE(2026,11,1)='Model inputs'!B33,IF('Model inputs'!B33="","",DATE(2026,11,1)='Model inputs'!B33))="",FALSE,IF(ISERROR(DATE(2026,11,1)='Model inputs'!B33),DATE(2026,11,1)='Model inputs'!B33,IF('Model inputs'!B33="","",DATE(2026,11,1)='Model inputs'!B33))),'Model inputs'!B91*'Model inputs'!B23,IF('Low-price monthly forecast'!B22="","",'Low-price monthly forecast'!B22)) -> 0 | D7: =IF(IF(IF(ISERROR(DATE(2026,12,1)='Model inputs'!B33),DATE(2026,12,1)='Model inputs'!B33,IF('Model inputs'!B33="","",DATE(2026,12,1)='Model inputs'!B33))="",FALSE,IF(ISERROR(DATE(2026,12,1)='Model inputs'!B33),DATE(2026,12,1)='Model inputs'!B33,IF('Model inputs'!B33="","",DATE(2026,12,1)='Model inputs'!B33))),'Model inputs'!B91*'Model inputs'!B23,IF('Low-price monthly forecast'!C22="","",'Low-price monthly forecast'!C22)) -> 0 | E7: =IF(IF(IF(ISERROR(DATE(2027,1,1)='Model inputs'!B33),DATE(2027,1,1)='Model inputs'!B33,IF('Model inputs'!B33="","",DATE(2027,1,1)='Model inputs'!B33))="",FALSE,IF(ISERROR(DATE(2027,1,1)='Model inputs'!B33),DATE(2027,1,1)='Model inputs'!B33,IF('Model inputs'!B33="","",DATE(2027,1,1)='Model inputs'!B33))),'Model inputs'!B91*'Model inputs'!B23,IF('Low-price monthly forecast'!D22="","",'Low-price monthly forecast'!D22)) -> 0 | F7: =IF(IF(IF(ISERROR(DATE(2027,2,1)='Model inputs'!B33),DATE(2027,2,1)='Model inputs'!B33,IF('Model inputs'!B33="","",DATE(2027,2,1)='Model inputs'!B33))="",FALSE,IF(ISERROR(DATE(2027,2,1)='Model inputs'!B33),DATE(2027,2,1)='Model inputs'!B33,IF('Model inputs'!B33="","",DATE(2027,2,1)='Model inputs'!B33))),'Model inputs'!B91*'Model inputs'!B23,IF('Low-price monthly forecast'!E22="","",'Low-price monthly forecast'!E22)) -> 0 | G7: =IF(IF(IF(ISERROR(DATE(2027,3,1)='Model inputs'!B33),DATE(2027,3,1)='Model inputs'!B33,IF('Model inputs'!B33="","",DATE(2027,3,1)='Model inputs'!B33))="",FALSE,IF(ISERROR(DATE(2027,3,1)='Model inputs'!B33),DATE(2027,3,1)='Model inputs'!B33,IF('Model inputs'!B33="","",DATE(2027,3,1)='Model inputs'!B33))),'Model inputs'!B91*'Model inputs'!B23,IF('Low-price monthly forecast'!F22="","",'Low-price monthly forecast'!F22)) -> 0 | H7: =IF(IF(IF(ISERROR(DATE(2027,4,1)='Model inputs'!B33),DATE(2027,4,1)='Model inputs'!B33,IF('Model inputs'!B33="","",DATE(2027,4,1)='Model inputs'!B33))="",FALSE,IF(ISERROR(DATE(2027,4,1)='Model inputs'!B33),DATE(2027,4,1)='Model inputs'!B33,IF('Model inputs'!B33="","",DATE(2027,4,1)='Model inputs'!B33))),'Model inputs'!B91*'Model inputs'!B23,IF('Low-price monthly forecast'!G22="","",'Low-price monthly forecast'!G22)) -> 0 | I7: =IF(IF(IF(ISERROR(DATE(2027,5,1)='Model inputs'!B33),DATE(2027,5,1)='Model inputs'!B33,IF('Model inputs'!B33="","",DATE(2027,5,1)='Model inputs'!B33))="",FALSE,IF(ISERROR(DATE(2027,5,1)='Model inputs'!B33),DATE(2027,5,1)='Model inputs'!B33,IF('Model inputs'!B33="","",DATE(2027,5,1)='Model inputs'!B33))),'Model inputs'!B91*'Model inputs'!B23,IF('Low-price monthly forecast'!H22="","",'Low-price monthly forecast'!H22)) -> 0 | J7: =IF(IF(IF(ISERROR(DATE(2027,6,1)='Model inputs'!B33),DATE(2027,6,1)='Model inputs'!B33,IF('Model inputs'!B33="","",DATE(2027,6,1)='Model inputs'!B33))="",FALSE,IF(ISERROR(DATE(2027,6,1)='Model inputs'!B33),DATE(2027,6,1)='Model inputs'!B33,IF('Model inputs'!B33="","",DATE(2027,6,1)='Model inputs'!B33))),'Model inputs'!B91*'Model inputs'!B23,IF('Low-price monthly forecast'!I22="","",'Low-price monthly forecast'!I22)) -> 0 | K7: =IF(IF(IF(ISERROR(DATE(2027,7,1)='Model inputs'!B33),DATE(2027,7,1)='Model inputs'!B33,IF('Model inputs'!B33="","",DATE(2027,7,1)='Model inputs'!B33))="",FALSE,IF(ISERROR(DATE(2027,7,1)='Model inputs'!B33),DATE(2027,7,1)='Model inputs'!B33,IF('Model inputs'!B33="","",DATE(2027,7,1)='Model inputs'!B33))),'Model inputs'!B91*'Model inputs'!B23,IF('Low-price monthly forecast'!J22="","",'Low-price monthly forecast'!J22)) -> 0 | L7: =IF(IF(IF(ISERROR(DATE(2027,8,1)='Model inputs'!B33),DATE(2027,8,1)='Model inputs'!B33,IF('Model inputs'!B33="","",DATE(2027,8,1)='Model inputs'!B33))="",FALSE,IF(ISERROR(DATE(2027,8,1)='Model inputs'!B33),DATE(2027,8,1)='Model inputs'!B33,IF('Model inputs'!B33="","",DATE(2027,8,1)='Model inputs'!B33))),'Model inputs'!B91*'Model inputs'!B23,IF('Low-price monthly forecast'!K22="","",'Low-price monthly forecast'!K22)) -> 0 | M7: =IF(IF(IF(ISERROR(DATE(2027,9,1)='Model inputs'!B33),DATE(2027,9,1)='Model inputs'!B33,IF('Model inputs'!B33="","",DATE(2027,9,1)='Model inputs'!B33))="",FALSE,IF(ISERROR(DATE(2027,9,1)='Model inputs'!B33),DATE(2027,9,1)='Model inputs'!B33,IF('Model inputs'!B33="","",DATE(2027,9,1)='Model inputs'!B33))),'Model inputs'!B91*'Model inputs'!B23,IF('Low-price monthly forecast'!L22="","",'Low-price monthly forecast'!L22)) -> 0 | N7: =IF(IF(IF(ISERROR(DATE(2027,10,1)='Model inputs'!B33),DATE(2027,10,1)='Model inputs'!B33,IF('Model inputs'!B33="","",DATE(2027,10,1)='Model inputs'!B33))="",FALSE,IF(ISERROR(DATE(2027,10,1)='Model inputs'!B33),DATE(2027,10,1)='Model inputs'!B33,IF('Model inputs'!B33="","",DATE(2027,10,1)='Model inputs'!B33))),'Model inputs'!B91*'Model inputs'!B23,IF('Low-price monthly forecast'!M22="","",'Low-price monthly forecast'!M22)) -> 0 | O7: =IF(IF(IF(ISERROR(DATE(2027,11,1)='Model inputs'!B33),DATE(2027,11,1)='Model inputs'!B33,IF('Model inputs'!B33="","",DATE(2027,11,1)='Model inputs'!B33))="",FALSE,IF(ISERROR(DATE(2027,11,1)='Model inputs'!B33),DATE(2027,11,1)='Model inputs'!B33,IF('Model inputs'!B33="","",DATE(2027,11,1)='Model inputs'!B33))),'Model inputs'!B91*'Model inputs'!B23,IF('Low-price monthly forecast'!N22="","",'Low-price monthly forecast'!N22)) -> 0 | P7: =IF(IF(IF(ISERROR(DATE(2027,12,1)='Model inputs'!B33),DATE(2027,12,1)='Model inputs'!B33,IF('Model inputs'!B33="","",DATE(2027,12,1)='Model inputs'!B33))="",FALSE,IF(ISERROR(DATE(2027,12,1)='Model inputs'!B33),DATE(2027,12,1)='Model inputs'!B33,IF('Model inputs'!B33="","",DATE(2027,12,1)='Model inputs'!B33))),'Model inputs'!B91*'Model inputs'!B23,IF('Low-price monthly forecast'!O22="","",'Low-price monthly forecast'!O22)) -> 0 | Q7: =IF(IF(IF(ISERROR(DATE(2028,1,1)='Model inputs'!B33),DATE(2028,1,1)='Model inputs'!B33,IF('Model inputs'!B33="","",DATE(2028,1,1)='Model inputs'!B33))="",FALSE,IF(ISERROR(DATE(2028,1,1)='Model inputs'!B33),DATE(2028,1,1)='Model inputs'!B33,IF('Model inputs'!B33="","",DATE(2028,1,1)='Model inputs'!B33))),'Model inputs'!B91*'Model inputs'!B23,IF('Low-price monthly forecast'!P22="","",'Low-price monthly forecast'!P22)) -> 0 | R7: =IF(IF(IF(ISERROR(DATE(2028,2,1)='Model inputs'!B33),DATE(2028,2,1)='Model inputs'!B33,IF('Model inputs'!B33="","",DATE(2028,2,1)='Model inputs'!B33))="",FALSE,IF(ISERROR(DATE(2028,2,1)='Model inputs'!B33),DATE(2028,2,1)='Model inputs'!B33,IF('Model inputs'!B33="","",DATE(2028,2,1)='Model inputs'!B33))),'Model inputs'!B91*'Model inputs'!B23,IF('Low-price monthly forecast'!Q22="","",'Low-price monthly forecast'!Q22)) -> 0 | S7: =IF(IF(IF(ISERROR(DATE(2028,3,1)='Model inputs'!B33),DATE(2028,3,1)='Model inputs'!B33,IF('Model inputs'!B33="","",DATE(2028,3,1)='Model inputs'!B33))="",FALSE,IF(ISERROR(DATE(2028,3,1)='Model inputs'!B33),DATE(2028,3,1)='Model inputs'!B33,IF('Model inputs'!B33="","",DATE(2028,3,1)='Model inputs'!B33))),'Model inputs'!B91*'Model inputs'!B23,IF('Low-price monthly forecast'!R22="","",'Low-price monthly forecast'!R22)) -> 0
A8: Starter | B8: =IF(IF(IF(ISERROR(DATE(2026,10,1)='Model inputs'!B33),DATE(2026,10,1)='Model inputs'!B33,IF('Model inputs'!B33="","",DATE(2026,10,1)='Model inputs'!B33))="",FALSE,IF(ISERROR(DATE(2026,10,1)='Model inputs'!B33),DATE(2026,10,1)='Model inputs'!B33,IF('Model inputs'!B33="","",DATE(2026,10,1)='Model inputs'!B33))),'Model inputs'!B91*'Model inputs'!B24,IF('Model inputs'!K80="","",'Model inputs'!K80)) -> 0 | C8: =IF(IF(IF(ISERROR(DATE(2026,11,1)='Model inputs'!B33),DATE(2026,11,1)='Model inputs'!B33,IF('Model inputs'!B33="","",DATE(2026,11,1)='Model inputs'!B33))="",FALSE,IF(ISERROR(DATE(2026,11,1)='Model inputs'!B33),DATE(2026,11,1)='Model inputs'!B33,IF('Model inputs'!B33="","",DATE(2026,11,1)='Model inputs'!B33))),'Model inputs'!B91*'Model inputs'!B24,IF('Low-price monthly forecast'!B23="","",'Low-price monthly forecast'!B23)) -> 22 | D8: =IF(IF(IF(ISERROR(DATE(2026,12,1)='Model inputs'!B33),DATE(2026,12,1)='Model inputs'!B33,IF('Model inputs'!B33="","",DATE(2026,12,1)='Model inputs'!B33))="",FALSE,IF(ISERROR(DATE(2026,12,1)='Model inputs'!B33),DATE(2026,12,1)='Model inputs'!B33,IF('Model inputs'!B33="","",DATE(2026,12,1)='Model inputs'!B33))),'Model inputs'!B91*'Model inputs'!B24,IF('Low-price monthly forecast'!C23="","",'Low-price monthly forecast'!C23)) -> 43.12 | E8: =IF(IF(IF(ISERROR(DATE(2027,1,1)='Model inputs'!B33),DATE(2027,1,1)='Model inputs'!B33,IF('Model inputs'!B33="","",DATE(2027,1,1)='Model inputs'!B33))="",FALSE,IF(ISERROR(DATE(2027,1,1)='Model inputs'!B33),DATE(2027,1,1)='Model inputs'!B33,IF('Model inputs'!B33="","",DATE(2027,1,1)='Model inputs'!B33))),'Model inputs'!B91*'Model inputs'!B24,IF('Low-price monthly forecast'!D23="","",'Low-price monthly forecast'!D23)) -> 63.3952 | F8: =IF(IF(IF(ISERROR(DATE(2027,2,1)='Model inputs'!B33),DATE(2027,2,1)='Model inputs'!B33,IF('Model inputs'!B33="","",DATE(2027,2,1)='Model inputs'!B33))="",FALSE,IF(ISERROR(DATE(2027,2,1)='Model inputs'!B33),DATE(2027,2,1)='Model inputs'!B33,IF('Model inputs'!B33="","",DATE(2027,2,1)='Model inputs'!B33))),'Model inputs'!B91*'Model inputs'!B24,IF('Low-price monthly forecast'!E23="","",'Low-price monthly forecast'!E23)) -> 82.859392 | G8: =IF(IF(IF(ISERROR(DATE(2027,3,1)='Model inputs'!B33),DATE(2027,3,1)='Model inputs'!B33,IF('Model inputs'!B33="","",DATE(2027,3,1)='Model inputs'!B33))="",FALSE,IF(ISERROR(DATE(2027,3,1)='Model inputs'!B33),DATE(2027,3,1)='Model inputs'!B33,IF('Model inputs'!B33="","",DATE(2027,3,1)='Model inputs'!B33))),'Model inputs'!B91*'Model inputs'!B24,IF('Low-price monthly forecast'!F23="","",'Low-price monthly forecast'!F23)) -> 101.54502 | H8: =IF(IF(IF(ISERROR(DATE(2027,4,1)='Model inputs'!B33),DATE(2027,4,1)='Model inputs'!B33,IF('Model inputs'!B33="","",DATE(2027,4,1)='Model inputs'!B33))="",FALSE,IF(ISERROR(DATE(2027,4,1)='Model inputs'!B33),DATE(2027,4,1)='Model inputs'!B33,IF('Model inputs'!B33="","",DATE(2027,4,1)='Model inputs'!B33))),'Model inputs'!B91*'Model inputs'!B24,IF('Low-price monthly forecast'!G23="","",'Low-price monthly forecast'!G23)) -> 119.48322 | I8: =IF(IF(IF(ISERROR(DATE(2027,5,1)='Model inputs'!B33),DATE(2027,5,1)='Model inputs'!B33,IF('Model inputs'!B33="","",DATE(2027,5,1)='Model inputs'!B33))="",FALSE,IF(ISERROR(DATE(2027,5,1)='Model inputs'!B33),DATE(2027,5,1)='Model inputs'!B33,IF('Model inputs'!B33="","",DATE(2027,5,1)='Model inputs'!B33))),'Model inputs'!B91*'Model inputs'!B24,IF('Low-price monthly forecast'!H23="","",'Low-price monthly forecast'!H23)) -> 136.70389 | J8: =IF(IF(IF(ISERROR(DATE(2027,6,1)='Model inputs'!B33),DATE(2027,6,1)='Model inputs'!B33,IF('Model inputs'!B33="","",DATE(2027,6,1)='Model inputs'!B33))="",FALSE,IF(ISERROR(DATE(2027,6,1)='Model inputs'!B33),DATE(2027,6,1)='Model inputs'!B33,IF('Model inputs'!B33="","",DATE(2027,6,1)='Model inputs'!B33))),'Model inputs'!B91*'Model inputs'!B24,IF('Low-price monthly forecast'!I23="","",'Low-price monthly forecast'!I23)) -> 153.23573 | K8: =IF(IF(IF(ISERROR(DATE(2027,7,1)='Model inputs'!B33),DATE(2027,7,1)='Model inputs'!B33,IF('Model inputs'!B33="","",DATE(2027,7,1)='Model inputs'!B33))="",FALSE,IF(ISERROR(DATE(2027,7,1)='Model inputs'!B33),DATE(2027,7,1)='Model inputs'!B33,IF('Model inputs'!B33="","",DATE(2027,7,1)='Model inputs'!B33))),'Model inputs'!B91*'Model inputs'!B24,IF('Low-price monthly forecast'!J23="","",'Low-price monthly forecast'!J23)) -> 169.1063 | L8: =IF(IF(IF(ISERROR(DATE(2027,8,1)='Model inputs'!B33),DATE(2027,8,1)='Model inputs'!B33,IF('Model inputs'!B33="","",DATE(2027,8,1)='Model inputs'!B33))="",FALSE,IF(ISERROR(DATE(2027,8,1)='Model inputs'!B33),DATE(2027,8,1)='Model inputs'!B33,IF('Model inputs'!B33="","",DATE(2027,8,1)='Model inputs'!B33))),'Model inputs'!B91*'Model inputs'!B24,IF('Low-price monthly forecast'!K23="","",'Low-price monthly forecast'!K23)) -> 184.34205 | M8: =IF(IF(IF(ISERROR(DATE(2027,9,1)='Model inputs'!B33),DATE(2027,9,1)='Model inputs'!B33,IF('Model inputs'!B33="","",DATE(2027,9,1)='Model inputs'!B33))="",FALSE,IF(ISERROR(DATE(2027,9,1)='Model inputs'!B33),DATE(2027,9,1)='Model inputs'!B33,IF('Model inputs'!B33="","",DATE(2027,9,1)='Model inputs'!B33))),'Model inputs'!B91*'Model inputs'!B24,IF('Low-price monthly forecast'!L23="","",'Low-price monthly forecast'!L23)) -> 198.96837 | N8: =IF(IF(IF(ISERROR(DATE(2027,10,1)='Model inputs'!B33),DATE(2027,10,1)='Model inputs'!B33,IF('Model inputs'!B33="","",DATE(2027,10,1)='Model inputs'!B33))="",FALSE,IF(ISERROR(DATE(2027,10,1)='Model inputs'!B33),DATE(2027,10,1)='Model inputs'!B33,IF('Model inputs'!B33="","",DATE(2027,10,1)='Model inputs'!B33))),'Model inputs'!B91*'Model inputs'!B24,IF('Low-price monthly forecast'!M23="","",'Low-price monthly forecast'!M23)) -> 213.00963 | O8: =IF(IF(IF(ISERROR(DATE(2027,11,1)='Model inputs'!B33),DATE(2027,11,1)='Model inputs'!B33,IF('Model inputs'!B33="","",DATE(2027,11,1)='Model inputs'!B33))="",FALSE,IF(ISERROR(DATE(2027,11,1)='Model inputs'!B33),DATE(2027,11,1)='Model inputs'!B33,IF('Model inputs'!B33="","",DATE(2027,11,1)='Model inputs'!B33))),'Model inputs'!B91*'Model inputs'!B24,IF('Low-price monthly forecast'!N23="","",'Low-price monthly forecast'!N23)) -> 226.48925 | P8: =IF(IF(IF(ISERROR(DATE(2027,12,1)='Model inputs'!B33),DATE(2027,12,1)='Model inputs'!B33,IF('Model inputs'!B33="","",DATE(2027,12,1)='Model inputs'!B33))="",FALSE,IF(ISERROR(DATE(2027,12,1)='Model inputs'!B33),DATE(2027,12,1)='Model inputs'!B33,IF('Model inputs'!B33="","",DATE(2027,12,1)='Model inputs'!B33))),'Model inputs'!B91*'Model inputs'!B24,IF('Low-price monthly forecast'!O23="","",'Low-price monthly forecast'!O23)) -> 239.42968 | Q8: =IF(IF(IF(ISERROR(DATE(2028,1,1)='Model inputs'!B33),DATE(2028,1,1)='Model inputs'!B33,IF('Model inputs'!B33="","",DATE(2028,1,1)='Model inputs'!B33))="",FALSE,IF(ISERROR(DATE(2028,1,1)='Model inputs'!B33),DATE(2028,1,1)='Model inputs'!B33,IF('Model inputs'!B33="","",DATE(2028,1,1)='Model inputs'!B33))),'Model inputs'!B91*'Model inputs'!B24,IF('Low-price monthly forecast'!P23="","",'Low-price monthly forecast'!P23)) -> 251.85249 | R8: =IF(IF(IF(ISERROR(DATE(2028,2,1)='Model inputs'!B33),DATE(2028,2,1)='Model inputs'!B33,IF('Model inputs'!B33="","",DATE(2028,2,1)='Model inputs'!B33))="",FALSE,IF(ISERROR(DATE(2028,2,1)='Model inputs'!B33),DATE(2028,2,1)='Model inputs'!B33,IF('Model inputs'!B33="","",DATE(2028,2,1)='Model inputs'!B33))),'Model inputs'!B91*'Model inputs'!B24,IF('Low-price monthly forecast'!Q23="","",'Low-price monthly forecast'!Q23)) -> 263.77839 | S8: =IF(IF(IF(ISERROR(DATE(2028,3,1)='Model inputs'!B33),DATE(2028,3,1)='Model inputs'!B33,IF('Model inputs'!B33="","",DATE(2028,3,1)='Model inputs'!B33))="",FALSE,IF(ISERROR(DATE(2028,3,1)='Model inputs'!B33),DATE(2028,3,1)='Model inputs'!B33,IF('Model inputs'!B33="","",DATE(2028,3,1)='Model inputs'!B33))),'Model inputs'!B91*'Model inputs'!B24,IF('Low-price monthly forecast'!R23="","",'Low-price monthly forecast'!R23)) -> 275.22726
A9: Team | B9: =IF(IF(IF(ISERROR(DATE(2026,10,1)='Model inputs'!B33),DATE(2026,10,1)='Model inputs'!B33,IF('Model inputs'!B33="","",DATE(2026,10,1)='Model inputs'!B33))="",FALSE,IF(ISERROR(DATE(2026,10,1)='Model inputs'!B33),DATE(2026,10,1)='Model inputs'!B33,IF('Model inputs'!B33="","",DATE(2026,10,1)='Model inputs'!B33))),'Model inputs'!B91*'Model inputs'!B25,IF('Model inputs'!K81="","",'Model inputs'!K81)) -> 0 | C9: =IF(IF(IF(ISERROR(DATE(2026,11,1)='Model inputs'!B33),DATE(2026,11,1)='Model inputs'!B33,IF('Model inputs'!B33="","",DATE(2026,11,1)='Model inputs'!B33))="",FALSE,IF(ISERROR(DATE(2026,11,1)='Model inputs'!B33),DATE(2026,11,1)='Model inputs'!B33,IF('Model inputs'!B33="","",DATE(2026,11,1)='Model inputs'!B33))),'Model inputs'!B91*'Model inputs'!B25,IF('Low-price monthly forecast'!B24="","",'Low-price monthly forecast'!B24)) -> 14 | D9: =IF(IF(IF(ISERROR(DATE(2026,12,1)='Model inputs'!B33),DATE(2026,12,1)='Model inputs'!B33,IF('Model inputs'!B33="","",DATE(2026,12,1)='Model inputs'!B33))="",FALSE,IF(ISERROR(DATE(2026,12,1)='Model inputs'!B33),DATE(2026,12,1)='Model inputs'!B33,IF('Model inputs'!B33="","",DATE(2026,12,1)='Model inputs'!B33))),'Model inputs'!B91*'Model inputs'!B25,IF('Low-price monthly forecast'!C24="","",'Low-price monthly forecast'!C24)) -> 27.44 | E9: =IF(IF(IF(ISERROR(DATE(2027,1,1)='Model inputs'!B33),DATE(2027,1,1)='Model inputs'!B33,IF('Model inputs'!B33="","",DATE(2027,1,1)='Model inputs'!B33))="",FALSE,IF(ISERROR(DATE(2027,1,1)='Model inputs'!B33),DATE(2027,1,1)='Model inputs'!B33,IF('Model inputs'!B33="","",DATE(2027,1,1)='Model inputs'!B33))),'Model inputs'!B91*'Model inputs'!B25,IF('Low-price monthly forecast'!D24="","",'Low-price monthly forecast'!D24)) -> 40.3424 | F9: =IF(IF(IF(ISERROR(DATE(2027,2,1)='Model inputs'!B33),DATE(2027,2,1)='Model inputs'!B33,IF('Model inputs'!B33="","",DATE(2027,2,1)='Model inputs'!B33))="",FALSE,IF(ISERROR(DATE(2027,2,1)='Model inputs'!B33),DATE(2027,2,1)='Model inputs'!B33,IF('Model inputs'!B33="","",DATE(2027,2,1)='Model inputs'!B33))),'Model inputs'!B91*'Model inputs'!B25,IF('Low-price monthly forecast'!E24="","",'Low-price monthly forecast'!E24)) -> 52.728704 | G9: =IF(IF(IF(ISERROR(DATE(2027,3,1)='Model inputs'!B33),DATE(2027,3,1)='Model inputs'!B33,IF('Model inputs'!B33="","",DATE(2027,3,1)='Model inputs'!B33))="",FALSE,IF(ISERROR(DATE(2027,3,1)='Model inputs'!B33),DATE(2027,3,1)='Model inputs'!B33,IF('Model inputs'!B33="","",DATE(2027,3,1)='Model inputs'!B33))),'Model inputs'!B91*'Model inputs'!B25,IF('Low-price monthly forecast'!F24="","",'Low-price monthly forecast'!F24)) -> 64.619556 | H9: =IF(IF(IF(ISERROR(DATE(2027,4,1)='Model inputs'!B33),DATE(2027,4,1)='Model inputs'!B33,IF('Model inputs'!B33="","",DATE(2027,4,1)='Model inputs'!B33))="",FALSE,IF(ISERROR(DATE(2027,4,1)='Model inputs'!B33),DATE(2027,4,1)='Model inputs'!B33,IF('Model inputs'!B33="","",DATE(2027,4,1)='Model inputs'!B33))),'Model inputs'!B91*'Model inputs'!B25,IF('Low-price monthly forecast'!G24="","",'Low-price monthly forecast'!G24)) -> 76.034774 | I9: =IF(IF(IF(ISERROR(DATE(2027,5,1)='Model inputs'!B33),DATE(2027,5,1)='Model inputs'!B33,IF('Model inputs'!B33="","",DATE(2027,5,1)='Model inputs'!B33))="",FALSE,IF(ISERROR(DATE(2027,5,1)='Model inputs'!B33),DATE(2027,5,1)='Model inputs'!B33,IF('Model inputs'!B33="","",DATE(2027,5,1)='Model inputs'!B33))),'Model inputs'!B91*'Model inputs'!B25,IF('Low-price monthly forecast'!H24="","",'Low-price monthly forecast'!H24)) -> 86.993383 | J9: =IF(IF(IF(ISERROR(DATE(2027,6,1)='Model inputs'!B33),DATE(2027,6,1)='Model inputs'!B33,IF('Model inputs'!B33="","",DATE(2027,6,1)='Model inputs'!B33))="",FALSE,IF(ISERROR(DATE(2027,6,1)='Model inputs'!B33),DATE(2027,6,1)='Model inputs'!B33,IF('Model inputs'!B33="","",DATE(2027,6,1)='Model inputs'!B33))),'Model inputs'!B91*'Model inputs'!B25,IF('Low-price monthly forecast'!I24="","",'Low-price monthly forecast'!I24)) -> 97.513647 | K9: =IF(IF(IF(ISERROR(DATE(2027,7,1)='Model inputs'!B33),DATE(2027,7,1)='Model inputs'!B33,IF('Model inputs'!B33="","",DATE(2027,7,1)='Model inputs'!B33))="",FALSE,IF(ISERROR(DATE(2027,7,1)='Model inputs'!B33),DATE(2027,7,1)='Model inputs'!B33,IF('Model inputs'!B33="","",DATE(2027,7,1)='Model inputs'!B33))),'Model inputs'!B91*'Model inputs'!B25,IF('Low-price monthly forecast'!J24="","",'Low-price monthly forecast'!J24)) -> 107.6131 | L9: =IF(IF(IF(ISERROR(DATE(2027,8,1)='Model inputs'!B33),DATE(2027,8,1)='Model inputs'!B33,IF('Model inputs'!B33="","",DATE(2027,8,1)='Model inputs'!B33))="",FALSE,IF(ISERROR(DATE(2027,8,1)='Model inputs'!B33),DATE(2027,8,1)='Model inputs'!B33,IF('Model inputs'!B33="","",DATE(2027,8,1)='Model inputs'!B33))),'Model inputs'!B91*'Model inputs'!B25,IF('Low-price monthly forecast'!K24="","",'Low-price monthly forecast'!K24)) -> 117.30858 | M9: =IF(IF(IF(ISERROR(DATE(2027,9,1)='Model inputs'!B33),DATE(2027,9,1)='Model inputs'!B33,IF('Model inputs'!B33="","",DATE(2027,9,1)='Model inputs'!B33))="",FALSE,IF(ISERROR(DATE(2027,9,1)='Model inputs'!B33),DATE(2027,9,1)='Model inputs'!B33,IF('Model inputs'!B33="","",DATE(2027,9,1)='Model inputs'!B33))),'Model inputs'!B91*'Model inputs'!B25,IF('Low-price monthly forecast'!L24="","",'Low-price monthly forecast'!L24)) -> 126.61623 | N9: =IF(IF(IF(ISERROR(DATE(2027,10,1)='Model inputs'!B33),DATE(2027,10,1)='Model inputs'!B33,IF('Model inputs'!B33="","",DATE(2027,10,1)='Model inputs'!B33))="",FALSE,IF(ISERROR(DATE(2027,10,1)='Model inputs'!B33),DATE(2027,10,1)='Model inputs'!B33,IF('Model inputs'!B33="","",DATE(2027,10,1)='Model inputs'!B33))),'Model inputs'!B91*'Model inputs'!B25,IF('Low-price monthly forecast'!M24="","",'Low-price monthly forecast'!M24)) -> 135.55158 | O9: =IF(IF(IF(ISERROR(DATE(2027,11,1)='Model inputs'!B33),DATE(2027,11,1)='Model inputs'!B33,IF('Model inputs'!B33="","",DATE(2027,11,1)='Model inputs'!B33))="",FALSE,IF(ISERROR(DATE(2027,11,1)='Model inputs'!B33),DATE(2027,11,1)='Model inputs'!B33,IF('Model inputs'!B33="","",DATE(2027,11,1)='Model inputs'!B33))),'Model inputs'!B91*'Model inputs'!B25,IF('Low-price monthly forecast'!N24="","",'Low-price monthly forecast'!N24)) -> 144.12952 | P9: =IF(IF(IF(ISERROR(DATE(2027,12,1)='Model inputs'!B33),DATE(2027,12,1)='Model inputs'!B33,IF('Model inputs'!B33="","",DATE(2027,12,1)='Model inputs'!B33))="",FALSE,IF(ISERROR(DATE(2027,12,1)='Model inputs'!B33),DATE(2027,12,1)='Model inputs'!B33,IF('Model inputs'!B33="","",DATE(2027,12,1)='Model inputs'!B33))),'Model inputs'!B91*'Model inputs'!B25,IF('Low-price monthly forecast'!O24="","",'Low-price monthly forecast'!O24)) -> 152.36434 | Q9: =IF(IF(IF(ISERROR(DATE(2028,1,1)='Model inputs'!B33),DATE(2028,1,1)='Model inputs'!B33,IF('Model inputs'!B33="","",DATE(2028,1,1)='Model inputs'!B33))="",FALSE,IF(ISERROR(DATE(2028,1,1)='Model inputs'!B33),DATE(2028,1,1)='Model inputs'!B33,IF('Model inputs'!B33="","",DATE(2028,1,1)='Model inputs'!B33))),'Model inputs'!B91*'Model inputs'!B25,IF('Low-price monthly forecast'!P24="","",'Low-price monthly forecast'!P24)) -> 160.26977 | R9: =IF(IF(IF(ISERROR(DATE(2028,2,1)='Model inputs'!B33),DATE(2028,2,1)='Model inputs'!B33,IF('Model inputs'!B33="","",DATE(2028,2,1)='Model inputs'!B33))="",FALSE,IF(ISERROR(DATE(2028,2,1)='Model inputs'!B33),DATE(2028,2,1)='Model inputs'!B33,IF('Model inputs'!B33="","",DATE(2028,2,1)='Model inputs'!B33))),'Model inputs'!B91*'Model inputs'!B25,IF('Low-price monthly forecast'!Q24="","",'Low-price monthly forecast'!Q24)) -> 167.85898 | S9: =IF(IF(IF(ISERROR(DATE(2028,3,1)='Model inputs'!B33),DATE(2028,3,1)='Model inputs'!B33,IF('Model inputs'!B33="","",DATE(2028,3,1)='Model inputs'!B33))="",FALSE,IF(ISERROR(DATE(2028,3,1)='Model inputs'!B33),DATE(2028,3,1)='Model inputs'!B33,IF('Model inputs'!B33="","",DATE(2028,3,1)='Model inputs'!B33))),'Model inputs'!B91*'Model inputs'!B25,IF('Low-price monthly forecast'!R24="","",'Low-price monthly forecast'!R24)) -> 175.14462
A10: NW New customers | B10: =SUM('Low-price monthly forecast'!B11,'Low-price monthly forecast'!B12,'Low-price monthly forecast'!B13,'Low-price monthly forecast'!B14) -> 40 | C10: =SUM('Low-price monthly forecast'!C11,'Low-price monthly forecast'!C12,'Low-price monthly forecast'!C13,'Low-price monthly forecast'!C14) -> 40 | D10: =SUM('Low-price monthly forecast'!D11,'Low-price monthly forecast'!D12,'Low-price monthly forecast'!D13,'Low-price monthly forecast'!D14) -> 40 | E10: =SUM('Low-price monthly forecast'!E11,'Low-price monthly forecast'!E12,'Low-price monthly forecast'!E13,'Low-price monthly forecast'!E14) -> 40 | F10: =SUM('Low-price monthly forecast'!F11,'Low-price monthly forecast'!F12,'Low-price monthly forecast'!F13,'Low-price monthly forecast'!F14) -> 40 | G10: =SUM('Low-price monthly forecast'!G11,'Low-price monthly forecast'!G12,'Low-price monthly forecast'!G13,'Low-price monthly forecast'!G14) -> 40 | H10: =SUM('Low-price monthly forecast'!H11,'Low-price monthly forecast'!H12,'Low-price monthly forecast'!H13,'Low-price monthly forecast'!H14) -> 40 | I10: =SUM('Low-price monthly forecast'!I11,'Low-price monthly forecast'!I12,'Low-price monthly forecast'!I13,'Low-price monthly forecast'!I14) -> 40 | ... S10: =SUM('Low-price monthly forecast'!S11,'Low-price monthly forecast'!S12,'Low-price monthly forecast'!S13,'Low-price monthly forecast'!S14) -> 40
A11: Business | B11: ='Model inputs'!B65*'Model inputs'!B22 -> 4 | C11: ='Model inputs'!B65*'Model inputs'!B22 -> 4 | D11: ='Model inputs'!B65*'Model inputs'!B22 -> 4 | E11: ='Model inputs'!B65*'Model inputs'!B22 -> 4 | F11: ='Model inputs'!B65*'Model inputs'!B22 -> 4 | G11: ='Model inputs'!B65*'Model inputs'!B22 -> 4 | H11: ='Model inputs'!B65*'Model inputs'!B22 -> 4 | I11: ='Model inputs'!B65*'Model inputs'!B22 -> 4 | J11: ='Model inputs'!B65*'Model inputs'!B22 -> 4 | K11: ='Model inputs'!B65*'Model inputs'!B22 -> 4 | L11: ='Model inputs'!B65*'Model inputs'!B22 -> 4 | M11: ='Model inputs'!B65*'Model inputs'!B22 -> 4 | N11: ='Model inputs'!B65*'Model inputs'!B22 -> 4 | O11: ='Model inputs'!B65*'Model inputs'!B22 -> 4 | P11: ='Model inputs'!B65*'Model inputs'!B22 -> 4 | Q11: ='Model inputs'!B65*'Model inputs'!B22 -> 4 | R11: ='Model inputs'!B65*'Model inputs'!B22 -> 4 | S11: ='Model inputs'!B65*'Model inputs'!B22 -> 4
A12: Community | B12: ='Model inputs'!B65*'Model inputs'!B23 -> 0 | C12: ='Model inputs'!B65*'Model inputs'!B23 -> 0 | D12: ='Model inputs'!B65*'Model inputs'!B23 -> 0 | E12: ='Model inputs'!B65*'Model inputs'!B23 -> 0 | F12: ='Model inputs'!B65*'Model inputs'!B23 -> 0 | G12: ='Model inputs'!B65*'Model inputs'!B23 -> 0 | H12: ='Model inputs'!B65*'Model inputs'!B23 -> 0 | I12: ='Model inputs'!B65*'Model inputs'!B23 -> 0 | J12: ='Model inputs'!B65*'Model inputs'!B23 -> 0 | K12: ='Model inputs'!B65*'Model inputs'!B23 -> 0 | L12: ='Model inputs'!B65*'Model inputs'!B23 -> 0 | M12: ='Model inputs'!B65*'Model inputs'!B23 -> 0 | N12: ='Model inputs'!B65*'Model inputs'!B23 -> 0 | O12: ='Model inputs'!B65*'Model inputs'!B23 -> 0 | P12: ='Model inputs'!B65*'Model inputs'!B23 -> 0 | Q12: ='Model inputs'!B65*'Model inputs'!B23 -> 0 | R12: ='Model inputs'!B65*'Model inputs'!B23 -> 0 | S12: ='Model inputs'!B65*'Model inputs'!B23 -> 0
A13: Starter | B13: ='Model inputs'!B65*'Model inputs'!B24 -> 22 | C13: ='Model inputs'!B65*'Model inputs'!B24 -> 22 | D13: ='Model inputs'!B65*'Model inputs'!B24 -> 22 | E13: ='Model inputs'!B65*'Model inputs'!B24 -> 22 | F13: ='Model inputs'!B65*'Model inputs'!B24 -> 22 | G13: ='Model inputs'!B65*'Model inputs'!B24 -> 22 | H13: ='Model inputs'!B65*'Model inputs'!B24 -> 22 | I13: ='Model inputs'!B65*'Model inputs'!B24 -> 22 | J13: ='Model inputs'!B65*'Model inputs'!B24 -> 22 | K13: ='Model inputs'!B65*'Model inputs'!B24 -> 22 | L13: ='Model inputs'!B65*'Model inputs'!B24 -> 22 | M13: ='Model inputs'!B65*'Model inputs'!B24 -> 22 | N13: ='Model inputs'!B65*'Model inputs'!B24 -> 22 | O13: ='Model inputs'!B65*'Model inputs'!B24 -> 22 | P13: ='Model inputs'!B65*'Model inputs'!B24 -> 22 | Q13: ='Model inputs'!B65*'Model inputs'!B24 -> 22 | R13: ='Model inputs'!B65*'Model inputs'!B24 -> 22 | S13: ='Model inputs'!B65*'Model inputs'!B24 -> 22
A14: Team | B14: ='Model inputs'!B65*'Model inputs'!B25 -> 14 | C14: ='Model inputs'!B65*'Model inputs'!B25 -> 14 | D14: ='Model inputs'!B65*'Model inputs'!B25 -> 14 | E14: ='Model inputs'!B65*'Model inputs'!B25 -> 14 | F14: ='Model inputs'!B65*'Model inputs'!B25 -> 14 | G14: ='Model inputs'!B65*'Model inputs'!B25 -> 14 | H14: ='Model inputs'!B65*'Model inputs'!B25 -> 14 | I14: ='Model inputs'!B65*'Model inputs'!B25 -> 14 | J14: ='Model inputs'!B65*'Model inputs'!B25 -> 14 | K14: ='Model inputs'!B65*'Model inputs'!B25 -> 14 | L14: ='Model inputs'!B65*'Model inputs'!B25 -> 14 | M14: ='Model inputs'!B65*'Model inputs'!B25 -> 14 | N14: ='Model inputs'!B65*'Model inputs'!B25 -> 14 | O14: ='Model inputs'!B65*'Model inputs'!B25 -> 14 | P14: ='Model inputs'!B65*'Model inputs'!B25 -> 14 | Q14: ='Model inputs'!B65*'Model inputs'!B25 -> 14 | R14: ='Model inputs'!B65*'Model inputs'!B25 -> 14 | S14: ='Model inputs'!B65*'Model inputs'!B25 -> 14
A15: NW Churned customers | B15: =SUM('Low-price monthly forecast'!B16,'Low-price monthly forecast'!B17,'Low-price monthly forecast'!B18,'Low-price monthly forecast'!B19) -> 0 | C15: =SUM('Low-price monthly forecast'!C16,'Low-price monthly forecast'!C17,'Low-price monthly forecast'!C18,'Low-price monthly forecast'!C19) -> 1.6 | D15: =SUM('Low-price monthly forecast'!D16,'Low-price monthly forecast'!D17,'Low-price monthly forecast'!D18,'Low-price monthly forecast'!D19) -> 3.136 | E15: =SUM('Low-price monthly forecast'!E16,'Low-price monthly forecast'!E17,'Low-price monthly forecast'!E18,'Low-price monthly forecast'!E19) -> 4.61056 | F15: =SUM('Low-price monthly forecast'!F16,'Low-price monthly forecast'!F17,'Low-price monthly forecast'!F18,'Low-price monthly forecast'!F19) -> 6.0261376 | G15: =SUM('Low-price monthly forecast'!G16,'Low-price monthly forecast'!G17,'Low-price monthly forecast'!G18,'Low-price monthly forecast'!G19) -> 7.3850921 | H15: =SUM('Low-price monthly forecast'!H16,'Low-price monthly forecast'!H17,'Low-price monthly forecast'!H18,'Low-price monthly forecast'!H19) -> 8.6896884 | I15: =SUM('Low-price monthly forecast'!I16,'Low-price monthly forecast'!I17,'Low-price monthly forecast'!I18,'Low-price monthly forecast'!I19) -> 9.9421009 | ... S15: =SUM('Low-price monthly forecast'!S16,'Low-price monthly forecast'!S17,'Low-price monthly forecast'!S18,'Low-price monthly forecast'!S19) -> 20.016528
A16: Business | B16: ='Low-price monthly forecast'!B6*'Model inputs'!B59 -> 0 | C16: ='Low-price monthly forecast'!C6*'Model inputs'!B59 -> 0.16 | D16: ='Low-price monthly forecast'!D6*'Model inputs'!B59 -> 0.3136 | E16: ='Low-price monthly forecast'!E6*'Model inputs'!B59 -> 0.461056 | F16: ='Low-price monthly forecast'!F6*'Model inputs'!B59 -> 0.60261376 | G16: ='Low-price monthly forecast'!G6*'Model inputs'!B59 -> 0.73850921 | H16: ='Low-price monthly forecast'!H6*'Model inputs'!B59 -> 0.86896884 | I16: ='Low-price monthly forecast'!I6*'Model inputs'!B59 -> 0.99421009 | J16: ='Low-price monthly forecast'!J6*'Model inputs'!B59 -> 1.1144417 | K16: ='Low-price monthly forecast'!K6*'Model inputs'!B59 -> 1.229864 | L16: ='Low-price monthly forecast'!L6*'Model inputs'!B59 -> 1.3406695 | M16: ='Low-price monthly forecast'!M6*'Model inputs'!B59 -> 1.4470427 | N16: ='Low-price monthly forecast'!N6*'Model inputs'!B59 -> 1.549161 | O16: ='Low-price monthly forecast'!O6*'Model inputs'!B59 -> 1.6471945 | P16: ='Low-price monthly forecast'!P6*'Model inputs'!B59 -> 1.7413068 | Q16: ='Low-price monthly forecast'!Q6*'Model inputs'!B59 -> 1.8316545 | R16: ='Low-price monthly forecast'!R6*'Model inputs'!B59 -> 1.9183883 | S16: ='Low-price monthly forecast'!S6*'Model inputs'!B59 -> 2.0016528
A17: Community | B17: ='Low-price monthly forecast'!B7*'Model inputs'!B59 -> 0 | C17: ='Low-price monthly forecast'!C7*'Model inputs'!B59 -> 0 | D17: ='Low-price monthly forecast'!D7*'Model inputs'!B59 -> 0 | E17: ='Low-price monthly forecast'!E7*'Model inputs'!B59 -> 0 | F17: ='Low-price monthly forecast'!F7*'Model inputs'!B59 -> 0 | G17: ='Low-price monthly forecast'!G7*'Model inputs'!B59 -> 0 | H17: ='Low-price monthly forecast'!H7*'Model inputs'!B59 -> 0 | I17: ='Low-price monthly forecast'!I7*'Model inputs'!B59 -> 0 | J17: ='Low-price monthly forecast'!J7*'Model inputs'!B59 -> 0 | K17: ='Low-price monthly forecast'!K7*'Model inputs'!B59 -> 0 | L17: ='Low-price monthly forecast'!L7*'Model inputs'!B59 -> 0 | M17: ='Low-price monthly forecast'!M7*'Model inputs'!B59 -> 0 | N17: ='Low-price monthly forecast'!N7*'Model inputs'!B59 -> 0 | O17: ='Low-price monthly forecast'!O7*'Model inputs'!B59 -> 0 | P17: ='Low-price monthly forecast'!P7*'Model inputs'!B59 -> 0 | Q17: ='Low-price monthly forecast'!Q7*'Model inputs'!B59 -> 0 | R17: ='Low-price monthly forecast'!R7*'Model inputs'!B59 -> 0 | S17: ='Low-price monthly forecast'!S7*'Model inputs'!B59 -> 0
A18: Starter | B18: ='Low-price monthly forecast'!B8*'Model inputs'!B59 -> 0 | C18: ='Low-price monthly forecast'!C8*'Model inputs'!B59 -> 0.88 | D18: ='Low-price monthly forecast'!D8*'Model inputs'!B59 -> 1.7248 | E18: ='Low-price monthly forecast'!E8*'Model inputs'!B59 -> 2.535808 | F18: ='Low-price monthly forecast'!F8*'Model inputs'!B59 -> 3.3143757 | G18: ='Low-price monthly forecast'!G8*'Model inputs'!B59 -> 4.0618007 | H18: ='Low-price monthly forecast'!H8*'Model inputs'!B59 -> 4.7793286 | I18: ='Low-price monthly forecast'!I8*'Model inputs'!B59 -> 5.4681555 | J18: ='Low-price monthly forecast'!J8*'Model inputs'!B59 -> 6.1294293 | K18: ='Low-price monthly forecast'!K8*'Model inputs'!B59 -> 6.7642521 | L18: ='Low-price monthly forecast'!L8*'Model inputs'!B59 -> 7.373682 | M18: ='Low-price monthly forecast'!M8*'Model inputs'!B59 -> 7.9587347 | N18: ='Low-price monthly forecast'!N8*'Model inputs'!B59 -> 8.5203853 | O18: ='Low-price monthly forecast'!O8*'Model inputs'!B59 -> 9.0595699 | P18: ='Low-price monthly forecast'!P8*'Model inputs'!B59 -> 9.5771871 | Q18: ='Low-price monthly forecast'!Q8*'Model inputs'!B59 -> 10.0741 | R18: ='Low-price monthly forecast'!R8*'Model inputs'!B59 -> 10.551136 | S18: ='Low-price monthly forecast'!S8*'Model inputs'!B59 -> 11.00909
A19: Team | B19: ='Low-price monthly forecast'!B9*'Model inputs'!B59 -> 0 | C19: ='Low-price monthly forecast'!C9*'Model inputs'!B59 -> 0.56 | D19: ='Low-price monthly forecast'!D9*'Model inputs'!B59 -> 1.0976 | E19: ='Low-price monthly forecast'!E9*'Model inputs'!B59 -> 1.613696 | F19: ='Low-price monthly forecast'!F9*'Model inputs'!B59 -> 2.1091482 | G19: ='Low-price monthly forecast'!G9*'Model inputs'!B59 -> 2.5847822 | H19: ='Low-price monthly forecast'!H9*'Model inputs'!B59 -> 3.0413909 | I19: ='Low-price monthly forecast'!I9*'Model inputs'!B59 -> 3.4797353 | J19: ='Low-price monthly forecast'!J9*'Model inputs'!B59 -> 3.9005459 | K19: ='Low-price monthly forecast'!K9*'Model inputs'!B59 -> 4.3045241 | L19: ='Low-price monthly forecast'!L9*'Model inputs'!B59 -> 4.6923431 | M19: ='Low-price monthly forecast'!M9*'Model inputs'!B59 -> 5.0646494 | N19: ='Low-price monthly forecast'!N9*'Model inputs'!B59 -> 5.4220634 | O19: ='Low-price monthly forecast'!O9*'Model inputs'!B59 -> 5.7651809 | P19: ='Low-price monthly forecast'!P9*'Model inputs'!B59 -> 6.0945736 | Q19: ='Low-price monthly forecast'!Q9*'Model inputs'!B59 -> 6.4107907 | R19: ='Low-price monthly forecast'!R9*'Model inputs'!B59 -> 6.7143591 | S19: ='Low-price monthly forecast'!S9*'Model inputs'!B59 -> 7.0057847
A20: NW Paying customers | B20: =SUM('Low-price monthly forecast'!B21,'Low-price monthly forecast'!B22,'Low-price monthly forecast'!B23,'Low-price monthly forecast'!B24) -> 40 | C20: =SUM('Low-price monthly forecast'!C21,'Low-price monthly forecast'!C22,'Low-price monthly forecast'!C23,'Low-price monthly forecast'!C24) -> 78.4 | D20: =SUM('Low-price monthly forecast'!D21,'Low-price monthly forecast'!D22,'Low-price monthly forecast'!D23,'Low-price monthly forecast'!D24) -> 115.264 | E20: =SUM('Low-price monthly forecast'!E21,'Low-price monthly forecast'!E22,'Low-price monthly forecast'!E23,'Low-price monthly forecast'!E24) -> 150.65344 | F20: =SUM('Low-price monthly forecast'!F21,'Low-price monthly forecast'!F22,'Low-price monthly forecast'!F23,'Low-price monthly forecast'!F24) -> 184.6273 | G20: =SUM('Low-price monthly forecast'!G21,'Low-price monthly forecast'!G22,'Low-price monthly forecast'!G23,'Low-price monthly forecast'!G24) -> 217.24221 | H20: =SUM('Low-price monthly forecast'!H21,'Low-price monthly forecast'!H22,'Low-price monthly forecast'!H23,'Low-price monthly forecast'!H24) -> 248.55252 | I20: =SUM('Low-price monthly forecast'!I21,'Low-price monthly forecast'!I22,'Low-price monthly forecast'!I23,'Low-price monthly forecast'!I24) -> 278.61042 | ... S20: =SUM('Low-price monthly forecast'!S21,'Low-price monthly forecast'!S22,'Low-price monthly forecast'!S23,'Low-price monthly forecast'!S24) -> 520.39666
A21: Business | B21: ='Low-price monthly forecast'!B6+'Low-price monthly forecast'!B11-'Low-price monthly forecast'!B16 -> 4 | C21: ='Low-price monthly forecast'!C6+'Low-price monthly forecast'!C11-'Low-price monthly forecast'!C16 -> 7.84 | D21: ='Low-price monthly forecast'!D6+'Low-price monthly forecast'!D11-'Low-price monthly forecast'!D16 -> 11.5264 | E21: ='Low-price monthly forecast'!E6+'Low-price monthly forecast'!E11-'Low-price monthly forecast'!E16 -> 15.065344 | F21: ='Low-price monthly forecast'!F6+'Low-price monthly forecast'!F11-'Low-price monthly forecast'!F16 -> 18.46273 | G21: ='Low-price monthly forecast'!G6+'Low-price monthly forecast'!G11-'Low-price monthly forecast'!G16 -> 21.724221 | H21: ='Low-price monthly forecast'!H6+'Low-price monthly forecast'!H11-'Low-price monthly forecast'!H16 -> 24.855252 | I21: ='Low-price monthly forecast'!I6+'Low-price monthly forecast'!I11-'Low-price monthly forecast'!I16 -> 27.861042 | ... S21: ='Low-price monthly forecast'!S6+'Low-price monthly forecast'!S11-'Low-price monthly forecast'!S16 -> 52.039666
A22: Community | B22: ='Low-price monthly forecast'!B7+'Low-price monthly forecast'!B12-'Low-price monthly forecast'!B17 -> 0 | C22: ='Low-price monthly forecast'!C7+'Low-price monthly forecast'!C12-'Low-price monthly forecast'!C17 -> 0 | D22: ='Low-price monthly forecast'!D7+'Low-price monthly forecast'!D12-'Low-price monthly forecast'!D17 -> 0 | E22: ='Low-price monthly forecast'!E7+'Low-price monthly forecast'!E12-'Low-price monthly forecast'!E17 -> 0 | F22: ='Low-price monthly forecast'!F7+'Low-price monthly forecast'!F12-'Low-price monthly forecast'!F17 -> 0 | G22: ='Low-price monthly forecast'!G7+'Low-price monthly forecast'!G12-'Low-price monthly forecast'!G17 -> 0 | H22: ='Low-price monthly forecast'!H7+'Low-price monthly forecast'!H12-'Low-price monthly forecast'!H17 -> 0 | I22: ='Low-price monthly forecast'!I7+'Low-price monthly forecast'!I12-'Low-price monthly forecast'!I17 -> 0 | ... S22: ='Low-price monthly forecast'!S7+'Low-price monthly forecast'!S12-'Low-price monthly forecast'!S17 -> 0
A23: Starter | B23: ='Low-price monthly forecast'!B8+'Low-price monthly forecast'!B13-'Low-price monthly forecast'!B18 -> 22 | C23: ='Low-price monthly forecast'!C8+'Low-price monthly forecast'!C13-'Low-price monthly forecast'!C18 -> 43.12 | D23: ='Low-price monthly forecast'!D8+'Low-price monthly forecast'!D13-'Low-price monthly forecast'!D18 -> 63.3952 | E23: ='Low-price monthly forecast'!E8+'Low-price monthly forecast'!E13-'Low-price monthly forecast'!E18 -> 82.859392 | F23: ='Low-price monthly forecast'!F8+'Low-price monthly forecast'!F13-'Low-price monthly forecast'!F18 -> 101.54502 | G23: ='Low-price monthly forecast'!G8+'Low-price monthly forecast'!G13-'Low-price monthly forecast'!G18 -> 119.48322 | H23: ='Low-price monthly forecast'!H8+'Low-price monthly forecast'!H13-'Low-price monthly forecast'!H18 -> 136.70389 | I23: ='Low-price monthly forecast'!I8+'Low-price monthly forecast'!I13-'Low-price monthly forecast'!I18 -> 153.23573 | ... S23: ='Low-price monthly forecast'!S8+'Low-price monthly forecast'!S13-'Low-price monthly forecast'!S18 -> 286.21817
A24: Team | B24: ='Low-price monthly forecast'!B9+'Low-price monthly forecast'!B14-'Low-price monthly forecast'!B19 -> 14 | C24: ='Low-price monthly forecast'!C9+'Low-price monthly forecast'!C14-'Low-price monthly forecast'!C19 -> 27.44 | D24: ='Low-price monthly forecast'!D9+'Low-price monthly forecast'!D14-'Low-price monthly forecast'!D19 -> 40.3424 | E24: ='Low-price monthly forecast'!E9+'Low-price monthly forecast'!E14-'Low-price monthly forecast'!E19 -> 52.728704 | F24: ='Low-price monthly forecast'!F9+'Low-price monthly forecast'!F14-'Low-price monthly forecast'!F19 -> 64.619556 | G24: ='Low-price monthly forecast'!G9+'Low-price monthly forecast'!G14-'Low-price monthly forecast'!G19 -> 76.034774 | H24: ='Low-price monthly forecast'!H9+'Low-price monthly forecast'!H14-'Low-price monthly forecast'!H19 -> 86.993383 | I24: ='Low-price monthly forecast'!I9+'Low-price monthly forecast'!I14-'Low-price monthly forecast'!I19 -> 97.513647 | ... S24: ='Low-price monthly forecast'!S9+'Low-price monthly forecast'!S14-'Low-price monthly forecast'!S19 -> 182.13883
A25: NW Subscription revenue | B25: =SUM('Low-price monthly forecast'!B26,'Low-price monthly forecast'!B27,'Low-price monthly forecast'!B28,'Low-price monthly forecast'!B29) -> 1154 | C25: =SUM('Low-price monthly forecast'!C26,'Low-price monthly forecast'!C27,'Low-price monthly forecast'!C28,'Low-price monthly forecast'!C29) -> 2261.84 | D25: =SUM('Low-price monthly forecast'!D26,'Low-price monthly forecast'!D27,'Low-price monthly forecast'!D28,'Low-price monthly forecast'!D29) -> 3325.3664 | E25: =SUM('Low-price monthly forecast'!E26,'Low-price monthly forecast'!E27,'Low-price monthly forecast'!E28,'Low-price monthly forecast'!E29) -> 4346.3517 | F25: =SUM('Low-price monthly forecast'!F26,'Low-price monthly forecast'!F27,'Low-price monthly forecast'!F28,'Low-price monthly forecast'!F29) -> 5326.4977 | G25: =SUM('Low-price monthly forecast'!G26,'Low-price monthly forecast'!G27,'Low-price monthly forecast'!G28,'Low-price monthly forecast'!G29) -> 6267.4378 | H25: =SUM('Low-price monthly forecast'!H26,'Low-price monthly forecast'!H27,'Low-price monthly forecast'!H28,'Low-price monthly forecast'!H29) -> 7170.7403 | I25: =SUM('Low-price monthly forecast'!I26,'Low-price monthly forecast'!I27,'Low-price monthly forecast'!I28,'Low-price monthly forecast'!I29) -> 8037.9106 | ... S25: =SUM('Low-price monthly forecast'!S26,'Low-price monthly forecast'!S27,'Low-price monthly forecast'!S28,'Low-price monthly forecast'!S29) -> 15013.444
A26: Business | B26: ='Low-price monthly forecast'!B21*'Model inputs'!B94 -> 624 | C26: ='Low-price monthly forecast'!C21*'Model inputs'!B94 -> 1223.04 | D26: ='Low-price monthly forecast'!D21*'Model inputs'!B94 -> 1798.1184 | E26: ='Low-price monthly forecast'!E21*'Model inputs'!B94 -> 2350.1937 | F26: ='Low-price monthly forecast'!F21*'Model inputs'!B94 -> 2880.1859 | G26: ='Low-price monthly forecast'!G21*'Model inputs'!B94 -> 3388.9785 | H26: ='Low-price monthly forecast'!H21*'Model inputs'!B94 -> 3877.4193 | I26: ='Low-price monthly forecast'!I21*'Model inputs'!B94 -> 4346.3226 | J26: ='Low-price monthly forecast'!J21*'Model inputs'!B94 -> 4796.4697 | K26: ='Low-price monthly forecast'!K21*'Model inputs'!B94 -> 5228.6109 | L26: ='Low-price monthly forecast'!L21*'Model inputs'!B94 -> 5643.4664 | M26: ='Low-price monthly forecast'!M21*'Model inputs'!B94 -> 6041.7278 | N26: ='Low-price monthly forecast'!N21*'Model inputs'!B94 -> 6424.0587 | O26: ='Low-price monthly forecast'!O21*'Model inputs'!B94 -> 6791.0963 | P26: ='Low-price monthly forecast'!P21*'Model inputs'!B94 -> 7143.4525 | Q26: ='Low-price monthly forecast'!Q21*'Model inputs'!B94 -> 7481.7144 | R26: ='Low-price monthly forecast'!R21*'Model inputs'!B94 -> 7806.4458 | S26: ='Low-price monthly forecast'!S21*'Model inputs'!B94 -> 8118.188
A27: Community | B27: ='Low-price monthly forecast'!B22*'Model inputs'!B95 -> 0 | C27: ='Low-price monthly forecast'!C22*'Model inputs'!B95 -> 0 | D27: ='Low-price monthly forecast'!D22*'Model inputs'!B95 -> 0 | E27: ='Low-price monthly forecast'!E22*'Model inputs'!B95 -> 0 | F27: ='Low-price monthly forecast'!F22*'Model inputs'!B95 -> 0 | G27: ='Low-price monthly forecast'!G22*'Model inputs'!B95 -> 0 | H27: ='Low-price monthly forecast'!H22*'Model inputs'!B95 -> 0 | I27: ='Low-price monthly forecast'!I22*'Model inputs'!B95 -> 0 | J27: ='Low-price monthly forecast'!J22*'Model inputs'!B95 -> 0 | K27: ='Low-price monthly forecast'!K22*'Model inputs'!B95 -> 0 | L27: ='Low-price monthly forecast'!L22*'Model inputs'!B95 -> 0 | M27: ='Low-price monthly forecast'!M22*'Model inputs'!B95 -> 0 | N27: ='Low-price monthly forecast'!N22*'Model inputs'!B95 -> 0 | O27: ='Low-price monthly forecast'!O22*'Model inputs'!B95 -> 0 | P27: ='Low-price monthly forecast'!P22*'Model inputs'!B95 -> 0 | Q27: ='Low-price monthly forecast'!Q22*'Model inputs'!B95 -> 0 | R27: ='Low-price monthly forecast'!R22*'Model inputs'!B95 -> 0 | S27: ='Low-price monthly forecast'!S22*'Model inputs'!B95 -> 0
A28: Starter | B28: ='Low-price monthly forecast'!B23*'Model inputs'!B96 -> 110 | C28: ='Low-price monthly forecast'!C23*'Model inputs'!B96 -> 215.6 | D28: ='Low-price monthly forecast'!D23*'Model inputs'!B96 -> 316.976 | E28: ='Low-price monthly forecast'!E23*'Model inputs'!B96 -> 414.29696 | F28: ='Low-price monthly forecast'!F23*'Model inputs'!B96 -> 507.72508 | G28: ='Low-price monthly forecast'!G23*'Model inputs'!B96 -> 597.41608 | H28: ='Low-price monthly forecast'!H23*'Model inputs'!B96 -> 683.51944 | I28: ='Low-price monthly forecast'!I23*'Model inputs'!B96 -> 766.17866 | J28: ='Low-price monthly forecast'!J23*'Model inputs'!B96 -> 845.53151 | K28: ='Low-price monthly forecast'!K23*'Model inputs'!B96 -> 921.71025 | L28: ='Low-price monthly forecast'!L23*'Model inputs'!B96 -> 994.84184 | M28: ='Low-price monthly forecast'!M23*'Model inputs'!B96 -> 1065.0482 | N28: ='Low-price monthly forecast'!N23*'Model inputs'!B96 -> 1132.4462 | O28: ='Low-price monthly forecast'!O23*'Model inputs'!B96 -> 1197.1484 | P28: ='Low-price monthly forecast'!P23*'Model inputs'!B96 -> 1259.2625 | Q28: ='Low-price monthly forecast'!Q23*'Model inputs'!B96 -> 1318.892 | R28: ='Low-price monthly forecast'!R23*'Model inputs'!B96 -> 1376.1363 | S28: ='Low-price monthly forecast'!S23*'Model inputs'!B96 -> 1431.0908
A29: Team | B29: ='Low-price monthly forecast'!B24*'Model inputs'!B97 -> 420 | C29: ='Low-price monthly forecast'!C24*'Model inputs'!B97 -> 823.2 | D29: ='Low-price monthly forecast'!D24*'Model inputs'!B97 -> 1210.272 | E29: ='Low-price monthly forecast'!E24*'Model inputs'!B97 -> 1581.8611 | F29: ='Low-price monthly forecast'!F24*'Model inputs'!B97 -> 1938.5867 | G29: ='Low-price monthly forecast'!G24*'Model inputs'!B97 -> 2281.0432 | H29: ='Low-price monthly forecast'!H24*'Model inputs'!B97 -> 2609.8015 | I29: ='Low-price monthly forecast'!I24*'Model inputs'!B97 -> 2925.4094 | J29: ='Low-price monthly forecast'!J24*'Model inputs'!B97 -> 3228.393 | K29: ='Low-price monthly forecast'!K24*'Model inputs'!B97 -> 3519.2573 | L29: ='Low-price monthly forecast'!L24*'Model inputs'!B97 -> 3798.487 | M29: ='Low-price monthly forecast'!M24*'Model inputs'!B97 -> 4066.5475 | N29: ='Low-price monthly forecast'!N24*'Model inputs'!B97 -> 4323.8856 | O29: ='Low-price monthly forecast'!O24*'Model inputs'!B97 -> 4570.9302 | P29: ='Low-price monthly forecast'!P24*'Model inputs'!B97 -> 4808.093 | Q29: ='Low-price monthly forecast'!Q24*'Model inputs'!B97 -> 5035.7693 | R29: ='Low-price monthly forecast'!R24*'Model inputs'!B97 -> 5254.3385 | S29: ='Low-price monthly forecast'!S24*'Model inputs'!B97 -> 5464.165
A30: NW Overage revenue | B30: =SUM('Low-price monthly forecast'!B31,'Low-price monthly forecast'!B32,'Low-price monthly forecast'!B33,'Low-price monthly forecast'!B34) -> 0 | C30: =SUM('Low-price monthly forecast'!C31,'Low-price monthly forecast'!C32,'Low-price monthly forecast'!C33,'Low-price monthly forecast'!C34) -> 0 | D30: =SUM('Low-price monthly forecast'!D31,'Low-price monthly forecast'!D32,'Low-price monthly forecast'!D33,'Low-price monthly forecast'!D34) -> 0 | E30: =SUM('Low-price monthly forecast'!E31,'Low-price monthly forecast'!E32,'Low-price monthly forecast'!E33,'Low-price monthly forecast'!E34) -> 0 | F30: =SUM('Low-price monthly forecast'!F31,'Low-price monthly forecast'!F32,'Low-price monthly forecast'!F33,'Low-price monthly forecast'!F34) -> 0 | G30: =SUM('Low-price monthly forecast'!G31,'Low-price monthly forecast'!G32,'Low-price monthly forecast'!G33,'Low-price monthly forecast'!G34) -> 0 | H30: =SUM('Low-price monthly forecast'!H31,'Low-price monthly forecast'!H32,'Low-price monthly forecast'!H33,'Low-price monthly forecast'!H34) -> 0 | I30: =SUM('Low-price monthly forecast'!I31,'Low-price monthly forecast'!I32,'Low-price monthly forecast'!I33,'Low-price monthly forecast'!I34) -> 0 | ... S30: =SUM('Low-price monthly forecast'!S31,'Low-price monthly forecast'!S32,'Low-price monthly forecast'!S33,'Low-price monthly forecast'!S34) -> 0
A31: Business | B31: ='Low-price monthly forecast'!B21*'Model inputs'!B73 -> 0 | C31: ='Low-price monthly forecast'!C21*'Model inputs'!B73 -> 0 | D31: ='Low-price monthly forecast'!D21*'Model inputs'!B73 -> 0 | E31: ='Low-price monthly forecast'!E21*'Model inputs'!B73 -> 0 | F31: ='Low-price monthly forecast'!F21*'Model inputs'!B73 -> 0 | G31: ='Low-price monthly forecast'!G21*'Model inputs'!B73 -> 0 | H31: ='Low-price monthly forecast'!H21*'Model inputs'!B73 -> 0 | I31: ='Low-price monthly forecast'!I21*'Model inputs'!B73 -> 0 | J31: ='Low-price monthly forecast'!J21*'Model inputs'!B73 -> 0 | K31: ='Low-price monthly forecast'!K21*'Model inputs'!B73 -> 0 | L31: ='Low-price monthly forecast'!L21*'Model inputs'!B73 -> 0 | M31: ='Low-price monthly forecast'!M21*'Model inputs'!B73 -> 0 | N31: ='Low-price monthly forecast'!N21*'Model inputs'!B73 -> 0 | O31: ='Low-price monthly forecast'!O21*'Model inputs'!B73 -> 0 | P31: ='Low-price monthly forecast'!P21*'Model inputs'!B73 -> 0 | Q31: ='Low-price monthly forecast'!Q21*'Model inputs'!B73 -> 0 | R31: ='Low-price monthly forecast'!R21*'Model inputs'!B73 -> 0 | S31: ='Low-price monthly forecast'!S21*'Model inputs'!B73 -> 0
A32: Community | B32: ='Low-price monthly forecast'!B22*'Model inputs'!B74 -> 0 | C32: ='Low-price monthly forecast'!C22*'Model inputs'!B74 -> 0 | D32: ='Low-price monthly forecast'!D22*'Model inputs'!B74 -> 0 | E32: ='Low-price monthly forecast'!E22*'Model inputs'!B74 -> 0 | F32: ='Low-price monthly forecast'!F22*'Model inputs'!B74 -> 0 | G32: ='Low-price monthly forecast'!G22*'Model inputs'!B74 -> 0 | H32: ='Low-price monthly forecast'!H22*'Model inputs'!B74 -> 0 | I32: ='Low-price monthly forecast'!I22*'Model inputs'!B74 -> 0 | J32: ='Low-price monthly forecast'!J22*'Model inputs'!B74 -> 0 | K32: ='Low-price monthly forecast'!K22*'Model inputs'!B74 -> 0 | L32: ='Low-price monthly forecast'!L22*'Model inputs'!B74 -> 0 | M32: ='Low-price monthly forecast'!M22*'Model inputs'!B74 -> 0 | N32: ='Low-price monthly forecast'!N22*'Model inputs'!B74 -> 0 | O32: ='Low-price monthly forecast'!O22*'Model inputs'!B74 -> 0 | P32: ='Low-price monthly forecast'!P22*'Model inputs'!B74 -> 0 | Q32: ='Low-price monthly forecast'!Q22*'Model inputs'!B74 -> 0 | R32: ='Low-price monthly forecast'!R22*'Model inputs'!B74 -> 0 | S32: ='Low-price monthly forecast'!S22*'Model inputs'!B74 -> 0
A33: Starter | B33: ='Low-price monthly forecast'!B23*'Model inputs'!B75 -> 0 | C33: ='Low-price monthly forecast'!C23*'Model inputs'!B75 -> 0 | D33: ='Low-price monthly forecast'!D23*'Model inputs'!B75 -> 0 | E33: ='Low-price monthly forecast'!E23*'Model inputs'!B75 -> 0 | F33: ='Low-price monthly forecast'!F23*'Model inputs'!B75 -> 0 | G33: ='Low-price monthly forecast'!G23*'Model inputs'!B75 -> 0 | H33: ='Low-price monthly forecast'!H23*'Model inputs'!B75 -> 0 | I33: ='Low-price monthly forecast'!I23*'Model inputs'!B75 -> 0 | J33: ='Low-price monthly forecast'!J23*'Model inputs'!B75 -> 0 | K33: ='Low-price monthly forecast'!K23*'Model inputs'!B75 -> 0 | L33: ='Low-price monthly forecast'!L23*'Model inputs'!B75 -> 0 | M33: ='Low-price monthly forecast'!M23*'Model inputs'!B75 -> 0 | N33: ='Low-price monthly forecast'!N23*'Model inputs'!B75 -> 0 | O33: ='Low-price monthly forecast'!O23*'Model inputs'!B75 -> 0 | P33: ='Low-price monthly forecast'!P23*'Model inputs'!B75 -> 0 | Q33: ='Low-price monthly forecast'!Q23*'Model inputs'!B75 -> 0 | R33: ='Low-price monthly forecast'!R23*'Model inputs'!B75 -> 0 | S33: ='Low-price monthly forecast'!S23*'Model inputs'!B75 -> 0
A34: Team | B34: ='Low-price monthly forecast'!B24*'Model inputs'!B76 -> 0 | C34: ='Low-price monthly forecast'!C24*'Model inputs'!B76 -> 0 | D34: ='Low-price monthly forecast'!D24*'Model inputs'!B76 -> 0 | E34: ='Low-price monthly forecast'!E24*'Model inputs'!B76 -> 0 | F34: ='Low-price monthly forecast'!F24*'Model inputs'!B76 -> 0 | G34: ='Low-price monthly forecast'!G24*'Model inputs'!B76 -> 0 | H34: ='Low-price monthly forecast'!H24*'Model inputs'!B76 -> 0 | I34: ='Low-price monthly forecast'!I24*'Model inputs'!B76 -> 0 | J34: ='Low-price monthly forecast'!J24*'Model inputs'!B76 -> 0 | K34: ='Low-price monthly forecast'!K24*'Model inputs'!B76 -> 0 | L34: ='Low-price monthly forecast'!L24*'Model inputs'!B76 -> 0 | M34: ='Low-price monthly forecast'!M24*'Model inputs'!B76 -> 0 | N34: ='Low-price monthly forecast'!N24*'Model inputs'!B76 -> 0 | O34: ='Low-price monthly forecast'!O24*'Model inputs'!B76 -> 0 | P34: ='Low-price monthly forecast'!P24*'Model inputs'!B76 -> 0 | Q34: ='Low-price monthly forecast'!Q24*'Model inputs'!B76 -> 0 | R34: ='Low-price monthly forecast'!R24*'Model inputs'!B76 -> 0 | S34: ='Low-price monthly forecast'!S24*'Model inputs'!B76 -> 0
A35: NW Revenue | B35: =SUM('Low-price monthly forecast'!B36,'Low-price monthly forecast'!B37,'Low-price monthly forecast'!B38,'Low-price monthly forecast'!B39) -> 1154 | C35: =SUM('Low-price monthly forecast'!C36,'Low-price monthly forecast'!C37,'Low-price monthly forecast'!C38,'Low-price monthly forecast'!C39) -> 2261.84 | D35: =SUM('Low-price monthly forecast'!D36,'Low-price monthly forecast'!D37,'Low-price monthly forecast'!D38,'Low-price monthly forecast'!D39) -> 3325.3664 | E35: =SUM('Low-price monthly forecast'!E36,'Low-price monthly forecast'!E37,'Low-price monthly forecast'!E38,'Low-price monthly forecast'!E39) -> 4346.3517 | F35: =SUM('Low-price monthly forecast'!F36,'Low-price monthly forecast'!F37,'Low-price monthly forecast'!F38,'Low-price monthly forecast'!F39) -> 5326.4977 | G35: =SUM('Low-price monthly forecast'!G36,'Low-price monthly forecast'!G37,'Low-price monthly forecast'!G38,'Low-price monthly forecast'!G39) -> 6267.4378 | H35: =SUM('Low-price monthly forecast'!H36,'Low-price monthly forecast'!H37,'Low-price monthly forecast'!H38,'Low-price monthly forecast'!H39) -> 7170.7403 | I35: =SUM('Low-price monthly forecast'!I36,'Low-price monthly forecast'!I37,'Low-price monthly forecast'!I38,'Low-price monthly forecast'!I39) -> 8037.9106 | ... S35: =SUM('Low-price monthly forecast'!S36,'Low-price monthly forecast'!S37,'Low-price monthly forecast'!S38,'Low-price monthly forecast'!S39) -> 15013.444
A36: Business | B36: ='Low-price monthly forecast'!B21*'Model inputs'!B86 -> 624 | C36: ='Low-price monthly forecast'!C21*'Model inputs'!B86 -> 1223.04 | D36: ='Low-price monthly forecast'!D21*'Model inputs'!B86 -> 1798.1184 | E36: ='Low-price monthly forecast'!E21*'Model inputs'!B86 -> 2350.1937 | F36: ='Low-price monthly forecast'!F21*'Model inputs'!B86 -> 2880.1859 | G36: ='Low-price monthly forecast'!G21*'Model inputs'!B86 -> 3388.9785 | H36: ='Low-price monthly forecast'!H21*'Model inputs'!B86 -> 3877.4193 | I36: ='Low-price monthly forecast'!I21*'Model inputs'!B86 -> 4346.3226 | J36: ='Low-price monthly forecast'!J21*'Model inputs'!B86 -> 4796.4697 | K36: ='Low-price monthly forecast'!K21*'Model inputs'!B86 -> 5228.6109 | L36: ='Low-price monthly forecast'!L21*'Model inputs'!B86 -> 5643.4664 | M36: ='Low-price monthly forecast'!M21*'Model inputs'!B86 -> 6041.7278 | N36: ='Low-price monthly forecast'!N21*'Model inputs'!B86 -> 6424.0587 | O36: ='Low-price monthly forecast'!O21*'Model inputs'!B86 -> 6791.0963 | P36: ='Low-price monthly forecast'!P21*'Model inputs'!B86 -> 7143.4525 | Q36: ='Low-price monthly forecast'!Q21*'Model inputs'!B86 -> 7481.7144 | R36: ='Low-price monthly forecast'!R21*'Model inputs'!B86 -> 7806.4458 | S36: ='Low-price monthly forecast'!S21*'Model inputs'!B86 -> 8118.188
A37: Community | B37: ='Low-price monthly forecast'!B22*'Model inputs'!B87 -> 0 | C37: ='Low-price monthly forecast'!C22*'Model inputs'!B87 -> 0 | D37: ='Low-price monthly forecast'!D22*'Model inputs'!B87 -> 0 | E37: ='Low-price monthly forecast'!E22*'Model inputs'!B87 -> 0 | F37: ='Low-price monthly forecast'!F22*'Model inputs'!B87 -> 0 | G37: ='Low-price monthly forecast'!G22*'Model inputs'!B87 -> 0 | H37: ='Low-price monthly forecast'!H22*'Model inputs'!B87 -> 0 | I37: ='Low-price monthly forecast'!I22*'Model inputs'!B87 -> 0 | J37: ='Low-price monthly forecast'!J22*'Model inputs'!B87 -> 0 | K37: ='Low-price monthly forecast'!K22*'Model inputs'!B87 -> 0 | L37: ='Low-price monthly forecast'!L22*'Model inputs'!B87 -> 0 | M37: ='Low-price monthly forecast'!M22*'Model inputs'!B87 -> 0 | N37: ='Low-price monthly forecast'!N22*'Model inputs'!B87 -> 0 | O37: ='Low-price monthly forecast'!O22*'Model inputs'!B87 -> 0 | P37: ='Low-price monthly forecast'!P22*'Model inputs'!B87 -> 0 | Q37: ='Low-price monthly forecast'!Q22*'Model inputs'!B87 -> 0 | R37: ='Low-price monthly forecast'!R22*'Model inputs'!B87 -> 0 | S37: ='Low-price monthly forecast'!S22*'Model inputs'!B87 -> 0
A38: Starter | B38: ='Low-price monthly forecast'!B23*'Model inputs'!B88 -> 110 | C38: ='Low-price monthly forecast'!C23*'Model inputs'!B88 -> 215.6 | D38: ='Low-price monthly forecast'!D23*'Model inputs'!B88 -> 316.976 | E38: ='Low-price monthly forecast'!E23*'Model inputs'!B88 -> 414.29696 | F38: ='Low-price monthly forecast'!F23*'Model inputs'!B88 -> 507.72508 | G38: ='Low-price monthly forecast'!G23*'Model inputs'!B88 -> 597.41608 | H38: ='Low-price monthly forecast'!H23*'Model inputs'!B88 -> 683.51944 | I38: ='Low-price monthly forecast'!I23*'Model inputs'!B88 -> 766.17866 | J38: ='Low-price monthly forecast'!J23*'Model inputs'!B88 -> 845.53151 | K38: ='Low-price monthly forecast'!K23*'Model inputs'!B88 -> 921.71025 | L38: ='Low-price monthly forecast'!L23*'Model inputs'!B88 -> 994.84184 | M38: ='Low-price monthly forecast'!M23*'Model inputs'!B88 -> 1065.0482 | N38: ='Low-price monthly forecast'!N23*'Model inputs'!B88 -> 1132.4462 | O38: ='Low-price monthly forecast'!O23*'Model inputs'!B88 -> 1197.1484 | P38: ='Low-price monthly forecast'!P23*'Model inputs'!B88 -> 1259.2625 | Q38: ='Low-price monthly forecast'!Q23*'Model inputs'!B88 -> 1318.892 | R38: ='Low-price monthly forecast'!R23*'Model inputs'!B88 -> 1376.1363 | S38: ='Low-price monthly forecast'!S23*'Model inputs'!B88 -> 1431.0908
A39: Team | B39: ='Low-price monthly forecast'!B24*'Model inputs'!B89 -> 420 | C39: ='Low-price monthly forecast'!C24*'Model inputs'!B89 -> 823.2 | D39: ='Low-price monthly forecast'!D24*'Model inputs'!B89 -> 1210.272 | E39: ='Low-price monthly forecast'!E24*'Model inputs'!B89 -> 1581.8611 | F39: ='Low-price monthly forecast'!F24*'Model inputs'!B89 -> 1938.5867 | G39: ='Low-price monthly forecast'!G24*'Model inputs'!B89 -> 2281.0432 | H39: ='Low-price monthly forecast'!H24*'Model inputs'!B89 -> 2609.8015 | I39: ='Low-price monthly forecast'!I24*'Model inputs'!B89 -> 2925.4094 | J39: ='Low-price monthly forecast'!J24*'Model inputs'!B89 -> 3228.393 | K39: ='Low-price monthly forecast'!K24*'Model inputs'!B89 -> 3519.2573 | L39: ='Low-price monthly forecast'!L24*'Model inputs'!B89 -> 3798.487 | M39: ='Low-price monthly forecast'!M24*'Model inputs'!B89 -> 4066.5475 | N39: ='Low-price monthly forecast'!N24*'Model inputs'!B89 -> 4323.8856 | O39: ='Low-price monthly forecast'!O24*'Model inputs'!B89 -> 4570.9302 | P39: ='Low-price monthly forecast'!P24*'Model inputs'!B89 -> 4808.093 | Q39: ='Low-price monthly forecast'!Q24*'Model inputs'!B89 -> 5035.7693 | R39: ='Low-price monthly forecast'!R24*'Model inputs'!B89 -> 5254.3385 | S39: ='Low-price monthly forecast'!S24*'Model inputs'!B89 -> 5464.165
A40: NW Model delivery cost | B40: =SUM('Low-price monthly forecast'!B41,'Low-price monthly forecast'!B42,'Low-price monthly forecast'!B43,'Low-price monthly forecast'!B44) -> 139.2 | C40: =SUM('Low-price monthly forecast'!C41,'Low-price monthly forecast'!C42,'Low-price monthly forecast'!C43,'Low-price monthly forecast'!C44) -> 272.832 | D40: =SUM('Low-price monthly forecast'!D41,'Low-price monthly forecast'!D42,'Low-price monthly forecast'!D43,'Low-price monthly forecast'!D44) -> 401.11872 | E40: =SUM('Low-price monthly forecast'!E41,'Low-price monthly forecast'!E42,'Low-price monthly forecast'!E43,'Low-price monthly forecast'!E44) -> 524.27397 | F40: =SUM('Low-price monthly forecast'!F41,'Low-price monthly forecast'!F42,'Low-price monthly forecast'!F43,'Low-price monthly forecast'!F44) -> 642.50301 | G40: =SUM('Low-price monthly forecast'!G41,'Low-price monthly forecast'!G42,'Low-price monthly forecast'!G43,'Low-price monthly forecast'!G44) -> 756.00289 | H40: =SUM('Low-price monthly forecast'!H41,'Low-price monthly forecast'!H42,'Low-price monthly forecast'!H43,'Low-price monthly forecast'!H44) -> 864.96278 | I40: =SUM('Low-price monthly forecast'!I41,'Low-price monthly forecast'!I42,'Low-price monthly forecast'!I43,'Low-price monthly forecast'!I44) -> 969.56427 | ... S40: =SUM('Low-price monthly forecast'!S41,'Low-price monthly forecast'!S42,'Low-price monthly forecast'!S43,'Low-price monthly forecast'!S44) -> 1810.9804
A41: Business | B41: ='Low-price monthly forecast'!B21*'Model inputs'!B55 -> 72 | C41: ='Low-price monthly forecast'!C21*'Model inputs'!B55 -> 141.12 | D41: ='Low-price monthly forecast'!D21*'Model inputs'!B55 -> 207.4752 | E41: ='Low-price monthly forecast'!E21*'Model inputs'!B55 -> 271.17619 | F41: ='Low-price monthly forecast'!F21*'Model inputs'!B55 -> 332.32914 | G41: ='Low-price monthly forecast'!G21*'Model inputs'!B55 -> 391.03598 | H41: ='Low-price monthly forecast'!H21*'Model inputs'!B55 -> 447.39454 | I41: ='Low-price monthly forecast'!I21*'Model inputs'!B55 -> 501.49876 | J41: ='Low-price monthly forecast'!J21*'Model inputs'!B55 -> 553.43881 | K41: ='Low-price monthly forecast'!K21*'Model inputs'!B55 -> 603.30126 | L41: ='Low-price monthly forecast'!L21*'Model inputs'!B55 -> 651.16921 | M41: ='Low-price monthly forecast'!M21*'Model inputs'!B55 -> 697.12244 | N41: ='Low-price monthly forecast'!N21*'Model inputs'!B55 -> 741.23754 | O41: ='Low-price monthly forecast'!O21*'Model inputs'!B55 -> 783.58804 | P41: ='Low-price monthly forecast'!P21*'Model inputs'!B55 -> 824.24452 | Q41: ='Low-price monthly forecast'!Q21*'Model inputs'!B55 -> 863.27474 | R41: ='Low-price monthly forecast'!R21*'Model inputs'!B55 -> 900.74375 | S41: ='Low-price monthly forecast'!S21*'Model inputs'!B55 -> 936.714
A42: Community | B42: ='Low-price monthly forecast'!B22*'Model inputs'!B56 -> 0 | C42: ='Low-price monthly forecast'!C22*'Model inputs'!B56 -> 0 | D42: ='Low-price monthly forecast'!D22*'Model inputs'!B56 -> 0 | E42: ='Low-price monthly forecast'!E22*'Model inputs'!B56 -> 0 | F42: ='Low-price monthly forecast'!F22*'Model inputs'!B56 -> 0 | G42: ='Low-price monthly forecast'!G22*'Model inputs'!B56 -> 0 | H42: ='Low-price monthly forecast'!H22*'Model inputs'!B56 -> 0 | I42: ='Low-price monthly forecast'!I22*'Model inputs'!B56 -> 0 | J42: ='Low-price monthly forecast'!J22*'Model inputs'!B56 -> 0 | K42: ='Low-price monthly forecast'!K22*'Model inputs'!B56 -> 0 | L42: ='Low-price monthly forecast'!L22*'Model inputs'!B56 -> 0 | M42: ='Low-price monthly forecast'!M22*'Model inputs'!B56 -> 0 | N42: ='Low-price monthly forecast'!N22*'Model inputs'!B56 -> 0 | O42: ='Low-price monthly forecast'!O22*'Model inputs'!B56 -> 0 | P42: ='Low-price monthly forecast'!P22*'Model inputs'!B56 -> 0 | Q42: ='Low-price monthly forecast'!Q22*'Model inputs'!B56 -> 0 | R42: ='Low-price monthly forecast'!R22*'Model inputs'!B56 -> 0 | S42: ='Low-price monthly forecast'!S22*'Model inputs'!B56 -> 0
A43: Starter | B43: ='Low-price monthly forecast'!B23*'Model inputs'!B57 -> 0 | C43: ='Low-price monthly forecast'!C23*'Model inputs'!B57 -> 0 | D43: ='Low-price monthly forecast'!D23*'Model inputs'!B57 -> 0 | E43: ='Low-price monthly forecast'!E23*'Model inputs'!B57 -> 0 | F43: ='Low-price monthly forecast'!F23*'Model inputs'!B57 -> 0 | G43: ='Low-price monthly forecast'!G23*'Model inputs'!B57 -> 0 | H43: ='Low-price monthly forecast'!H23*'Model inputs'!B57 -> 0 | I43: ='Low-price monthly forecast'!I23*'Model inputs'!B57 -> 0 | J43: ='Low-price monthly forecast'!J23*'Model inputs'!B57 -> 0 | K43: ='Low-price monthly forecast'!K23*'Model inputs'!B57 -> 0 | L43: ='Low-price monthly forecast'!L23*'Model inputs'!B57 -> 0 | M43: ='Low-price monthly forecast'!M23*'Model inputs'!B57 -> 0 | N43: ='Low-price monthly forecast'!N23*'Model inputs'!B57 -> 0 | O43: ='Low-price monthly forecast'!O23*'Model inputs'!B57 -> 0 | P43: ='Low-price monthly forecast'!P23*'Model inputs'!B57 -> 0 | Q43: ='Low-price monthly forecast'!Q23*'Model inputs'!B57 -> 0 | R43: ='Low-price monthly forecast'!R23*'Model inputs'!B57 -> 0 | S43: ='Low-price monthly forecast'!S23*'Model inputs'!B57 -> 0
A44: Team | B44: ='Low-price monthly forecast'!B24*'Model inputs'!B58 -> 67.2 | C44: ='Low-price monthly forecast'!C24*'Model inputs'!B58 -> 131.712 | D44: ='Low-price monthly forecast'!D24*'Model inputs'!B58 -> 193.64352 | E44: ='Low-price monthly forecast'!E24*'Model inputs'!B58 -> 253.09778 | F44: ='Low-price monthly forecast'!F24*'Model inputs'!B58 -> 310.17387 | G44: ='Low-price monthly forecast'!G24*'Model inputs'!B58 -> 364.96691 | H44: ='Low-price monthly forecast'!H24*'Model inputs'!B58 -> 417.56824 | I44: ='Low-price monthly forecast'!I24*'Model inputs'!B58 -> 468.06551 | J44: ='Low-price monthly forecast'!J24*'Model inputs'!B58 -> 516.54289 | K44: ='Low-price monthly forecast'!K24*'Model inputs'!B58 -> 563.08117 | L44: ='Low-price monthly forecast'!L24*'Model inputs'!B58 -> 607.75792 | M44: ='Low-price monthly forecast'!M24*'Model inputs'!B58 -> 650.64761 | N44: ='Low-price monthly forecast'!N24*'Model inputs'!B58 -> 691.8217 | O44: ='Low-price monthly forecast'!O24*'Model inputs'!B58 -> 731.34884 | P44: ='Low-price monthly forecast'!P24*'Model inputs'!B58 -> 769.29488 | Q44: ='Low-price monthly forecast'!Q24*'Model inputs'!B58 -> 805.72309 | R44: ='Low-price monthly forecast'!R24*'Model inputs'!B58 -> 840.69416 | S44: ='Low-price monthly forecast'!S24*'Model inputs'!B58 -> 874.2664
A45: NW Infrastructure delivery cost | B45: =SUM('Low-price monthly forecast'!B46,'Low-price monthly forecast'!B47,'Low-price monthly forecast'!B48,'Low-price monthly forecast'!B49) -> 92.4 | C45: =SUM('Low-price monthly forecast'!C46,'Low-price monthly forecast'!C47,'Low-price monthly forecast'!C48,'Low-price monthly forecast'!C49) -> 181.104 | D45: =SUM('Low-price monthly forecast'!D46,'Low-price monthly forecast'!D47,'Low-price monthly forecast'!D48,'Low-price monthly forecast'!D49) -> 266.25984 | E45: =SUM('Low-price monthly forecast'!E46,'Low-price monthly forecast'!E47,'Low-price monthly forecast'!E48,'Low-price monthly forecast'!E49) -> 348.00945 | F45: =SUM('Low-price monthly forecast'!F46,'Low-price monthly forecast'!F47,'Low-price monthly forecast'!F48,'Low-price monthly forecast'!F49) -> 426.48907 | G45: =SUM('Low-price monthly forecast'!G46,'Low-price monthly forecast'!G47,'Low-price monthly forecast'!G48,'Low-price monthly forecast'!G49) -> 501.82951 | H45: =SUM('Low-price monthly forecast'!H46,'Low-price monthly forecast'!H47,'Low-price monthly forecast'!H48,'Low-price monthly forecast'!H49) -> 574.15633 | I45: =SUM('Low-price monthly forecast'!I46,'Low-price monthly forecast'!I47,'Low-price monthly forecast'!I48,'Low-price monthly forecast'!I49) -> 643.59007 | ... S45: =SUM('Low-price monthly forecast'!S46,'Low-price monthly forecast'!S47,'Low-price monthly forecast'!S48,'Low-price monthly forecast'!S49) -> 1202.1163
A46: Business | B46: ='Low-price monthly forecast'!B21*'Model inputs'!B50 -> 22.4 | C46: ='Low-price monthly forecast'!C21*'Model inputs'!B50 -> 43.904 | D46: ='Low-price monthly forecast'!D21*'Model inputs'!B50 -> 64.54784 | E46: ='Low-price monthly forecast'!E21*'Model inputs'!B50 -> 84.365926 | F46: ='Low-price monthly forecast'!F21*'Model inputs'!B50 -> 103.39129 | G46: ='Low-price monthly forecast'!G21*'Model inputs'!B50 -> 121.65564 | H46: ='Low-price monthly forecast'!H21*'Model inputs'!B50 -> 139.18941 | I46: ='Low-price monthly forecast'!I21*'Model inputs'!B50 -> 156.02184 | J46: ='Low-price monthly forecast'!J21*'Model inputs'!B50 -> 172.18096 | K46: ='Low-price monthly forecast'!K21*'Model inputs'!B50 -> 187.69372 | L46: ='Low-price monthly forecast'!L21*'Model inputs'!B50 -> 202.58597 | M46: ='Low-price monthly forecast'!M21*'Model inputs'!B50 -> 216.88254 | N46: ='Low-price monthly forecast'!N21*'Model inputs'!B50 -> 230.60723 | O46: ='Low-price monthly forecast'!O21*'Model inputs'!B50 -> 243.78295 | P46: ='Low-price monthly forecast'!P21*'Model inputs'!B50 -> 256.43163 | Q46: ='Low-price monthly forecast'!Q21*'Model inputs'!B50 -> 268.57436 | R46: ='Low-price monthly forecast'!R21*'Model inputs'!B50 -> 280.23139 | S46: ='Low-price monthly forecast'!S21*'Model inputs'!B50 -> 291.42213
A47: Community | B47: ='Low-price monthly forecast'!B22*'Model inputs'!B51 -> 0 | C47: ='Low-price monthly forecast'!C22*'Model inputs'!B51 -> 0 | D47: ='Low-price monthly forecast'!D22*'Model inputs'!B51 -> 0 | E47: ='Low-price monthly forecast'!E22*'Model inputs'!B51 -> 0 | F47: ='Low-price monthly forecast'!F22*'Model inputs'!B51 -> 0 | G47: ='Low-price monthly forecast'!G22*'Model inputs'!B51 -> 0 | H47: ='Low-price monthly forecast'!H22*'Model inputs'!B51 -> 0 | I47: ='Low-price monthly forecast'!I22*'Model inputs'!B51 -> 0 | J47: ='Low-price monthly forecast'!J22*'Model inputs'!B51 -> 0 | K47: ='Low-price monthly forecast'!K22*'Model inputs'!B51 -> 0 | L47: ='Low-price monthly forecast'!L22*'Model inputs'!B51 -> 0 | M47: ='Low-price monthly forecast'!M22*'Model inputs'!B51 -> 0 | N47: ='Low-price monthly forecast'!N22*'Model inputs'!B51 -> 0 | O47: ='Low-price monthly forecast'!O22*'Model inputs'!B51 -> 0 | P47: ='Low-price monthly forecast'!P22*'Model inputs'!B51 -> 0 | Q47: ='Low-price monthly forecast'!Q22*'Model inputs'!B51 -> 0 | R47: ='Low-price monthly forecast'!R22*'Model inputs'!B51 -> 0 | S47: ='Low-price monthly forecast'!S22*'Model inputs'!B51 -> 0
A48: Starter | B48: ='Low-price monthly forecast'!B23*'Model inputs'!B52 -> 30.8 | C48: ='Low-price monthly forecast'!C23*'Model inputs'!B52 -> 60.368 | D48: ='Low-price monthly forecast'!D23*'Model inputs'!B52 -> 88.75328 | E48: ='Low-price monthly forecast'!E23*'Model inputs'!B52 -> 116.00315 | F48: ='Low-price monthly forecast'!F23*'Model inputs'!B52 -> 142.16302 | G48: ='Low-price monthly forecast'!G23*'Model inputs'!B52 -> 167.2765 | H48: ='Low-price monthly forecast'!H23*'Model inputs'!B52 -> 191.38544 | I48: ='Low-price monthly forecast'!I23*'Model inputs'!B52 -> 214.53002 | J48: ='Low-price monthly forecast'!J23*'Model inputs'!B52 -> 236.74882 | K48: ='Low-price monthly forecast'!K23*'Model inputs'!B52 -> 258.07887 | L48: ='Low-price monthly forecast'!L23*'Model inputs'!B52 -> 278.55572 | M48: ='Low-price monthly forecast'!M23*'Model inputs'!B52 -> 298.21349 | N48: ='Low-price monthly forecast'!N23*'Model inputs'!B52 -> 317.08495 | O48: ='Low-price monthly forecast'!O23*'Model inputs'!B52 -> 335.20155 | P48: ='Low-price monthly forecast'!P23*'Model inputs'!B52 -> 352.59349 | Q48: ='Low-price monthly forecast'!Q23*'Model inputs'!B52 -> 369.28975 | R48: ='Low-price monthly forecast'!R23*'Model inputs'!B52 -> 385.31816 | S48: ='Low-price monthly forecast'!S23*'Model inputs'!B52 -> 400.70543
A49: Team | B49: ='Low-price monthly forecast'!B24*'Model inputs'!B53 -> 39.2 | C49: ='Low-price monthly forecast'!C24*'Model inputs'!B53 -> 76.832 | D49: ='Low-price monthly forecast'!D24*'Model inputs'!B53 -> 112.95872 | E49: ='Low-price monthly forecast'!E24*'Model inputs'!B53 -> 147.64037 | F49: ='Low-price monthly forecast'!F24*'Model inputs'!B53 -> 180.93476 | G49: ='Low-price monthly forecast'!G24*'Model inputs'!B53 -> 212.89737 | H49: ='Low-price monthly forecast'!H24*'Model inputs'!B53 -> 243.58147 | I49: ='Low-price monthly forecast'!I24*'Model inputs'!B53 -> 273.03821 | J49: ='Low-price monthly forecast'!J24*'Model inputs'!B53 -> 301.31668 | K49: ='Low-price monthly forecast'!K24*'Model inputs'!B53 -> 328.46402 | L49: ='Low-price monthly forecast'!L24*'Model inputs'!B53 -> 354.52546 | M49: ='Low-price monthly forecast'!M24*'Model inputs'!B53 -> 379.54444 | N49: ='Low-price monthly forecast'!N24*'Model inputs'!B53 -> 403.56266 | O49: ='Low-price monthly forecast'!O24*'Model inputs'!B53 -> 426.62015 | P49: ='Low-price monthly forecast'!P24*'Model inputs'!B53 -> 448.75535 | Q49: ='Low-price monthly forecast'!Q24*'Model inputs'!B53 -> 470.00513 | R49: ='Low-price monthly forecast'!R24*'Model inputs'!B53 -> 490.40493 | S49: ='Low-price monthly forecast'!S24*'Model inputs'!B53 -> 509.98873
A50: NW Support delivery cost | B50: =SUM('Low-price monthly forecast'!B51,'Low-price monthly forecast'!B52,'Low-price monthly forecast'!B53,'Low-price monthly forecast'!B54) -> 49.8 | C50: =SUM('Low-price monthly forecast'!C51,'Low-price monthly forecast'!C52,'Low-price monthly forecast'!C53,'Low-price monthly forecast'!C54) -> 97.608 | D50: =SUM('Low-price monthly forecast'!D51,'Low-price monthly forecast'!D52,'Low-price monthly forecast'!D53,'Low-price monthly forecast'!D54) -> 143.50368 | E50: =SUM('Low-price monthly forecast'!E51,'Low-price monthly forecast'!E52,'Low-price monthly forecast'!E53,'Low-price monthly forecast'!E54) -> 187.56353 | F50: =SUM('Low-price monthly forecast'!F51,'Low-price monthly forecast'!F52,'Low-price monthly forecast'!F53,'Low-price monthly forecast'!F54) -> 229.86099 | G50: =SUM('Low-price monthly forecast'!G51,'Low-price monthly forecast'!G52,'Low-price monthly forecast'!G53,'Low-price monthly forecast'!G54) -> 270.46655 | H50: =SUM('Low-price monthly forecast'!H51,'Low-price monthly forecast'!H52,'Low-price monthly forecast'!H53,'Low-price monthly forecast'!H54) -> 309.44789 | I50: =SUM('Low-price monthly forecast'!I51,'Low-price monthly forecast'!I52,'Low-price monthly forecast'!I53,'Low-price monthly forecast'!I54) -> 346.86997 | ... S50: =SUM('Low-price monthly forecast'!S51,'Low-price monthly forecast'!S52,'Low-price monthly forecast'!S53,'Low-price monthly forecast'!S54) -> 647.89385
A51: Business | B51: ='Low-price monthly forecast'!B21*'Model inputs'!B99 -> 20 | C51: ='Low-price monthly forecast'!C21*'Model inputs'!B99 -> 39.2 | D51: ='Low-price monthly forecast'!D21*'Model inputs'!B99 -> 57.632 | E51: ='Low-price monthly forecast'!E21*'Model inputs'!B99 -> 75.32672 | F51: ='Low-price monthly forecast'!F21*'Model inputs'!B99 -> 92.313651 | G51: ='Low-price monthly forecast'!G21*'Model inputs'!B99 -> 108.62111 | H51: ='Low-price monthly forecast'!H21*'Model inputs'!B99 -> 124.27626 | I51: ='Low-price monthly forecast'!I21*'Model inputs'!B99 -> 139.30521 | J51: ='Low-price monthly forecast'!J21*'Model inputs'!B99 -> 153.733 | K51: ='Low-price monthly forecast'!K21*'Model inputs'!B99 -> 167.58368 | L51: ='Low-price monthly forecast'!L21*'Model inputs'!B99 -> 180.88033 | M51: ='Low-price monthly forecast'!M21*'Model inputs'!B99 -> 193.64512 | N51: ='Low-price monthly forecast'!N21*'Model inputs'!B99 -> 205.89932 | O51: ='Low-price monthly forecast'!O21*'Model inputs'!B99 -> 217.66334 | P51: ='Low-price monthly forecast'!P21*'Model inputs'!B99 -> 228.95681 | Q51: ='Low-price monthly forecast'!Q21*'Model inputs'!B99 -> 239.79854 | R51: ='Low-price monthly forecast'!R21*'Model inputs'!B99 -> 250.2066 | S51: ='Low-price monthly forecast'!S21*'Model inputs'!B99 -> 260.19833
A52: Community | B52: ='Low-price monthly forecast'!B22*'Model inputs'!B100 -> 0 | C52: ='Low-price monthly forecast'!C22*'Model inputs'!B100 -> 0 | D52: ='Low-price monthly forecast'!D22*'Model inputs'!B100 -> 0 | E52: ='Low-price monthly forecast'!E22*'Model inputs'!B100 -> 0 | F52: ='Low-price monthly forecast'!F22*'Model inputs'!B100 -> 0 | G52: ='Low-price monthly forecast'!G22*'Model inputs'!B100 -> 0 | H52: ='Low-price monthly forecast'!H22*'Model inputs'!B100 -> 0 | I52: ='Low-price monthly forecast'!I22*'Model inputs'!B100 -> 0 | J52: ='Low-price monthly forecast'!J22*'Model inputs'!B100 -> 0 | K52: ='Low-price monthly forecast'!K22*'Model inputs'!B100 -> 0 | L52: ='Low-price monthly forecast'!L22*'Model inputs'!B100 -> 0 | M52: ='Low-price monthly forecast'!M22*'Model inputs'!B100 -> 0 | N52: ='Low-price monthly forecast'!N22*'Model inputs'!B100 -> 0 | O52: ='Low-price monthly forecast'!O22*'Model inputs'!B100 -> 0 | P52: ='Low-price monthly forecast'!P22*'Model inputs'!B100 -> 0 | Q52: ='Low-price monthly forecast'!Q22*'Model inputs'!B100 -> 0 | R52: ='Low-price monthly forecast'!R22*'Model inputs'!B100 -> 0 | S52: ='Low-price monthly forecast'!S22*'Model inputs'!B100 -> 0
A53: Starter | B53: ='Low-price monthly forecast'!B23*'Model inputs'!B101 -> 8.8 | C53: ='Low-price monthly forecast'!C23*'Model inputs'!B101 -> 17.248 | D53: ='Low-price monthly forecast'!D23*'Model inputs'!B101 -> 25.35808 | E53: ='Low-price monthly forecast'!E23*'Model inputs'!B101 -> 33.143757 | F53: ='Low-price monthly forecast'!F23*'Model inputs'!B101 -> 40.618007 | G53: ='Low-price monthly forecast'!G23*'Model inputs'!B101 -> 47.793286 | H53: ='Low-price monthly forecast'!H23*'Model inputs'!B101 -> 54.681555 | I53: ='Low-price monthly forecast'!I23*'Model inputs'!B101 -> 61.294293 | J53: ='Low-price monthly forecast'!J23*'Model inputs'!B101 -> 67.642521 | K53: ='Low-price monthly forecast'!K23*'Model inputs'!B101 -> 73.73682 | L53: ='Low-price monthly forecast'!L23*'Model inputs'!B101 -> 79.587347 | M53: ='Low-price monthly forecast'!M23*'Model inputs'!B101 -> 85.203853 | N53: ='Low-price monthly forecast'!N23*'Model inputs'!B101 -> 90.595699 | O53: ='Low-price monthly forecast'!O23*'Model inputs'!B101 -> 95.771871 | P53: ='Low-price monthly forecast'!P23*'Model inputs'!B101 -> 100.741 | Q53: ='Low-price monthly forecast'!Q23*'Model inputs'!B101 -> 105.51136 | R53: ='Low-price monthly forecast'!R23*'Model inputs'!B101 -> 110.0909 | S53: ='Low-price monthly forecast'!S23*'Model inputs'!B101 -> 114.48727
A54: Team | B54: ='Low-price monthly forecast'!B24*'Model inputs'!B102 -> 21 | C54: ='Low-price monthly forecast'!C24*'Model inputs'!B102 -> 41.16 | D54: ='Low-price monthly forecast'!D24*'Model inputs'!B102 -> 60.5136 | E54: ='Low-price monthly forecast'!E24*'Model inputs'!B102 -> 79.093056 | F54: ='Low-price monthly forecast'!F24*'Model inputs'!B102 -> 96.929334 | G54: ='Low-price monthly forecast'!G24*'Model inputs'!B102 -> 114.05216 | H54: ='Low-price monthly forecast'!H24*'Model inputs'!B102 -> 130.49007 | I54: ='Low-price monthly forecast'!I24*'Model inputs'!B102 -> 146.27047 | J54: ='Low-price monthly forecast'!J24*'Model inputs'!B102 -> 161.41965 | K54: ='Low-price monthly forecast'!K24*'Model inputs'!B102 -> 175.96287 | L54: ='Low-price monthly forecast'!L24*'Model inputs'!B102 -> 189.92435 | M54: ='Low-price monthly forecast'!M24*'Model inputs'!B102 -> 203.32738 | N54: ='Low-price monthly forecast'!N24*'Model inputs'!B102 -> 216.19428 | O54: ='Low-price monthly forecast'!O24*'Model inputs'!B102 -> 228.54651 | P54: ='Low-price monthly forecast'!P24*'Model inputs'!B102 -> 240.40465 | Q54: ='Low-price monthly forecast'!Q24*'Model inputs'!B102 -> 251.78846 | R54: ='Low-price monthly forecast'!R24*'Model inputs'!B102 -> 262.71693 | S54: ='Low-price monthly forecast'!S24*'Model inputs'!B102 -> 273.20825
A55: NW Payment fees | B55: =SUM('Low-price monthly forecast'!B56,'Low-price monthly forecast'!B57,'Low-price monthly forecast'!B58,'Low-price monthly forecast'!B59) -> 57.7 | C55: =SUM('Low-price monthly forecast'!C56,'Low-price monthly forecast'!C57,'Low-price monthly forecast'!C58,'Low-price monthly forecast'!C59) -> 113.092 | D55: =SUM('Low-price monthly forecast'!D56,'Low-price monthly forecast'!D57,'Low-price monthly forecast'!D58,'Low-price monthly forecast'!D59) -> 166.26832 | E55: =SUM('Low-price monthly forecast'!E56,'Low-price monthly forecast'!E57,'Low-price monthly forecast'!E58,'Low-price monthly forecast'!E59) -> 217.31759 | F55: =SUM('Low-price monthly forecast'!F56,'Low-price monthly forecast'!F57,'Low-price monthly forecast'!F58,'Low-price monthly forecast'!F59) -> 266.32488 | G55: =SUM('Low-price monthly forecast'!G56,'Low-price monthly forecast'!G57,'Low-price monthly forecast'!G58,'Low-price monthly forecast'!G59) -> 313.37189 | H55: =SUM('Low-price monthly forecast'!H56,'Low-price monthly forecast'!H57,'Low-price monthly forecast'!H58,'Low-price monthly forecast'!H59) -> 358.53701 | I55: =SUM('Low-price monthly forecast'!I56,'Low-price monthly forecast'!I57,'Low-price monthly forecast'!I58,'Low-price monthly forecast'!I59) -> 401.89553 | ... S55: =SUM('Low-price monthly forecast'!S56,'Low-price monthly forecast'!S57,'Low-price monthly forecast'!S58,'Low-price monthly forecast'!S59) -> 750.67219
A56: Business | B56: ='Low-price monthly forecast'!B21*'Model inputs'!B27 -> 31.2 | C56: ='Low-price monthly forecast'!C21*'Model inputs'!B27 -> 61.152 | D56: ='Low-price monthly forecast'!D21*'Model inputs'!B27 -> 89.90592 | E56: ='Low-price monthly forecast'!E21*'Model inputs'!B27 -> 117.50968 | F56: ='Low-price monthly forecast'!F21*'Model inputs'!B27 -> 144.0093 | G56: ='Low-price monthly forecast'!G21*'Model inputs'!B27 -> 169.44892 | H56: ='Low-price monthly forecast'!H21*'Model inputs'!B27 -> 193.87097 | I56: ='Low-price monthly forecast'!I21*'Model inputs'!B27 -> 217.31613 | J56: ='Low-price monthly forecast'!J21*'Model inputs'!B27 -> 239.82348 | K56: ='Low-price monthly forecast'!K21*'Model inputs'!B27 -> 261.43054 | L56: ='Low-price monthly forecast'!L21*'Model inputs'!B27 -> 282.17332 | M56: ='Low-price monthly forecast'!M21*'Model inputs'!B27 -> 302.08639 | N56: ='Low-price monthly forecast'!N21*'Model inputs'!B27 -> 321.20293 | O56: ='Low-price monthly forecast'!O21*'Model inputs'!B27 -> 339.55482 | P56: ='Low-price monthly forecast'!P21*'Model inputs'!B27 -> 357.17262 | Q56: ='Low-price monthly forecast'!Q21*'Model inputs'!B27 -> 374.08572 | R56: ='Low-price monthly forecast'!R21*'Model inputs'!B27 -> 390.32229 | S56: ='Low-price monthly forecast'!S21*'Model inputs'!B27 -> 405.9094
A57: Community | B57: ='Low-price monthly forecast'!B22*'Model inputs'!B28 -> 0 | C57: ='Low-price monthly forecast'!C22*'Model inputs'!B28 -> 0 | D57: ='Low-price monthly forecast'!D22*'Model inputs'!B28 -> 0 | E57: ='Low-price monthly forecast'!E22*'Model inputs'!B28 -> 0 | F57: ='Low-price monthly forecast'!F22*'Model inputs'!B28 -> 0 | G57: ='Low-price monthly forecast'!G22*'Model inputs'!B28 -> 0 | H57: ='Low-price monthly forecast'!H22*'Model inputs'!B28 -> 0 | I57: ='Low-price monthly forecast'!I22*'Model inputs'!B28 -> 0 | J57: ='Low-price monthly forecast'!J22*'Model inputs'!B28 -> 0 | K57: ='Low-price monthly forecast'!K22*'Model inputs'!B28 -> 0 | L57: ='Low-price monthly forecast'!L22*'Model inputs'!B28 -> 0 | M57: ='Low-price monthly forecast'!M22*'Model inputs'!B28 -> 0 | N57: ='Low-price monthly forecast'!N22*'Model inputs'!B28 -> 0 | O57: ='Low-price monthly forecast'!O22*'Model inputs'!B28 -> 0 | P57: ='Low-price monthly forecast'!P22*'Model inputs'!B28 -> 0 | Q57: ='Low-price monthly forecast'!Q22*'Model inputs'!B28 -> 0 | R57: ='Low-price monthly forecast'!R22*'Model inputs'!B28 -> 0 | S57: ='Low-price monthly forecast'!S22*'Model inputs'!B28 -> 0
A58: Starter | B58: ='Low-price monthly forecast'!B23*'Model inputs'!B29 -> 5.5 | C58: ='Low-price monthly forecast'!C23*'Model inputs'!B29 -> 10.78 | D58: ='Low-price monthly forecast'!D23*'Model inputs'!B29 -> 15.8488 | E58: ='Low-price monthly forecast'!E23*'Model inputs'!B29 -> 20.714848 | F58: ='Low-price monthly forecast'!F23*'Model inputs'!B29 -> 25.386254 | G58: ='Low-price monthly forecast'!G23*'Model inputs'!B29 -> 29.870804 | H58: ='Low-price monthly forecast'!H23*'Model inputs'!B29 -> 34.175972 | I58: ='Low-price monthly forecast'!I23*'Model inputs'!B29 -> 38.308933 | J58: ='Low-price monthly forecast'!J23*'Model inputs'!B29 -> 42.276576 | K58: ='Low-price monthly forecast'!K23*'Model inputs'!B29 -> 46.085513 | L58: ='Low-price monthly forecast'!L23*'Model inputs'!B29 -> 49.742092 | M58: ='Low-price monthly forecast'!M23*'Model inputs'!B29 -> 53.252408 | N58: ='Low-price monthly forecast'!N23*'Model inputs'!B29 -> 56.622312 | O58: ='Low-price monthly forecast'!O23*'Model inputs'!B29 -> 59.85742 | P58: ='Low-price monthly forecast'!P23*'Model inputs'!B29 -> 62.963123 | Q58: ='Low-price monthly forecast'!Q23*'Model inputs'!B29 -> 65.944598 | R58: ='Low-price monthly forecast'!R23*'Model inputs'!B29 -> 68.806814 | S58: ='Low-price monthly forecast'!S23*'Model inputs'!B29 -> 71.554541
A59: Team | B59: ='Low-price monthly forecast'!B24*'Model inputs'!B30 -> 21 | C59: ='Low-price monthly forecast'!C24*'Model inputs'!B30 -> 41.16 | D59: ='Low-price monthly forecast'!D24*'Model inputs'!B30 -> 60.5136 | E59: ='Low-price monthly forecast'!E24*'Model inputs'!B30 -> 79.093056 | F59: ='Low-price monthly forecast'!F24*'Model inputs'!B30 -> 96.929334 | G59: ='Low-price monthly forecast'!G24*'Model inputs'!B30 -> 114.05216 | H59: ='Low-price monthly forecast'!H24*'Model inputs'!B30 -> 130.49007 | I59: ='Low-price monthly forecast'!I24*'Model inputs'!B30 -> 146.27047 | J59: ='Low-price monthly forecast'!J24*'Model inputs'!B30 -> 161.41965 | K59: ='Low-price monthly forecast'!K24*'Model inputs'!B30 -> 175.96287 | L59: ='Low-price monthly forecast'!L24*'Model inputs'!B30 -> 189.92435 | M59: ='Low-price monthly forecast'!M24*'Model inputs'!B30 -> 203.32738 | N59: ='Low-price monthly forecast'!N24*'Model inputs'!B30 -> 216.19428 | O59: ='Low-price monthly forecast'!O24*'Model inputs'!B30 -> 228.54651 | P59: ='Low-price monthly forecast'!P24*'Model inputs'!B30 -> 240.40465 | Q59: ='Low-price monthly forecast'!Q24*'Model inputs'!B30 -> 251.78846 | R59: ='Low-price monthly forecast'!R24*'Model inputs'!B30 -> 262.71693 | S59: ='Low-price monthly forecast'!S24*'Model inputs'!B30 -> 273.20825
A60: NW Cost of revenue | B60: =SUM('Low-price monthly forecast'!B61,'Low-price monthly forecast'!B62,'Low-price monthly forecast'!B63,'Low-price monthly forecast'!B64) -> 339.1 | C60: =SUM('Low-price monthly forecast'!C61,'Low-price monthly forecast'!C62,'Low-price monthly forecast'!C63,'Low-price monthly forecast'!C64) -> 664.636 | D60: =SUM('Low-price monthly forecast'!D61,'Low-price monthly forecast'!D62,'Low-price monthly forecast'!D63,'Low-price monthly forecast'!D64) -> 977.15056 | E60: =SUM('Low-price monthly forecast'!E61,'Low-price monthly forecast'!E62,'Low-price monthly forecast'!E63,'Low-price monthly forecast'!E64) -> 1277.1645 | F60: =SUM('Low-price monthly forecast'!F61,'Low-price monthly forecast'!F62,'Low-price monthly forecast'!F63,'Low-price monthly forecast'!F64) -> 1565.178 | G60: =SUM('Low-price monthly forecast'!G61,'Low-price monthly forecast'!G62,'Low-price monthly forecast'!G63,'Low-price monthly forecast'!G64) -> 1841.6708 | H60: =SUM('Low-price monthly forecast'!H61,'Low-price monthly forecast'!H62,'Low-price monthly forecast'!H63,'Low-price monthly forecast'!H64) -> 2107.104 | I60: =SUM('Low-price monthly forecast'!I61,'Low-price monthly forecast'!I62,'Low-price monthly forecast'!I63,'Low-price monthly forecast'!I64) -> 2361.9198 | ... S60: =SUM('Low-price monthly forecast'!S61,'Low-price monthly forecast'!S62,'Low-price monthly forecast'!S63,'Low-price monthly forecast'!S64) -> 4411.6627
A61: Business | B61: ='Low-price monthly forecast'!B21*'Model inputs'!B17 -> 145.6 | C61: ='Low-price monthly forecast'!C21*'Model inputs'!B17 -> 285.376 | D61: ='Low-price monthly forecast'!D21*'Model inputs'!B17 -> 419.56096 | E61: ='Low-price monthly forecast'!E21*'Model inputs'!B17 -> 548.37852 | F61: ='Low-price monthly forecast'!F21*'Model inputs'!B17 -> 672.04338 | G61: ='Low-price monthly forecast'!G21*'Model inputs'!B17 -> 790.76165 | H61: ='Low-price monthly forecast'!H21*'Model inputs'!B17 -> 904.73118 | I61: ='Low-price monthly forecast'!I21*'Model inputs'!B17 -> 1014.1419 | J61: ='Low-price monthly forecast'!J21*'Model inputs'!B17 -> 1119.1763 | K61: ='Low-price monthly forecast'!K21*'Model inputs'!B17 -> 1220.0092 | L61: ='Low-price monthly forecast'!L21*'Model inputs'!B17 -> 1316.8088 | M61: ='Low-price monthly forecast'!M21*'Model inputs'!B17 -> 1409.7365 | N61: ='Low-price monthly forecast'!N21*'Model inputs'!B17 -> 1498.947 | O61: ='Low-price monthly forecast'!O21*'Model inputs'!B17 -> 1584.5891 | P61: ='Low-price monthly forecast'!P21*'Model inputs'!B17 -> 1666.8056 | Q61: ='Low-price monthly forecast'!Q21*'Model inputs'!B17 -> 1745.7334 | R61: ='Low-price monthly forecast'!R21*'Model inputs'!B17 -> 1821.504 | S61: ='Low-price monthly forecast'!S21*'Model inputs'!B17 -> 1894.2439
A62: Community | B62: ='Low-price monthly forecast'!B22*'Model inputs'!B18 -> 0 | C62: ='Low-price monthly forecast'!C22*'Model inputs'!B18 -> 0 | D62: ='Low-price monthly forecast'!D22*'Model inputs'!B18 -> 0 | E62: ='Low-price monthly forecast'!E22*'Model inputs'!B18 -> 0 | F62: ='Low-price monthly forecast'!F22*'Model inputs'!B18 -> 0 | G62: ='Low-price monthly forecast'!G22*'Model inputs'!B18 -> 0 | H62: ='Low-price monthly forecast'!H22*'Model inputs'!B18 -> 0 | I62: ='Low-price monthly forecast'!I22*'Model inputs'!B18 -> 0 | J62: ='Low-price monthly forecast'!J22*'Model inputs'!B18 -> 0 | K62: ='Low-price monthly forecast'!K22*'Model inputs'!B18 -> 0 | L62: ='Low-price monthly forecast'!L22*'Model inputs'!B18 -> 0 | M62: ='Low-price monthly forecast'!M22*'Model inputs'!B18 -> 0 | N62: ='Low-price monthly forecast'!N22*'Model inputs'!B18 -> 0 | O62: ='Low-price monthly forecast'!O22*'Model inputs'!B18 -> 0 | P62: ='Low-price monthly forecast'!P22*'Model inputs'!B18 -> 0 | Q62: ='Low-price monthly forecast'!Q22*'Model inputs'!B18 -> 0 | R62: ='Low-price monthly forecast'!R22*'Model inputs'!B18 -> 0 | S62: ='Low-price monthly forecast'!S22*'Model inputs'!B18 -> 0
A63: Starter | B63: ='Low-price monthly forecast'!B23*'Model inputs'!B19 -> 45.1 | C63: ='Low-price monthly forecast'!C23*'Model inputs'!B19 -> 88.396 | D63: ='Low-price monthly forecast'!D23*'Model inputs'!B19 -> 129.96016 | E63: ='Low-price monthly forecast'!E23*'Model inputs'!B19 -> 169.86175 | F63: ='Low-price monthly forecast'!F23*'Model inputs'!B19 -> 208.16728 | G63: ='Low-price monthly forecast'!G23*'Model inputs'!B19 -> 244.94059 | H63: ='Low-price monthly forecast'!H23*'Model inputs'!B19 -> 280.24297 | I63: ='Low-price monthly forecast'!I23*'Model inputs'!B19 -> 314.13325 | J63: ='Low-price monthly forecast'!J23*'Model inputs'!B19 -> 346.66792 | K63: ='Low-price monthly forecast'!K23*'Model inputs'!B19 -> 377.9012 | L63: ='Low-price monthly forecast'!L23*'Model inputs'!B19 -> 407.88515 | M63: ='Low-price monthly forecast'!M23*'Model inputs'!B19 -> 436.66975 | N63: ='Low-price monthly forecast'!N23*'Model inputs'!B19 -> 464.30296 | O63: ='Low-price monthly forecast'!O23*'Model inputs'!B19 -> 490.83084 | P63: ='Low-price monthly forecast'!P23*'Model inputs'!B19 -> 516.29761 | Q63: ='Low-price monthly forecast'!Q23*'Model inputs'!B19 -> 540.7457 | R63: ='Low-price monthly forecast'!R23*'Model inputs'!B19 -> 564.21587 | S63: ='Low-price monthly forecast'!S23*'Model inputs'!B19 -> 586.74724
A64: Team | B64: ='Low-price monthly forecast'!B24*'Model inputs'!B20 -> 148.4 | C64: ='Low-price monthly forecast'!C24*'Model inputs'!B20 -> 290.864 | D64: ='Low-price monthly forecast'!D24*'Model inputs'!B20 -> 427.62944 | E64: ='Low-price monthly forecast'!E24*'Model inputs'!B20 -> 558.92426 | F64: ='Low-price monthly forecast'!F24*'Model inputs'!B20 -> 684.96729 | G64: ='Low-price monthly forecast'!G24*'Model inputs'!B20 -> 805.9686 | H64: ='Low-price monthly forecast'!H24*'Model inputs'!B20 -> 922.12986 | I64: ='Low-price monthly forecast'!I24*'Model inputs'!B20 -> 1033.6447 | J64: ='Low-price monthly forecast'!J24*'Model inputs'!B20 -> 1140.6989 | K64: ='Low-price monthly forecast'!K24*'Model inputs'!B20 -> 1243.4709 | L64: ='Low-price monthly forecast'!L24*'Model inputs'!B20 -> 1342.1321 | M64: ='Low-price monthly forecast'!M24*'Model inputs'!B20 -> 1436.8468 | N64: ='Low-price monthly forecast'!N24*'Model inputs'!B20 -> 1527.7729 | O64: ='Low-price monthly forecast'!O24*'Model inputs'!B20 -> 1615.062 | P64: ='Low-price monthly forecast'!P24*'Model inputs'!B20 -> 1698.8595 | Q64: ='Low-price monthly forecast'!Q24*'Model inputs'!B20 -> 1779.3051 | R64: ='Low-price monthly forecast'!R24*'Model inputs'!B20 -> 1856.5329 | S64: ='Low-price monthly forecast'!S24*'Model inputs'!B20 -> 1930.6716
A65: NW Gross profit | B65: =SUM('Low-price monthly forecast'!B66,'Low-price monthly forecast'!B67,'Low-price monthly forecast'!B68,'Low-price monthly forecast'!B69) -> 814.9 | C65: =SUM('Low-price monthly forecast'!C66,'Low-price monthly forecast'!C67,'Low-price monthly forecast'!C68,'Low-price monthly forecast'!C69) -> 1597.204 | D65: =SUM('Low-price monthly forecast'!D66,'Low-price monthly forecast'!D67,'Low-price monthly forecast'!D68,'Low-price monthly forecast'!D69) -> 2348.2158 | E65: =SUM('Low-price monthly forecast'!E66,'Low-price monthly forecast'!E67,'Low-price monthly forecast'!E68,'Low-price monthly forecast'!E69) -> 3069.1872 | F65: =SUM('Low-price monthly forecast'!F66,'Low-price monthly forecast'!F67,'Low-price monthly forecast'!F68,'Low-price monthly forecast'!F69) -> 3761.3197 | G65: =SUM('Low-price monthly forecast'!G66,'Low-price monthly forecast'!G67,'Low-price monthly forecast'!G68,'Low-price monthly forecast'!G69) -> 4425.7669 | H65: =SUM('Low-price monthly forecast'!H66,'Low-price monthly forecast'!H67,'Low-price monthly forecast'!H68,'Low-price monthly forecast'!H69) -> 5063.6363 | I65: =SUM('Low-price monthly forecast'!I66,'Low-price monthly forecast'!I67,'Low-price monthly forecast'!I68,'Low-price monthly forecast'!I69) -> 5675.9908 | ... S65: =SUM('Low-price monthly forecast'!S66,'Low-price monthly forecast'!S67,'Low-price monthly forecast'!S68,'Low-price monthly forecast'!S69) -> 10601.781
A66: Business | B66: ='Low-price monthly forecast'!B21*'Model inputs'!B40 -> 478.4 | C66: ='Low-price monthly forecast'!C21*'Model inputs'!B40 -> 937.664 | D66: ='Low-price monthly forecast'!D21*'Model inputs'!B40 -> 1378.5574 | E66: ='Low-price monthly forecast'!E21*'Model inputs'!B40 -> 1801.8151 | F66: ='Low-price monthly forecast'!F21*'Model inputs'!B40 -> 2208.1425 | G66: ='Low-price monthly forecast'!G21*'Model inputs'!B40 -> 2598.2168 | H66: ='Low-price monthly forecast'!H21*'Model inputs'!B40 -> 2972.6882 | I66: ='Low-price monthly forecast'!I21*'Model inputs'!B40 -> 3332.1806 | J66: ='Low-price monthly forecast'!J21*'Model inputs'!B40 -> 3677.2934 | K66: ='Low-price monthly forecast'!K21*'Model inputs'!B40 -> 4008.6017 | L66: ='Low-price monthly forecast'!L21*'Model inputs'!B40 -> 4326.6576 | M66: ='Low-price monthly forecast'!M21*'Model inputs'!B40 -> 4631.9913 | N66: ='Low-price monthly forecast'!N21*'Model inputs'!B40 -> 4925.1117 | O66: ='Low-price monthly forecast'!O21*'Model inputs'!B40 -> 5206.5072 | P66: ='Low-price monthly forecast'!P21*'Model inputs'!B40 -> 5476.6469 | Q66: ='Low-price monthly forecast'!Q21*'Model inputs'!B40 -> 5735.981 | R66: ='Low-price monthly forecast'!R21*'Model inputs'!B40 -> 5984.9418 | S66: ='Low-price monthly forecast'!S21*'Model inputs'!B40 -> 6223.9441
A67: Community | B67: ='Low-price monthly forecast'!B22*'Model inputs'!B41 -> 0 | C67: ='Low-price monthly forecast'!C22*'Model inputs'!B41 -> 0 | D67: ='Low-price monthly forecast'!D22*'Model inputs'!B41 -> 0 | E67: ='Low-price monthly forecast'!E22*'Model inputs'!B41 -> 0 | F67: ='Low-price monthly forecast'!F22*'Model inputs'!B41 -> 0 | G67: ='Low-price monthly forecast'!G22*'Model inputs'!B41 -> 0 | H67: ='Low-price monthly forecast'!H22*'Model inputs'!B41 -> 0 | I67: ='Low-price monthly forecast'!I22*'Model inputs'!B41 -> 0 | J67: ='Low-price monthly forecast'!J22*'Model inputs'!B41 -> 0 | K67: ='Low-price monthly forecast'!K22*'Model inputs'!B41 -> 0 | L67: ='Low-price monthly forecast'!L22*'Model inputs'!B41 -> 0 | M67: ='Low-price monthly forecast'!M22*'Model inputs'!B41 -> 0 | N67: ='Low-price monthly forecast'!N22*'Model inputs'!B41 -> 0 | O67: ='Low-price monthly forecast'!O22*'Model inputs'!B41 -> 0 | P67: ='Low-price monthly forecast'!P22*'Model inputs'!B41 -> 0 | Q67: ='Low-price monthly forecast'!Q22*'Model inputs'!B41 -> 0 | R67: ='Low-price monthly forecast'!R22*'Model inputs'!B41 -> 0 | S67: ='Low-price monthly forecast'!S22*'Model inputs'!B41 -> 0
A68: Starter | B68: ='Low-price monthly forecast'!B23*'Model inputs'!B42 -> 64.9 | C68: ='Low-price monthly forecast'!C23*'Model inputs'!B42 -> 127.204 | D68: ='Low-price monthly forecast'!D23*'Model inputs'!B42 -> 187.01584 | E68: ='Low-price monthly forecast'!E23*'Model inputs'!B42 -> 244.43521 | F68: ='Low-price monthly forecast'!F23*'Model inputs'!B42 -> 299.5578 | G68: ='Low-price monthly forecast'!G23*'Model inputs'!B42 -> 352.47549 | H68: ='Low-price monthly forecast'!H23*'Model inputs'!B42 -> 403.27647 | I68: ='Low-price monthly forecast'!I23*'Model inputs'!B42 -> 452.04541 | J68: ='Low-price monthly forecast'!J23*'Model inputs'!B42 -> 498.86359 | K68: ='Low-price monthly forecast'!K23*'Model inputs'!B42 -> 543.80905 | L68: ='Low-price monthly forecast'!L23*'Model inputs'!B42 -> 586.95669 | M68: ='Low-price monthly forecast'!M23*'Model inputs'!B42 -> 628.37842 | N68: ='Low-price monthly forecast'!N23*'Model inputs'!B42 -> 668.14328 | O68: ='Low-price monthly forecast'!O23*'Model inputs'!B42 -> 706.31755 | P68: ='Low-price monthly forecast'!P23*'Model inputs'!B42 -> 742.96485 | Q68: ='Low-price monthly forecast'!Q23*'Model inputs'!B42 -> 778.14625 | R68: ='Low-price monthly forecast'!R23*'Model inputs'!B42 -> 811.9204 | S68: ='Low-price monthly forecast'!S23*'Model inputs'!B42 -> 844.34359
A69: Team | B69: ='Low-price monthly forecast'!B24*'Model inputs'!B43 -> 271.6 | C69: ='Low-price monthly forecast'!C24*'Model inputs'!B43 -> 532.336 | D69: ='Low-price monthly forecast'!D24*'Model inputs'!B43 -> 782.64256 | E69: ='Low-price monthly forecast'!E24*'Model inputs'!B43 -> 1022.9369 | F69: ='Low-price monthly forecast'!F24*'Model inputs'!B43 -> 1253.6194 | G69: ='Low-price monthly forecast'!G24*'Model inputs'!B43 -> 1475.0746 | H69: ='Low-price monthly forecast'!H24*'Model inputs'!B43 -> 1687.6716 | I69: ='Low-price monthly forecast'!I24*'Model inputs'!B43 -> 1891.7648 | J69: ='Low-price monthly forecast'!J24*'Model inputs'!B43 -> 2087.6942 | K69: ='Low-price monthly forecast'!K24*'Model inputs'!B43 -> 2275.7864 | L69: ='Low-price monthly forecast'!L24*'Model inputs'!B43 -> 2456.3549 | M69: ='Low-price monthly forecast'!M24*'Model inputs'!B43 -> 2629.7007 | N69: ='Low-price monthly forecast'!N24*'Model inputs'!B43 -> 2796.1127 | O69: ='Low-price monthly forecast'!O24*'Model inputs'!B43 -> 2955.8682 | P69: ='Low-price monthly forecast'!P24*'Model inputs'!B43 -> 3109.2335 | Q69: ='Low-price monthly forecast'!Q24*'Model inputs'!B43 -> 3256.4641 | R69: ='Low-price monthly forecast'!R24*'Model inputs'!B43 -> 3397.8056 | S69: ='Low-price monthly forecast'!S24*'Model inputs'!B43 -> 3533.4934
A70: NW Gross margin | B70: =IFERROR('Low-price monthly forecast'!B65/'Low-price monthly forecast'!B35,"") -> 0.70615251 | C70: =IFERROR('Low-price monthly forecast'!C65/'Low-price monthly forecast'!C35,"") -> 0.70615251 | D70: =IFERROR('Low-price monthly forecast'!D65/'Low-price monthly forecast'!D35,"") -> 0.70615251 | E70: =IFERROR('Low-price monthly forecast'!E65/'Low-price monthly forecast'!E35,"") -> 0.70615251 | F70: =IFERROR('Low-price monthly forecast'!F65/'Low-price monthly forecast'!F35,"") -> 0.70615251 | G70: =IFERROR('Low-price monthly forecast'!G65/'Low-price monthly forecast'!G35,"") -> 0.70615251 | H70: =IFERROR('Low-price monthly forecast'!H65/'Low-price monthly forecast'!H35,"") -> 0.70615251 | I70: =IFERROR('Low-price monthly forecast'!I65/'Low-price monthly forecast'!I35,"") -> 0.70615251 | ... S70: =IFERROR('Low-price monthly forecast'!S65/'Low-price monthly forecast'!S35,"") -> 0.70615251
A71: NW Fixed expenses | B71: =IF('Model inputs'!B32="","",'Model inputs'!B32) -> 4050 | C71: =IF('Model inputs'!B32="","",'Model inputs'!B32) -> 4050 | D71: =IF('Model inputs'!B32="","",'Model inputs'!B32) -> 4050 | E71: =IF('Model inputs'!B32="","",'Model inputs'!B32) -> 4050 | F71: =IF('Model inputs'!B32="","",'Model inputs'!B32) -> 4050 | G71: =IF('Model inputs'!B32="","",'Model inputs'!B32) -> 4050 | H71: =IF('Model inputs'!B32="","",'Model inputs'!B32) -> 4050 | I71: =IF('Model inputs'!B32="","",'Model inputs'!B32) -> 4050 | J71: =IF('Model inputs'!B32="","",'Model inputs'!B32) -> 4050 | K71: =IF('Model inputs'!B32="","",'Model inputs'!B32) -> 4050 | L71: =IF('Model inputs'!B32="","",'Model inputs'!B32) -> 4050 | M71: =IF('Model inputs'!B32="","",'Model inputs'!B32) -> 4050 | N71: =IF('Model inputs'!B32="","",'Model inputs'!B32) -> 4050 | O71: =IF('Model inputs'!B32="","",'Model inputs'!B32) -> 4050 | P71: =IF('Model inputs'!B32="","",'Model inputs'!B32) -> 4050 | Q71: =IF('Model inputs'!B32="","",'Model inputs'!B32) -> 4050 | R71: =IF('Model inputs'!B32="","",'Model inputs'!B32) -> 4050 | S71: =IF('Model inputs'!B32="","",'Model inputs'!B32) -> 4050
A72: NW Acquisition expenses | B72: =IF('Model inputs'!B8="","",'Model inputs'!B8) -> 600 | C72: =IF('Model inputs'!B8="","",'Model inputs'!B8) -> 600 | D72: =IF('Model inputs'!B8="","",'Model inputs'!B8) -> 600 | E72: =IF('Model inputs'!B8="","",'Model inputs'!B8) -> 600 | F72: =IF('Model inputs'!B8="","",'Model inputs'!B8) -> 600 | G72: =IF('Model inputs'!B8="","",'Model inputs'!B8) -> 600 | H72: =IF('Model inputs'!B8="","",'Model inputs'!B8) -> 600 | I72: =IF('Model inputs'!B8="","",'Model inputs'!B8) -> 600 | J72: =IF('Model inputs'!B8="","",'Model inputs'!B8) -> 600 | K72: =IF('Model inputs'!B8="","",'Model inputs'!B8) -> 600 | L72: =IF('Model inputs'!B8="","",'Model inputs'!B8) -> 600 | M72: =IF('Model inputs'!B8="","",'Model inputs'!B8) -> 600 | N72: =IF('Model inputs'!B8="","",'Model inputs'!B8) -> 600 | O72: =IF('Model inputs'!B8="","",'Model inputs'!B8) -> 600 | P72: =IF('Model inputs'!B8="","",'Model inputs'!B8) -> 600 | Q72: =IF('Model inputs'!B8="","",'Model inputs'!B8) -> 600 | R72: =IF('Model inputs'!B8="","",'Model inputs'!B8) -> 600 | S72: =IF('Model inputs'!B8="","",'Model inputs'!B8) -> 600
A73: NW Operating profit | B73: ='Low-price monthly forecast'!B65-'Low-price monthly forecast'!B71-'Low-price monthly forecast'!B72 -> -3835.1 | C73: ='Low-price monthly forecast'!C65-'Low-price monthly forecast'!C71-'Low-price monthly forecast'!C72 -> -3052.796 | D73: ='Low-price monthly forecast'!D65-'Low-price monthly forecast'!D71-'Low-price monthly forecast'!D72 -> -2301.7842 | E73: ='Low-price monthly forecast'!E65-'Low-price monthly forecast'!E71-'Low-price monthly forecast'!E72 -> -1580.8128 | F73: ='Low-price monthly forecast'!F65-'Low-price monthly forecast'!F71-'Low-price monthly forecast'!F72 -> -888.68028 | G73: ='Low-price monthly forecast'!G65-'Low-price monthly forecast'!G71-'Low-price monthly forecast'!G72 -> -224.23307 | H73: ='Low-price monthly forecast'!H65-'Low-price monthly forecast'!H71-'Low-price monthly forecast'!H72 -> 413.63625 | I73: ='Low-price monthly forecast'!I65-'Low-price monthly forecast'!I71-'Low-price monthly forecast'!I72 -> 1025.9908 | ... S73: ='Low-price monthly forecast'!S65-'Low-price monthly forecast'!S71-'Low-price monthly forecast'!S72 -> 5951.7811
A74: NW Cash balance | B74: =IF(IF(IF(IF(ISERROR(DATE(2026,10,1)='Model inputs'!B33),DATE(2026,10,1)='Model inputs'!B33,IF('Model inputs'!B33="","",DATE(2026,10,1)='Model inputs'!B33))="",FALSE,IF(ISERROR(DATE(2026,10,1)='Model inputs'!B33),DATE(2026,10,1)='Model inputs'!B33,IF('Model inputs'!B33="","",DATE(2026,10,1)='Model inputs'!B33))),IF('Model inputs'!B90="","",'Model inputs'!B90),IF('Model inputs'!K15="","",'Model inputs'!K15))="",0,IF(IF(IF(ISERROR(DATE(2026,10,1)='Model inputs'!B33),DATE(2026,10,1)='Model inputs'!B33,IF('Model inputs'!B33="","",DATE(2026,10,1)='Model inputs'!B33))="",FALSE,IF(ISERROR(DATE(2026,10,1)='Model inputs'!B33),DATE(2026,10,1)='Model inputs'!B33,IF('Model inputs'!B33="","",DATE(2026,10,1)='Model inputs'!B33))),IF('Model inputs'!B90="","",'Model inputs'!B90),IF('Model inputs'!K15="","",'Model inputs'!K15)))+'Low-price monthly forecast'!B73 -> 11164.9 | C74: =IF(IF(IF(IF(ISERROR(DATE(2026,11,1)='Model inputs'!B33),DATE(2026,11,1)='Model inputs'!B33,IF('Model inputs'!B33="","",DATE(2026,11,1)='Model inputs'!B33))="",FALSE,IF(ISERROR(DATE(2026,11,1)='Model inputs'!B33),DATE(2026,11,1)='Model inputs'!B33,IF('Model inputs'!B33="","",DATE(2026,11,1)='Model inputs'!B33))),IF('Model inputs'!B90="","",'Model inputs'!B90),IF('Low-price monthly forecast'!B74="","",'Low-price monthly forecast'!B74))="",0,IF(IF(IF(ISERROR(DATE(2026,11,1)='Model inputs'!B33),DATE(2026,11,1)='Model inputs'!B33,IF('Model inputs'!B33="","",DATE(2026,11,1)='Model inputs'!B33))="",FALSE,IF(ISERROR(DATE(2026,11,1)='Model inputs'!B33),DATE(2026,11,1)='Model inputs'!B33,IF('Model inputs'!B33="","",DATE(2026,11,1)='Model inputs'!B33))),IF('Model inputs'!B90="","",'Model inputs'!B90),IF('Low-price monthly forecast'!B74="","",'Low-price monthly forecast'!B74)))+'Low-price monthly forecast'!C73 -> 8112.104 | D74: =IF(IF(IF(IF(ISERROR(DATE(2026,12,1)='Model inputs'!B33),DATE(2026,12,1)='Model inputs'!B33,IF('Model inputs'!B33="","",DATE(2026,12,1)='Model inputs'!B33))="",FALSE,IF(ISERROR(DATE(2026,12,1)='Model inputs'!B33),DATE(2026,12,1)='Model inputs'!B33,IF('Model inputs'!B33="","",DATE(2026,12,1)='Model inputs'!B33))),IF('Model inputs'!B90="","",'Model inputs'!B90),IF('Low-price monthly forecast'!C74="","",'Low-price monthly forecast'!C74))="",0,IF(IF(IF(ISERROR(DATE(2026,12,1)='Model inputs'!B33),DATE(2026,12,1)='Model inputs'!B33,IF('Model inputs'!B33="","",DATE(2026,12,1)='Model inputs'!B33))="",FALSE,IF(ISERROR(DATE(2026,12,1)='Model inputs'!B33),DATE(2026,12,1)='Model inputs'!B33,IF('Model inputs'!B33="","",DATE(2026,12,1)='Model inputs'!B33))),IF('Model inputs'!B90="","",'Model inputs'!B90),IF('Low-price monthly forecast'!C74="","",'Low-price monthly forecast'!C74)))+'Low-price monthly forecast'!D73 -> 5810.3198 | E74: =IF(IF(IF(IF(ISERROR(DATE(2027,1,1)='Model inputs'!B33),DATE(2027,1,1)='Model inputs'!B33,IF('Model inputs'!B33="","",DATE(2027,1,1)='Model inputs'!B33))="",FALSE,IF(ISERROR(DATE(2027,1,1)='Model inputs'!B33),DATE(2027,1,1)='Model inputs'!B33,IF('Model inputs'!B33="","",DATE(2027,1,1)='Model inputs'!B33))),IF('Model inputs'!B90="","",'Model inputs'!B90),IF('Low-price monthly forecast'!D74="","",'Low-price monthly forecast'!D74))="",0,IF(IF(IF(ISERROR(DATE(2027,1,1)='Model inputs'!B33),DATE(2027,1,1)='Model inputs'!B33,IF('Model inputs'!B33="","",DATE(2027,1,1)='Model inputs'!B33))="",FALSE,IF(ISERROR(DATE(2027,1,1)='Model inputs'!B33),DATE(2027,1,1)='Model inputs'!B33,IF('Model inputs'!B33="","",DATE(2027,1,1)='Model inputs'!B33))),IF('Model inputs'!B90="","",'Model inputs'!B90),IF('Low-price monthly forecast'!D74="","",'Low-price monthly forecast'!D74)))+'Low-price monthly forecast'!E73 -> 4229.507 | F74: =IF(IF(IF(IF(ISERROR(DATE(2027,2,1)='Model inputs'!B33),DATE(2027,2,1)='Model inputs'!B33,IF('Model inputs'!B33="","",DATE(2027,2,1)='Model inputs'!B33))="",FALSE,IF(ISERROR(DATE(2027,2,1)='Model inputs'!B33),DATE(2027,2,1)='Model inputs'!B33,IF('Model inputs'!B33="","",DATE(2027,2,1)='Model inputs'!B33))),IF('Model inputs'!B90="","",'Model inputs'!B90),IF('Low-price monthly forecast'!E74="","",'Low-price monthly forecast'!E74))="",0,IF(IF(IF(ISERROR(DATE(2027,2,1)='Model inputs'!B33),DATE(2027,2,1)='Model inputs'!B33,IF('Model inputs'!B33="","",DATE(2027,2,1)='Model inputs'!B33))="",FALSE,IF(ISERROR(DATE(2027,2,1)='Model inputs'!B33),DATE(2027,2,1)='Model inputs'!B33,IF('Model inputs'!B33="","",DATE(2027,2,1)='Model inputs'!B33))),IF('Model inputs'!B90="","",'Model inputs'!B90),IF('Low-price monthly forecast'!E74="","",'Low-price monthly forecast'!E74)))+'Low-price monthly forecast'!F73 -> 3340.8268 | G74: =IF(IF(IF(IF(ISERROR(DATE(2027,3,1)='Model inputs'!B33),DATE(2027,3,1)='Model inputs'!B33,IF('Model inputs'!B33="","",DATE(2027,3,1)='Model inputs'!B33))="",FALSE,IF(ISERROR(DATE(2027,3,1)='Model inputs'!B33),DATE(2027,3,1)='Model inputs'!B33,IF('Model inputs'!B33="","",DATE(2027,3,1)='Model inputs'!B33))),IF('Model inputs'!B90="","",'Model inputs'!B90),IF('Low-price monthly forecast'!F74="","",'Low-price monthly forecast'!F74))="",0,IF(IF(IF(ISERROR(DATE(2027,3,1)='Model inputs'!B33),DATE(2027,3,1)='Model inputs'!B33,IF('Model inputs'!B33="","",DATE(2027,3,1)='Model inputs'!B33))="",FALSE,IF(ISERROR(DATE(2027,3,1)='Model inputs'!B33),DATE(2027,3,1)='Model inputs'!B33,IF('Model inputs'!B33="","",DATE(2027,3,1)='Model inputs'!B33))),IF('Model inputs'!B90="","",'Model inputs'!B90),IF('Low-price monthly forecast'!F74="","",'Low-price monthly forecast'!F74)))+'Low-price monthly forecast'!G73 -> 3116.5937 | H74: =IF(IF(IF(IF(ISERROR(DATE(2027,4,1)='Model inputs'!B33),DATE(2027,4,1)='Model inputs'!B33,IF('Model inputs'!B33="","",DATE(2027,4,1)='Model inputs'!B33))="",FALSE,IF(ISERROR(DATE(2027,4,1)='Model inputs'!B33),DATE(2027,4,1)='Model inputs'!B33,IF('Model inputs'!B33="","",DATE(2027,4,1)='Model inputs'!B33))),IF('Model inputs'!B90="","",'Model inputs'!B90),IF('Low-price monthly forecast'!G74="","",'Low-price monthly forecast'!G74))="",0,IF(IF(IF(ISERROR(DATE(2027,4,1)='Model inputs'!B33),DATE(2027,4,1)='Model inputs'!B33,IF('Model inputs'!B33="","",DATE(2027,4,1)='Model inputs'!B33))="",FALSE,IF(ISERROR(DATE(2027,4,1)='Model inputs'!B33),DATE(2027,4,1)='Model inputs'!B33,IF('Model inputs'!B33="","",DATE(2027,4,1)='Model inputs'!B33))),IF('Model inputs'!B90="","",'Model inputs'!B90),IF('Low-price monthly forecast'!G74="","",'Low-price monthly forecast'!G74)))+'Low-price monthly forecast'!H73 -> 3530.2299 | I74: =IF(IF(IF(IF(ISERROR(DATE(2027,5,1)='Model inputs'!B33),DATE(2027,5,1)='Model inputs'!B33,IF('Model inputs'!B33="","",DATE(2027,5,1)='Model inputs'!B33))="",FALSE,IF(ISERROR(DATE(2027,5,1)='Model inputs'!B33),DATE(2027,5,1)='Model inputs'!B33,IF('Model inputs'!B33="","",DATE(2027,5,1)='Model inputs'!B33))),IF('Model inputs'!B90="","",'Model inputs'!B90),IF('Low-price monthly forecast'!H74="","",'Low-price monthly forecast'!H74))="",0,IF(IF(IF(ISERROR(DATE(2027,5,1)='Model inputs'!B33),DATE(2027,5,1)='Model inputs'!B33,IF('Model inputs'!B33="","",DATE(2027,5,1)='Model inputs'!B33))="",FALSE,IF(ISERROR(DATE(2027,5,1)='Model inputs'!B33),DATE(2027,5,1)='Model inputs'!B33,IF('Model inputs'!B33="","",DATE(2027,5,1)='Model inputs'!B33))),IF('Model inputs'!B90="","",'Model inputs'!B90),IF('Low-price monthly forecast'!H74="","",'Low-price monthly forecast'!H74)))+'Low-price monthly forecast'!I73 -> 4556.2207 | J74: =IF(IF(IF(IF(ISERROR(DATE(2027,6,1)='Model inputs'!B33),DATE(2027,6,1)='Model inputs'!B33,IF('Model inputs'!B33="","",DATE(2027,6,1)='Model inputs'!B33))="",FALSE,IF(ISERROR(DATE(2027,6,1)='Model inputs'!B33),DATE(2027,6,1)='Model inputs'!B33,IF('Model inputs'!B33="","",DATE(2027,6,1)='Model inputs'!B33))),IF('Model inputs'!B90="","",'Model inputs'!B90),IF('Low-price monthly forecast'!I74="","",'Low-price monthly forecast'!I74))="",0,IF(IF(IF(ISERROR(DATE(2027,6,1)='Model inputs'!B33),DATE(2027,6,1)='Model inputs'!B33,IF('Model inputs'!B33="","",DATE(2027,6,1)='Model inputs'!B33))="",FALSE,IF(ISERROR(DATE(2027,6,1)='Model inputs'!B33),DATE(2027,6,1)='Model inputs'!B33,IF('Model inputs'!B33="","",DATE(2027,6,1)='Model inputs'!B33))),IF('Model inputs'!B90="","",'Model inputs'!B90),IF('Low-price monthly forecast'!I74="","",'Low-price monthly forecast'!I74)))+'Low-price monthly forecast'!J73 -> 6170.0719 | K74: =IF(IF(IF(IF(ISERROR(DATE(2027,7,1)='Model inputs'!B33),DATE(2027,7,1)='Model inputs'!B33,IF('Model inputs'!B33="","",DATE(2027,7,1)='Model inputs'!B33))="",FALSE,IF(ISERROR(DATE(2027,7,1)='Model inputs'!B33),DATE(2027,7,1)='Model inputs'!B33,IF('Model inputs'!B33="","",DATE(2027,7,1)='Model inputs'!B33))),IF('Model inputs'!B90="","",'Model inputs'!B90),IF('Low-price monthly forecast'!J74="","",'Low-price monthly forecast'!J74))="",0,IF(IF(IF(ISERROR(DATE(2027,7,1)='Model inputs'!B33),DATE(2027,7,1)='Model inputs'!B33,IF('Model inputs'!B33="","",DATE(2027,7,1)='Model inputs'!B33))="",FALSE,IF(ISERROR(DATE(2027,7,1)='Model inputs'!B33),DATE(2027,7,1)='Model inputs'!B33,IF('Model inputs'!B33="","",DATE(2027,7,1)='Model inputs'!B33))),IF('Model inputs'!B90="","",'Model inputs'!B90),IF('Low-price monthly forecast'!J74="","",'Low-price monthly forecast'!J74)))+'Low-price monthly forecast'!K73 -> 8348.269 | L74: =IF(IF(IF(IF(ISERROR(DATE(2027,8,1)='Model inputs'!B33),DATE(2027,8,1)='Model inputs'!B33,IF('Model inputs'!B33="","",DATE(2027,8,1)='Model inputs'!B33))="",FALSE,IF(ISERROR(DATE(2027,8,1)='Model inputs'!B33),DATE(2027,8,1)='Model inputs'!B33,IF('Model inputs'!B33="","",DATE(2027,8,1)='Model inputs'!B33))),IF('Model inputs'!B90="","",'Model inputs'!B90),IF('Low-price monthly forecast'!K74="","",'Low-price monthly forecast'!K74))="",0,IF(IF(IF(ISERROR(DATE(2027,8,1)='Model inputs'!B33),DATE(2027,8,1)='Model inputs'!B33,IF('Model inputs'!B33="","",DATE(2027,8,1)='Model inputs'!B33))="",FALSE,IF(ISERROR(DATE(2027,8,1)='Model inputs'!B33),DATE(2027,8,1)='Model inputs'!B33,IF('Model inputs'!B33="","",DATE(2027,8,1)='Model inputs'!B33))),IF('Model inputs'!B90="","",'Model inputs'!B90),IF('Low-price monthly forecast'!K74="","",'Low-price monthly forecast'!K74)))+'Low-price monthly forecast'!L73 -> 11068.238 | M74: =IF(IF(IF(IF(ISERROR(DATE(2027,9,1)='Model inputs'!B33),DATE(2027,9,1)='Model inputs'!B33,IF('Model inputs'!B33="","",DATE(2027,9,1)='Model inputs'!B33))="",FALSE,IF(ISERROR(DATE(2027,9,1)='Model inputs'!B33),DATE(2027,9,1)='Model inputs'!B33,IF('Model inputs'!B33="","",DATE(2027,9,1)='Model inputs'!B33))),IF('Model inputs'!B90="","",'Model inputs'!B90),IF('Low-price monthly forecast'!L74="","",'Low-price monthly forecast'!L74))="",0,IF(IF(IF(ISERROR(DATE(2027,9,1)='Model inputs'!B33),DATE(2027,9,1)='Model inputs'!B33,IF('Model inputs'!B33="","",DATE(2027,9,1)='Model inputs'!B33))="",FALSE,IF(ISERROR(DATE(2027,9,1)='Model inputs'!B33),DATE(2027,9,1)='Model inputs'!B33,IF('Model inputs'!B33="","",DATE(2027,9,1)='Model inputs'!B33))),IF('Model inputs'!B90="","",'Model inputs'!B90),IF('Low-price monthly forecast'!L74="","",'Low-price monthly forecast'!L74)))+'Low-price monthly forecast'!M73 -> 14308.309 | N74: =IF(IF(IF(IF(ISERROR(DATE(2027,10,1)='Model inputs'!B33),DATE(2027,10,1)='Model inputs'!B33,IF('Model inputs'!B33="","",DATE(2027,10,1)='Model inputs'!B33))="",FALSE,IF(ISERROR(DATE(2027,10,1)='Model inputs'!B33),DATE(2027,10,1)='Model inputs'!B33,IF('Model inputs'!B33="","",DATE(2027,10,1)='Model inputs'!B33))),IF('Model inputs'!B90="","",'Model inputs'!B90),IF('Low-price monthly forecast'!M74="","",'Low-price monthly forecast'!M74))="",0,IF(IF(IF(ISERROR(DATE(2027,10,1)='Model inputs'!B33),DATE(2027,10,1)='Model inputs'!B33,IF('Model inputs'!B33="","",DATE(2027,10,1)='Model inputs'!B33))="",FALSE,IF(ISERROR(DATE(2027,10,1)='Model inputs'!B33),DATE(2027,10,1)='Model inputs'!B33,IF('Model inputs'!B33="","",DATE(2027,10,1)='Model inputs'!B33))),IF('Model inputs'!B90="","",'Model inputs'!B90),IF('Low-price monthly forecast'!M74="","",'Low-price monthly forecast'!M74)))+'Low-price monthly forecast'!N73 -> 18047.676 | O74: =IF(IF(IF(IF(ISERROR(DATE(2027,11,1)='Model inputs'!B33),DATE(2027,11,1)='Model inputs'!B33,IF('Model inputs'!B33="","",DATE(2027,11,1)='Model inputs'!B33))="",FALSE,IF(ISERROR(DATE(2027,11,1)='Model inputs'!B33),DATE(2027,11,1)='Model inputs'!B33,IF('Model inputs'!B33="","",DATE(2027,11,1)='Model inputs'!B33))),IF('Model inputs'!B90="","",'Model inputs'!B90),IF('Low-price monthly forecast'!N74="","",'Low-price monthly forecast'!N74))="",0,IF(IF(IF(ISERROR(DATE(2027,11,1)='Model inputs'!B33),DATE(2027,11,1)='Model inputs'!B33,IF('Model inputs'!B33="","",DATE(2027,11,1)='Model inputs'!B33))="",FALSE,IF(ISERROR(DATE(2027,11,1)='Model inputs'!B33),DATE(2027,11,1)='Model inputs'!B33,IF('Model inputs'!B33="","",DATE(2027,11,1)='Model inputs'!B33))),IF('Model inputs'!B90="","",'Model inputs'!B90),IF('Low-price monthly forecast'!N74="","",'Low-price monthly forecast'!N74)))+'Low-price monthly forecast'!O73 -> 22266.369 | P74: =IF(IF(IF(IF(ISERROR(DATE(2027,12,1)='Model inputs'!B33),DATE(2027,12,1)='Model inputs'!B33,IF('Model inputs'!B33="","",DATE(2027,12,1)='Model inputs'!B33))="",FALSE,IF(ISERROR(DATE(2027,12,1)='Model inputs'!B33),DATE(2027,12,1)='Model inputs'!B33,IF('Model inputs'!B33="","",DATE(2027,12,1)='Model inputs'!B33))),IF('Model inputs'!B90="","",'Model inputs'!B90),IF('Low-price monthly forecast'!O74="","",'Low-price monthly forecast'!O74))="",0,IF(IF(IF(ISERROR(DATE(2027,12,1)='Model inputs'!B33),DATE(2027,12,1)='Model inputs'!B33,IF('Model inputs'!B33="","",DATE(2027,12,1)='Model inputs'!B33))="",FALSE,IF(ISERROR(DATE(2027,12,1)='Model inputs'!B33),DATE(2027,12,1)='Model inputs'!B33,IF('Model inputs'!B33="","",DATE(2027,12,1)='Model inputs'!B33))),IF('Model inputs'!B90="","",'Model inputs'!B90),IF('Low-price monthly forecast'!O74="","",'Low-price monthly forecast'!O74)))+'Low-price monthly forecast'!P73 -> 26945.215 | Q74: =IF(IF(IF(IF(ISERROR(DATE(2028,1,1)='Model inputs'!B33),DATE(2028,1,1)='Model inputs'!B33,IF('Model inputs'!B33="","",DATE(2028,1,1)='Model inputs'!B33))="",FALSE,IF(ISERROR(DATE(2028,1,1)='Model inputs'!B33),DATE(2028,1,1)='Model inputs'!B33,IF('Model inputs'!B33="","",DATE(2028,1,1)='Model inputs'!B33))),IF('Model inputs'!B90="","",'Model inputs'!B90),IF('Low-price monthly forecast'!P74="","",'Low-price monthly forecast'!P74))="",0,IF(IF(IF(ISERROR(DATE(2028,1,1)='Model inputs'!B33),DATE(2028,1,1)='Model inputs'!B33,IF('Model inputs'!B33="","",DATE(2028,1,1)='Model inputs'!B33))="",FALSE,IF(ISERROR(DATE(2028,1,1)='Model inputs'!B33),DATE(2028,1,1)='Model inputs'!B33,IF('Model inputs'!B33="","",DATE(2028,1,1)='Model inputs'!B33))),IF('Model inputs'!B90="","",'Model inputs'!B90),IF('Low-price monthly forecast'!P74="","",'Low-price monthly forecast'!P74)))+'Low-price monthly forecast'!Q73 -> 32065.806 | R74: =IF(IF(IF(IF(ISERROR(DATE(2028,2,1)='Model inputs'!B33),DATE(2028,2,1)='Model inputs'!B33,IF('Model inputs'!B33="","",DATE(2028,2,1)='Model inputs'!B33))="",FALSE,IF(ISERROR(DATE(2028,2,1)='Model inputs'!B33),DATE(2028,2,1)='Model inputs'!B33,IF('Model inputs'!B33="","",DATE(2028,2,1)='Model inputs'!B33))),IF('Model inputs'!B90="","",'Model inputs'!B90),IF('Low-price monthly forecast'!Q74="","",'Low-price monthly forecast'!Q74))="",0,IF(IF(IF(ISERROR(DATE(2028,2,1)='Model inputs'!B33),DATE(2028,2,1)='Model inputs'!B33,IF('Model inputs'!B33="","",DATE(2028,2,1)='Model inputs'!B33))="",FALSE,IF(ISERROR(DATE(2028,2,1)='Model inputs'!B33),DATE(2028,2,1)='Model inputs'!B33,IF('Model inputs'!B33="","",DATE(2028,2,1)='Model inputs'!B33))),IF('Model inputs'!B90="","",'Model inputs'!B90),IF('Low-price monthly forecast'!Q74="","",'Low-price monthly forecast'!Q74)))+'Low-price monthly forecast'!R73 -> 37610.474 | S74: =IF(IF(IF(IF(ISERROR(DATE(2028,3,1)='Model inputs'!B33),DATE(2028,3,1)='Model inputs'!B33,IF('Model inputs'!B33="","",DATE(2028,3,1)='Model inputs'!B33))="",FALSE,IF(ISERROR(DATE(2028,3,1)='Model inputs'!B33),DATE(2028,3,1)='Model inputs'!B33,IF('Model inputs'!B33="","",DATE(2028,3,1)='Model inputs'!B33))),IF('Model inputs'!B90="","",'Model inputs'!B90),IF('Low-price monthly forecast'!R74="","",'Low-price monthly forecast'!R74))="",0,IF(IF(IF(ISERROR(DATE(2028,3,1)='Model inputs'!B33),DATE(2028,3,1)='Model inputs'!B33,IF('Model inputs'!B33="","",DATE(2028,3,1)='Model inputs'!B33))="",FALSE,IF(ISERROR(DATE(2028,3,1)='Model inputs'!B33),DATE(2028,3,1)='Model inputs'!B33,IF('Model inputs'!B33="","",DATE(2028,3,1)='Model inputs'!B33))),IF('Model inputs'!B90="","",'Model inputs'!B90),IF('Low-price monthly forecast'!R74="","",'Low-price monthly forecast'!R74)))+'Low-price monthly forecast'!S73 -> 43562.255
A75: NW Higher-price revenue | B75: ='Low-price monthly forecast'!B20*'Model inputs'!B45 -> 1266 | C75: ='Low-price monthly forecast'!C20*'Model inputs'!B45 -> 2481.36 | D75: ='Low-price monthly forecast'!D20*'Model inputs'!B45 -> 3648.1056 | E75: ='Low-price monthly forecast'!E20*'Model inputs'!B45 -> 4768.1814 | F75: ='Low-price monthly forecast'!F20*'Model inputs'!B45 -> 5843.4541 | G75: ='Low-price monthly forecast'!G20*'Model inputs'!B45 -> 6875.716 | H75: ='Low-price monthly forecast'!H20*'Model inputs'!B45 -> 7866.6873 | I75: ='Low-price monthly forecast'!I20*'Model inputs'!B45 -> 8818.0198 | J75: ='Low-price monthly forecast'!J20*'Model inputs'!B45 -> 9731.299 | K75: ='Low-price monthly forecast'!K20*'Model inputs'!B45 -> 10608.047 | L75: ='Low-price monthly forecast'!L20*'Model inputs'!B45 -> 11449.725 | M75: ='Low-price monthly forecast'!M20*'Model inputs'!B45 -> 12257.736 | N75: ='Low-price monthly forecast'!N20*'Model inputs'!B45 -> 13033.427 | O75: ='Low-price monthly forecast'!O20*'Model inputs'!B45 -> 13778.09 | P75: ='Low-price monthly forecast'!P20*'Model inputs'!B45 -> 14492.966 | Q75: ='Low-price monthly forecast'!Q20*'Model inputs'!B45 -> 15179.247 | R75: ='Low-price monthly forecast'!R20*'Model inputs'!B45 -> 15838.078 | S75: ='Low-price monthly forecast'!S20*'Model inputs'!B45 -> 16470.554
A76: NW Higher-price gross profit | B76: ='Low-price monthly forecast'!B20*'Model inputs'!B44 -> 921.3 | C76: ='Low-price monthly forecast'!C20*'Model inputs'!B44 -> 1805.748 | D76: ='Low-price monthly forecast'!D20*'Model inputs'!B44 -> 2654.8181 | E76: ='Low-price monthly forecast'!E20*'Model inputs'!B44 -> 3469.9254 | F76: ='Low-price monthly forecast'!F20*'Model inputs'!B44 -> 4252.4283 | G76: ='Low-price monthly forecast'!G20*'Model inputs'!B44 -> 5003.6312 | H76: ='Low-price monthly forecast'!H20*'Model inputs'!B44 -> 5724.786 | I76: ='Low-price monthly forecast'!I20*'Model inputs'!B44 -> 6417.0945 | J76: ='Low-price monthly forecast'!J20*'Model inputs'!B44 -> 7081.7107 | K76: ='Low-price monthly forecast'!K20*'Model inputs'!B44 -> 7719.7423 | L76: ='Low-price monthly forecast'!L20*'Model inputs'!B44 -> 8332.2526 | M76: ='Low-price monthly forecast'!M20*'Model inputs'!B44 -> 8920.2625 | N76: ='Low-price monthly forecast'!N20*'Model inputs'!B44 -> 9484.752 | O76: ='Low-price monthly forecast'!O20*'Model inputs'!B44 -> 10026.662 | P76: ='Low-price monthly forecast'!P20*'Model inputs'!B44 -> 10546.895 | Q76: ='Low-price monthly forecast'!Q20*'Model inputs'!B44 -> 11046.32 | R76: ='Low-price monthly forecast'!R20*'Model inputs'!B44 -> 11525.767 | S76: ='Low-price monthly forecast'!S20*'Model inputs'!B44 -> 11986.036
A77: NW Higher-price gross margin | B77: =IFERROR('Low-price monthly forecast'!B76/'Low-price monthly forecast'!B75,"") -> 0.72772512 | C77: =IFERROR('Low-price monthly forecast'!C76/'Low-price monthly forecast'!C75,"") -> 0.72772512 | D77: =IFERROR('Low-price monthly forecast'!D76/'Low-price monthly forecast'!D75,"") -> 0.72772512 | E77: =IFERROR('Low-price monthly forecast'!E76/'Low-price monthly forecast'!E75,"") -> 0.72772512 | F77: =IFERROR('Low-price monthly forecast'!F76/'Low-price monthly forecast'!F75,"") -> 0.72772512 | G77: =IFERROR('Low-price monthly forecast'!G76/'Low-price monthly forecast'!G75,"") -> 0.72772512 | H77: =IFERROR('Low-price monthly forecast'!H76/'Low-price monthly forecast'!H75,"") -> 0.72772512 | I77: =IFERROR('Low-price monthly forecast'!I76/'Low-price monthly forecast'!I75,"") -> 0.72772512 | ... S77: =IFERROR('Low-price monthly forecast'!S76/'Low-price monthly forecast'!S75,"") -> 0.72772512
A78: NW Higher-price operating profit | B78: ='Low-price monthly forecast'!B76-'Low-price monthly forecast'!B71-'Low-price monthly forecast'!B72 -> -3728.7 | C78: ='Low-price monthly forecast'!C76-'Low-price monthly forecast'!C71-'Low-price monthly forecast'!C72 -> -2844.252 | D78: ='Low-price monthly forecast'!D76-'Low-price monthly forecast'!D71-'Low-price monthly forecast'!D72 -> -1995.1819 | E78: ='Low-price monthly forecast'!E76-'Low-price monthly forecast'!E71-'Low-price monthly forecast'!E72 -> -1180.0746 | F78: ='Low-price monthly forecast'!F76-'Low-price monthly forecast'!F71-'Low-price monthly forecast'!F72 -> -397.57166 | G78: ='Low-price monthly forecast'!G76-'Low-price monthly forecast'!G71-'Low-price monthly forecast'!G72 -> 353.63121 | H78: ='Low-price monthly forecast'!H76-'Low-price monthly forecast'!H71-'Low-price monthly forecast'!H72 -> 1074.786 | I78: ='Low-price monthly forecast'!I76-'Low-price monthly forecast'!I71-'Low-price monthly forecast'!I72 -> 1767.0945 | ... S78: ='Low-price monthly forecast'!S76-'Low-price monthly forecast'!S71-'Low-price monthly forecast'!S72 -> 7336.0362
A79: NW Higher-price cash balance | B79: =IF(IF(IF(IF(ISERROR(DATE(2026,10,1)='Model inputs'!B33),DATE(2026,10,1)='Model inputs'!B33,IF('Model inputs'!B33="","",DATE(2026,10,1)='Model inputs'!B33))="",FALSE,IF(ISERROR(DATE(2026,10,1)='Model inputs'!B33),DATE(2026,10,1)='Model inputs'!B33,IF('Model inputs'!B33="","",DATE(2026,10,1)='Model inputs'!B33))),IF('Model inputs'!B90="","",'Model inputs'!B90),IF('Model inputs'!K46="","",'Model inputs'!K46))="",0,IF(IF(IF(ISERROR(DATE(2026,10,1)='Model inputs'!B33),DATE(2026,10,1)='Model inputs'!B33,IF('Model inputs'!B33="","",DATE(2026,10,1)='Model inputs'!B33))="",FALSE,IF(ISERROR(DATE(2026,10,1)='Model inputs'!B33),DATE(2026,10,1)='Model inputs'!B33,IF('Model inputs'!B33="","",DATE(2026,10,1)='Model inputs'!B33))),IF('Model inputs'!B90="","",'Model inputs'!B90),IF('Model inputs'!K46="","",'Model inputs'!K46)))+'Low-price monthly forecast'!B78 -> 11271.3 | C79: =IF(IF(IF(IF(ISERROR(DATE(2026,11,1)='Model inputs'!B33),DATE(2026,11,1)='Model inputs'!B33,IF('Model inputs'!B33="","",DATE(2026,11,1)='Model inputs'!B33))="",FALSE,IF(ISERROR(DATE(2026,11,1)='Model inputs'!B33),DATE(2026,11,1)='Model inputs'!B33,IF('Model inputs'!B33="","",DATE(2026,11,1)='Model inputs'!B33))),IF('Model inputs'!B90="","",'Model inputs'!B90),IF('Low-price monthly forecast'!B79="","",'Low-price monthly forecast'!B79))="",0,IF(IF(IF(ISERROR(DATE(2026,11,1)='Model inputs'!B33),DATE(2026,11,1)='Model inputs'!B33,IF('Model inputs'!B33="","",DATE(2026,11,1)='Model inputs'!B33))="",FALSE,IF(ISERROR(DATE(2026,11,1)='Model inputs'!B33),DATE(2026,11,1)='Model inputs'!B33,IF('Model inputs'!B33="","",DATE(2026,11,1)='Model inputs'!B33))),IF('Model inputs'!B90="","",'Model inputs'!B90),IF('Low-price monthly forecast'!B79="","",'Low-price monthly forecast'!B79)))+'Low-price monthly forecast'!C78 -> 8427.048 | D79: =IF(IF(IF(IF(ISERROR(DATE(2026,12,1)='Model inputs'!B33),DATE(2026,12,1)='Model inputs'!B33,IF('Model inputs'!B33="","",DATE(2026,12,1)='Model inputs'!B33))="",FALSE,IF(ISERROR(DATE(2026,12,1)='Model inputs'!B33),DATE(2026,12,1)='Model inputs'!B33,IF('Model inputs'!B33="","",DATE(2026,12,1)='Model inputs'!B33))),IF('Model inputs'!B90="","",'Model inputs'!B90),IF('Low-price monthly forecast'!C79="","",'Low-price monthly forecast'!C79))="",0,IF(IF(IF(ISERROR(DATE(2026,12,1)='Model inputs'!B33),DATE(2026,12,1)='Model inputs'!B33,IF('Model inputs'!B33="","",DATE(2026,12,1)='Model inputs'!B33))="",FALSE,IF(ISERROR(DATE(2026,12,1)='Model inputs'!B33),DATE(2026,12,1)='Model inputs'!B33,IF('Model inputs'!B33="","",DATE(2026,12,1)='Model inputs'!B33))),IF('Model inputs'!B90="","",'Model inputs'!B90),IF('Low-price monthly forecast'!C79="","",'Low-price monthly forecast'!C79)))+'Low-price monthly forecast'!D78 -> 6431.8661 | E79: =IF(IF(IF(IF(ISERROR(DATE(2027,1,1)='Model inputs'!B33),DATE(2027,1,1)='Model inputs'!B33,IF('Model inputs'!B33="","",DATE(2027,1,1)='Model inputs'!B33))="",FALSE,IF(ISERROR(DATE(2027,1,1)='Model inputs'!B33),DATE(2027,1,1)='Model inputs'!B33,IF('Model inputs'!B33="","",DATE(2027,1,1)='Model inputs'!B33))),IF('Model inputs'!B90="","",'Model inputs'!B90),IF('Low-price monthly forecast'!D79="","",'Low-price monthly forecast'!D79))="",0,IF(IF(IF(ISERROR(DATE(2027,1,1)='Model inputs'!B33),DATE(2027,1,1)='Model inputs'!B33,IF('Model inputs'!B33="","",DATE(2027,1,1)='Model inputs'!B33))="",FALSE,IF(ISERROR(DATE(2027,1,1)='Model inputs'!B33),DATE(2027,1,1)='Model inputs'!B33,IF('Model inputs'!B33="","",DATE(2027,1,1)='Model inputs'!B33))),IF('Model inputs'!B90="","",'Model inputs'!B90),IF('Low-price monthly forecast'!D79="","",'Low-price monthly forecast'!D79)))+'Low-price monthly forecast'!E78 -> 5251.7914 | F79: =IF(IF(IF(IF(ISERROR(DATE(2027,2,1)='Model inputs'!B33),DATE(2027,2,1)='Model inputs'!B33,IF('Model inputs'!B33="","",DATE(2027,2,1)='Model inputs'!B33))="",FALSE,IF(ISERROR(DATE(2027,2,1)='Model inputs'!B33),DATE(2027,2,1)='Model inputs'!B33,IF('Model inputs'!B33="","",DATE(2027,2,1)='Model inputs'!B33))),IF('Model inputs'!B90="","",'Model inputs'!B90),IF('Low-price monthly forecast'!E79="","",'Low-price monthly forecast'!E79))="",0,IF(IF(IF(ISERROR(DATE(2027,2,1)='Model inputs'!B33),DATE(2027,2,1)='Model inputs'!B33,IF('Model inputs'!B33="","",DATE(2027,2,1)='Model inputs'!B33))="",FALSE,IF(ISERROR(DATE(2027,2,1)='Model inputs'!B33),DATE(2027,2,1)='Model inputs'!B33,IF('Model inputs'!B33="","",DATE(2027,2,1)='Model inputs'!B33))),IF('Model inputs'!B90="","",'Model inputs'!B90),IF('Low-price monthly forecast'!E79="","",'Low-price monthly forecast'!E79)))+'Low-price monthly forecast'!F78 -> 4854.2198 | G79: =IF(IF(IF(IF(ISERROR(DATE(2027,3,1)='Model inputs'!B33),DATE(2027,3,1)='Model inputs'!B33,IF('Model inputs'!B33="","",DATE(2027,3,1)='Model inputs'!B33))="",FALSE,IF(ISERROR(DATE(2027,3,1)='Model inputs'!B33),DATE(2027,3,1)='Model inputs'!B33,IF('Model inputs'!B33="","",DATE(2027,3,1)='Model inputs'!B33))),IF('Model inputs'!B90="","",'Model inputs'!B90),IF('Low-price monthly forecast'!F79="","",'Low-price monthly forecast'!F79))="",0,IF(IF(IF(ISERROR(DATE(2027,3,1)='Model inputs'!B33),DATE(2027,3,1)='Model inputs'!B33,IF('Model inputs'!B33="","",DATE(2027,3,1)='Model inputs'!B33))="",FALSE,IF(ISERROR(DATE(2027,3,1)='Model inputs'!B33),DATE(2027,3,1)='Model inputs'!B33,IF('Model inputs'!B33="","",DATE(2027,3,1)='Model inputs'!B33))),IF('Model inputs'!B90="","",'Model inputs'!B90),IF('Low-price monthly forecast'!F79="","",'Low-price monthly forecast'!F79)))+'Low-price monthly forecast'!G78 -> 5207.851 | H79: =IF(IF(IF(IF(ISERROR(DATE(2027,4,1)='Model inputs'!B33),DATE(2027,4,1)='Model inputs'!B33,IF('Model inputs'!B33="","",DATE(2027,4,1)='Model inputs'!B33))="",FALSE,IF(ISERROR(DATE(2027,4,1)='Model inputs'!B33),DATE(2027,4,1)='Model inputs'!B33,IF('Model inputs'!B33="","",DATE(2027,4,1)='Model inputs'!B33))),IF('Model inputs'!B90="","",'Model inputs'!B90),IF('Low-price monthly forecast'!G79="","",'Low-price monthly forecast'!G79))="",0,IF(IF(IF(ISERROR(DATE(2027,4,1)='Model inputs'!B33),DATE(2027,4,1)='Model inputs'!B33,IF('Model inputs'!B33="","",DATE(2027,4,1)='Model inputs'!B33))="",FALSE,IF(ISERROR(DATE(2027,4,1)='Model inputs'!B33),DATE(2027,4,1)='Model inputs'!B33,IF('Model inputs'!B33="","",DATE(2027,4,1)='Model inputs'!B33))),IF('Model inputs'!B90="","",'Model inputs'!B90),IF('Low-price monthly forecast'!G79="","",'Low-price monthly forecast'!G79)))+'Low-price monthly forecast'!H78 -> 6282.6369 | I79: =IF(IF(IF(IF(ISERROR(DATE(2027,5,1)='Model inputs'!B33),DATE(2027,5,1)='Model inputs'!B33,IF('Model inputs'!B33="","",DATE(2027,5,1)='Model inputs'!B33))="",FALSE,IF(ISERROR(DATE(2027,5,1)='Model inputs'!B33),DATE(2027,5,1)='Model inputs'!B33,IF('Model inputs'!B33="","",DATE(2027,5,1)='Model inputs'!B33))),IF('Model inputs'!B90="","",'Model inputs'!B90),IF('Low-price monthly forecast'!H79="","",'Low-price monthly forecast'!H79))="",0,IF(IF(IF(ISERROR(DATE(2027,5,1)='Model inputs'!B33),DATE(2027,5,1)='Model inputs'!B33,IF('Model inputs'!B33="","",DATE(2027,5,1)='Model inputs'!B33))="",FALSE,IF(ISERROR(DATE(2027,5,1)='Model inputs'!B33),DATE(2027,5,1)='Model inputs'!B33,IF('Model inputs'!B33="","",DATE(2027,5,1)='Model inputs'!B33))),IF('Model inputs'!B90="","",'Model inputs'!B90),IF('Low-price monthly forecast'!H79="","",'Low-price monthly forecast'!H79)))+'Low-price monthly forecast'!I78 -> 8049.7315 | J79: =IF(IF(IF(IF(ISERROR(DATE(2027,6,1)='Model inputs'!B33),DATE(2027,6,1)='Model inputs'!B33,IF('Model inputs'!B33="","",DATE(2027,6,1)='Model inputs'!B33))="",FALSE,IF(ISERROR(DATE(2027,6,1)='Model inputs'!B33),DATE(2027,6,1)='Model inputs'!B33,IF('Model inputs'!B33="","",DATE(2027,6,1)='Model inputs'!B33))),IF('Model inputs'!B90="","",'Model inputs'!B90),IF('Low-price monthly forecast'!I79="","",'Low-price monthly forecast'!I79))="",0,IF(IF(IF(ISERROR(DATE(2027,6,1)='Model inputs'!B33),DATE(2027,6,1)='Model inputs'!B33,IF('Model inputs'!B33="","",DATE(2027,6,1)='Model inputs'!B33))="",FALSE,IF(ISERROR(DATE(2027,6,1)='Model inputs'!B33),DATE(2027,6,1)='Model inputs'!B33,IF('Model inputs'!B33="","",DATE(2027,6,1)='Model inputs'!B33))),IF('Model inputs'!B90="","",'Model inputs'!B90),IF('Low-price monthly forecast'!I79="","",'Low-price monthly forecast'!I79)))+'Low-price monthly forecast'!J78 -> 10481.442 | K79: =IF(IF(IF(IF(ISERROR(DATE(2027,7,1)='Model inputs'!B33),DATE(2027,7,1)='Model inputs'!B33,IF('Model inputs'!B33="","",DATE(2027,7,1)='Model inputs'!B33))="",FALSE,IF(ISERROR(DATE(2027,7,1)='Model inputs'!B33),DATE(2027,7,1)='Model inputs'!B33,IF('Model inputs'!B33="","",DATE(2027,7,1)='Model inputs'!B33))),IF('Model inputs'!B90="","",'Model inputs'!B90),IF('Low-price monthly forecast'!J79="","",'Low-price monthly forecast'!J79))="",0,IF(IF(IF(ISERROR(DATE(2027,7,1)='Model inputs'!B33),DATE(2027,7,1)='Model inputs'!B33,IF('Model inputs'!B33="","",DATE(2027,7,1)='Model inputs'!B33))="",FALSE,IF(ISERROR(DATE(2027,7,1)='Model inputs'!B33),DATE(2027,7,1)='Model inputs'!B33,IF('Model inputs'!B33="","",DATE(2027,7,1)='Model inputs'!B33))),IF('Model inputs'!B90="","",'Model inputs'!B90),IF('Low-price monthly forecast'!J79="","",'Low-price monthly forecast'!J79)))+'Low-price monthly forecast'!K78 -> 13551.185 | L79: =IF(IF(IF(IF(ISERROR(DATE(2027,8,1)='Model inputs'!B33),DATE(2027,8,1)='Model inputs'!B33,IF('Model inputs'!B33="","",DATE(2027,8,1)='Model inputs'!B33))="",FALSE,IF(ISERROR(DATE(2027,8,1)='Model inputs'!B33),DATE(2027,8,1)='Model inputs'!B33,IF('Model inputs'!B33="","",DATE(2027,8,1)='Model inputs'!B33))),IF('Model inputs'!B90="","",'Model inputs'!B90),IF('Low-price monthly forecast'!K79="","",'Low-price monthly forecast'!K79))="",0,IF(IF(IF(ISERROR(DATE(2027,8,1)='Model inputs'!B33),DATE(2027,8,1)='Model inputs'!B33,IF('Model inputs'!B33="","",DATE(2027,8,1)='Model inputs'!B33))="",FALSE,IF(ISERROR(DATE(2027,8,1)='Model inputs'!B33),DATE(2027,8,1)='Model inputs'!B33,IF('Model inputs'!B33="","",DATE(2027,8,1)='Model inputs'!B33))),IF('Model inputs'!B90="","",'Model inputs'!B90),IF('Low-price monthly forecast'!K79="","",'Low-price monthly forecast'!K79)))+'Low-price monthly forecast'!L78 -> 17233.437 | M79: =IF(IF(IF(IF(ISERROR(DATE(2027,9,1)='Model inputs'!B33),DATE(2027,9,1)='Model inputs'!B33,IF('Model inputs'!B33="","",DATE(2027,9,1)='Model inputs'!B33))="",FALSE,IF(ISERROR(DATE(2027,9,1)='Model inputs'!B33),DATE(2027,9,1)='Model inputs'!B33,IF('Model inputs'!B33="","",DATE(2027,9,1)='Model inputs'!B33))),IF('Model inputs'!B90="","",'Model inputs'!B90),IF('Low-price monthly forecast'!L79="","",'Low-price monthly forecast'!L79))="",0,IF(IF(IF(ISERROR(DATE(2027,9,1)='Model inputs'!B33),DATE(2027,9,1)='Model inputs'!B33,IF('Model inputs'!B33="","",DATE(2027,9,1)='Model inputs'!B33))="",FALSE,IF(ISERROR(DATE(2027,9,1)='Model inputs'!B33),DATE(2027,9,1)='Model inputs'!B33,IF('Model inputs'!B33="","",DATE(2027,9,1)='Model inputs'!B33))),IF('Model inputs'!B90="","",'Model inputs'!B90),IF('Low-price monthly forecast'!L79="","",'Low-price monthly forecast'!L79)))+'Low-price monthly forecast'!M78 -> 21503.7 | N79: =IF(IF(IF(IF(ISERROR(DATE(2027,10,1)='Model inputs'!B33),DATE(2027,10,1)='Model inputs'!B33,IF('Model inputs'!B33="","",DATE(2027,10,1)='Model inputs'!B33))="",FALSE,IF(ISERROR(DATE(2027,10,1)='Model inputs'!B33),DATE(2027,10,1)='Model inputs'!B33,IF('Model inputs'!B33="","",DATE(2027,10,1)='Model inputs'!B33))),IF('Model inputs'!B90="","",'Model inputs'!B90),IF('Low-price monthly forecast'!M79="","",'Low-price monthly forecast'!M79))="",0,IF(IF(IF(ISERROR(DATE(2027,10,1)='Model inputs'!B33),DATE(2027,10,1)='Model inputs'!B33,IF('Model inputs'!B33="","",DATE(2027,10,1)='Model inputs'!B33))="",FALSE,IF(ISERROR(DATE(2027,10,1)='Model inputs'!B33),DATE(2027,10,1)='Model inputs'!B33,IF('Model inputs'!B33="","",DATE(2027,10,1)='Model inputs'!B33))),IF('Model inputs'!B90="","",'Model inputs'!B90),IF('Low-price monthly forecast'!M79="","",'Low-price monthly forecast'!M79)))+'Low-price monthly forecast'!N78 -> 26338.452 | O79: =IF(IF(IF(IF(ISERROR(DATE(2027,11,1)='Model inputs'!B33),DATE(2027,11,1)='Model inputs'!B33,IF('Model inputs'!B33="","",DATE(2027,11,1)='Model inputs'!B33))="",FALSE,IF(ISERROR(DATE(2027,11,1)='Model inputs'!B33),DATE(2027,11,1)='Model inputs'!B33,IF('Model inputs'!B33="","",DATE(2027,11,1)='Model inputs'!B33))),IF('Model inputs'!B90="","",'Model inputs'!B90),IF('Low-price monthly forecast'!N79="","",'Low-price monthly forecast'!N79))="",0,IF(IF(IF(ISERROR(DATE(2027,11,1)='Model inputs'!B33),DATE(2027,11,1)='Model inputs'!B33,IF('Model inputs'!B33="","",DATE(2027,11,1)='Model inputs'!B33))="",FALSE,IF(ISERROR(DATE(2027,11,1)='Model inputs'!B33),DATE(2027,11,1)='Model inputs'!B33,IF('Model inputs'!B33="","",DATE(2027,11,1)='Model inputs'!B33))),IF('Model inputs'!B90="","",'Model inputs'!B90),IF('Low-price monthly forecast'!N79="","",'Low-price monthly forecast'!N79)))+'Low-price monthly forecast'!O78 -> 31715.114 | P79: =IF(IF(IF(IF(ISERROR(DATE(2027,12,1)='Model inputs'!B33),DATE(2027,12,1)='Model inputs'!B33,IF('Model inputs'!B33="","",DATE(2027,12,1)='Model inputs'!B33))="",FALSE,IF(ISERROR(DATE(2027,12,1)='Model inputs'!B33),DATE(2027,12,1)='Model inputs'!B33,IF('Model inputs'!B33="","",DATE(2027,12,1)='Model inputs'!B33))),IF('Model inputs'!B90="","",'Model inputs'!B90),IF('Low-price monthly forecast'!O79="","",'Low-price monthly forecast'!O79))="",0,IF(IF(IF(ISERROR(DATE(2027,12,1)='Model inputs'!B33),DATE(2027,12,1)='Model inputs'!B33,IF('Model inputs'!B33="","",DATE(2027,12,1)='Model inputs'!B33))="",FALSE,IF(ISERROR(DATE(2027,12,1)='Model inputs'!B33),DATE(2027,12,1)='Model inputs'!B33,IF('Model inputs'!B33="","",DATE(2027,12,1)='Model inputs'!B33))),IF('Model inputs'!B90="","",'Model inputs'!B90),IF('Low-price monthly forecast'!O79="","",'Low-price monthly forecast'!O79)))+'Low-price monthly forecast'!P78 -> 37612.009 | Q79: =IF(IF(IF(IF(ISERROR(DATE(2028,1,1)='Model inputs'!B33),DATE(2028,1,1)='Model inputs'!B33,IF('Model inputs'!B33="","",DATE(2028,1,1)='Model inputs'!B33))="",FALSE,IF(ISERROR(DATE(2028,1,1)='Model inputs'!B33),DATE(2028,1,1)='Model inputs'!B33,IF('Model inputs'!B33="","",DATE(2028,1,1)='Model inputs'!B33))),IF('Model inputs'!B90="","",'Model inputs'!B90),IF('Low-price monthly forecast'!P79="","",'Low-price monthly forecast'!P79))="",0,IF(IF(IF(ISERROR(DATE(2028,1,1)='Model inputs'!B33),DATE(2028,1,1)='Model inputs'!B33,IF('Model inputs'!B33="","",DATE(2028,1,1)='Model inputs'!B33))="",FALSE,IF(ISERROR(DATE(2028,1,1)='Model inputs'!B33),DATE(2028,1,1)='Model inputs'!B33,IF('Model inputs'!B33="","",DATE(2028,1,1)='Model inputs'!B33))),IF('Model inputs'!B90="","",'Model inputs'!B90),IF('Low-price monthly forecast'!P79="","",'Low-price monthly forecast'!P79)))+'Low-price monthly forecast'!Q78 -> 44008.329 | R79: =IF(IF(IF(IF(ISERROR(DATE(2028,2,1)='Model inputs'!B33),DATE(2028,2,1)='Model inputs'!B33,IF('Model inputs'!B33="","",DATE(2028,2,1)='Model inputs'!B33))="",FALSE,IF(ISERROR(DATE(2028,2,1)='Model inputs'!B33),DATE(2028,2,1)='Model inputs'!B33,IF('Model inputs'!B33="","",DATE(2028,2,1)='Model inputs'!B33))),IF('Model inputs'!B90="","",'Model inputs'!B90),IF('Low-price monthly forecast'!Q79="","",'Low-price monthly forecast'!Q79))="",0,IF(IF(IF(ISERROR(DATE(2028,2,1)='Model inputs'!B33),DATE(2028,2,1)='Model inputs'!B33,IF('Model inputs'!B33="","",DATE(2028,2,1)='Model inputs'!B33))="",FALSE,IF(ISERROR(DATE(2028,2,1)='Model inputs'!B33),DATE(2028,2,1)='Model inputs'!B33,IF('Model inputs'!B33="","",DATE(2028,2,1)='Model inputs'!B33))),IF('Model inputs'!B90="","",'Model inputs'!B90),IF('Low-price monthly forecast'!Q79="","",'Low-price monthly forecast'!Q79)))+'Low-price monthly forecast'!R78 -> 50884.096 | S79: =IF(IF(IF(IF(ISERROR(DATE(2028,3,1)='Model inputs'!B33),DATE(2028,3,1)='Model inputs'!B33,IF('Model inputs'!B33="","",DATE(2028,3,1)='Model inputs'!B33))="",FALSE,IF(ISERROR(DATE(2028,3,1)='Model inputs'!B33),DATE(2028,3,1)='Model inputs'!B33,IF('Model inputs'!B33="","",DATE(2028,3,1)='Model inputs'!B33))),IF('Model inputs'!B90="","",'Model inputs'!B90),IF('Low-price monthly forecast'!R79="","",'Low-price monthly forecast'!R79))="",0,IF(IF(IF(ISERROR(DATE(2028,3,1)='Model inputs'!B33),DATE(2028,3,1)='Model inputs'!B33,IF('Model inputs'!B33="","",DATE(2028,3,1)='Model inputs'!B33))="",FALSE,IF(ISERROR(DATE(2028,3,1)='Model inputs'!B33),DATE(2028,3,1)='Model inputs'!B33,IF('Model inputs'!B33="","",DATE(2028,3,1)='Model inputs'!B33))),IF('Model inputs'!B90="","",'Model inputs'!B90),IF('Low-price monthly forecast'!R79="","",'Low-price monthly forecast'!R79)))+'Low-price monthly forecast'!S78 -> 58220.132
A80: NW BYOK-test revenue | B80: ='Low-price monthly forecast'!B20*'Model inputs'!B11 -> 1154 | C80: ='Low-price monthly forecast'!C20*'Model inputs'!B11 -> 2261.84 | D80: ='Low-price monthly forecast'!D20*'Model inputs'!B11 -> 3325.3664 | E80: ='Low-price monthly forecast'!E20*'Model inputs'!B11 -> 4346.3517 | F80: ='Low-price monthly forecast'!F20*'Model inputs'!B11 -> 5326.4977 | G80: ='Low-price monthly forecast'!G20*'Model inputs'!B11 -> 6267.4378 | H80: ='Low-price monthly forecast'!H20*'Model inputs'!B11 -> 7170.7403 | I80: ='Low-price monthly forecast'!I20*'Model inputs'!B11 -> 8037.9106 | J80: ='Low-price monthly forecast'!J20*'Model inputs'!B11 -> 8870.3942 | K80: ='Low-price monthly forecast'!K20*'Model inputs'!B11 -> 9669.5785 | L80: ='Low-price monthly forecast'!L20*'Model inputs'!B11 -> 10436.795 | M80: ='Low-price monthly forecast'!M20*'Model inputs'!B11 -> 11173.324 | N80: ='Low-price monthly forecast'!N20*'Model inputs'!B11 -> 11880.391 | O80: ='Low-price monthly forecast'!O20*'Model inputs'!B11 -> 12559.175 | P80: ='Low-price monthly forecast'!P20*'Model inputs'!B11 -> 13210.808 | Q80: ='Low-price monthly forecast'!Q20*'Model inputs'!B11 -> 13836.376 | R80: ='Low-price monthly forecast'!R20*'Model inputs'!B11 -> 14436.921 | S80: ='Low-price monthly forecast'!S20*'Model inputs'!B11 -> 15013.444
A81: NW BYOK-test gross profit | B81: ='Low-price monthly forecast'!B20*'Model inputs'!B10 -> 884.5 | C81: ='Low-price monthly forecast'!C20*'Model inputs'!B10 -> 1733.62 | D81: ='Low-price monthly forecast'!D20*'Model inputs'!B10 -> 2548.7752 | E81: ='Low-price monthly forecast'!E20*'Model inputs'!B10 -> 3331.3242 | F81: ='Low-price monthly forecast'!F20*'Model inputs'!B10 -> 4082.5712 | G81: ='Low-price monthly forecast'!G20*'Model inputs'!B10 -> 4803.7684 | H81: ='Low-price monthly forecast'!H20*'Model inputs'!B10 -> 5496.1176 | I81: ='Low-price monthly forecast'!I20*'Model inputs'!B10 -> 6160.7729 | J81: ='Low-price monthly forecast'!J20*'Model inputs'!B10 -> 6798.842 | K81: ='Low-price monthly forecast'!K20*'Model inputs'!B10 -> 7411.3883 | L81: ='Low-price monthly forecast'!L20*'Model inputs'!B10 -> 7999.4328 | M81: ='Low-price monthly forecast'!M20*'Model inputs'!B10 -> 8563.9555 | N81: ='Low-price monthly forecast'!N20*'Model inputs'!B10 -> 9105.8973 | O81: ='Low-price monthly forecast'!O20*'Model inputs'!B10 -> 9626.1614 | P81: ='Low-price monthly forecast'!P20*'Model inputs'!B10 -> 10125.615 | Q81: ='Low-price monthly forecast'!Q20*'Model inputs'!B10 -> 10605.09 | R81: ='Low-price monthly forecast'!R20*'Model inputs'!B10 -> 11065.387 | S81: ='Low-price monthly forecast'!S20*'Model inputs'!B10 -> 11507.271
A82: NW BYOK-test gross margin | B82: =IFERROR('Low-price monthly forecast'!B81/'Low-price monthly forecast'!B80,"") -> 0.76646447 | C82: =IFERROR('Low-price monthly forecast'!C81/'Low-price monthly forecast'!C80,"") -> 0.76646447 | D82: =IFERROR('Low-price monthly forecast'!D81/'Low-price monthly forecast'!D80,"") -> 0.76646447 | E82: =IFERROR('Low-price monthly forecast'!E81/'Low-price monthly forecast'!E80,"") -> 0.76646447 | F82: =IFERROR('Low-price monthly forecast'!F81/'Low-price monthly forecast'!F80,"") -> 0.76646447 | G82: =IFERROR('Low-price monthly forecast'!G81/'Low-price monthly forecast'!G80,"") -> 0.76646447 | H82: =IFERROR('Low-price monthly forecast'!H81/'Low-price monthly forecast'!H80,"") -> 0.76646447 | I82: =IFERROR('Low-price monthly forecast'!I81/'Low-price monthly forecast'!I80,"") -> 0.76646447 | ... S82: =IFERROR('Low-price monthly forecast'!S81/'Low-price monthly forecast'!S80,"") -> 0.76646447
A83: NW BYOK-test operating profit | B83: ='Low-price monthly forecast'!B81-'Low-price monthly forecast'!B71-'Low-price monthly forecast'!B72 -> -3765.5 | C83: ='Low-price monthly forecast'!C81-'Low-price monthly forecast'!C71-'Low-price monthly forecast'!C72 -> -2916.38 | D83: ='Low-price monthly forecast'!D81-'Low-price monthly forecast'!D71-'Low-price monthly forecast'!D72 -> -2101.2248 | E83: ='Low-price monthly forecast'!E81-'Low-price monthly forecast'!E71-'Low-price monthly forecast'!E72 -> -1318.6758 | F83: ='Low-price monthly forecast'!F81-'Low-price monthly forecast'!F71-'Low-price monthly forecast'!F72 -> -567.42878 | G83: ='Low-price monthly forecast'!G81-'Low-price monthly forecast'!G71-'Low-price monthly forecast'!G72 -> 153.76838 | H83: ='Low-price monthly forecast'!H81-'Low-price monthly forecast'!H71-'Low-price monthly forecast'!H72 -> 846.11764 | I83: ='Low-price monthly forecast'!I81-'Low-price monthly forecast'!I71-'Low-price monthly forecast'!I72 -> 1510.7729 | ... S83: ='Low-price monthly forecast'!S81-'Low-price monthly forecast'!S71-'Low-price monthly forecast'!S72 -> 6857.2712
A84: NW BYOK-test cash balance | B84: =IF(IF(IF(IF(ISERROR(DATE(2026,10,1)='Model inputs'!B33),DATE(2026,10,1)='Model inputs'!B33,IF('Model inputs'!B33="","",DATE(2026,10,1)='Model inputs'!B33))="",FALSE,IF(ISERROR(DATE(2026,10,1)='Model inputs'!B33),DATE(2026,10,1)='Model inputs'!B33,IF('Model inputs'!B33="","",DATE(2026,10,1)='Model inputs'!B33))),IF('Model inputs'!B90="","",'Model inputs'!B90),IF('Model inputs'!K12="","",'Model inputs'!K12))="",0,IF(IF(IF(ISERROR(DATE(2026,10,1)='Model inputs'!B33),DATE(2026,10,1)='Model inputs'!B33,IF('Model inputs'!B33="","",DATE(2026,10,1)='Model inputs'!B33))="",FALSE,IF(ISERROR(DATE(2026,10,1)='Model inputs'!B33),DATE(2026,10,1)='Model inputs'!B33,IF('Model inputs'!B33="","",DATE(2026,10,1)='Model inputs'!B33))),IF('Model inputs'!B90="","",'Model inputs'!B90),IF('Model inputs'!K12="","",'Model inputs'!K12)))+'Low-price monthly forecast'!B83 -> 11234.5 | C84: =IF(IF(IF(IF(ISERROR(DATE(2026,11,1)='Model inputs'!B33),DATE(2026,11,1)='Model inputs'!B33,IF('Model inputs'!B33="","",DATE(2026,11,1)='Model inputs'!B33))="",FALSE,IF(ISERROR(DATE(2026,11,1)='Model inputs'!B33),DATE(2026,11,1)='Model inputs'!B33,IF('Model inputs'!B33="","",DATE(2026,11,1)='Model inputs'!B33))),IF('Model inputs'!B90="","",'Model inputs'!B90),IF('Low-price monthly forecast'!B84="","",'Low-price monthly forecast'!B84))="",0,IF(IF(IF(ISERROR(DATE(2026,11,1)='Model inputs'!B33),DATE(2026,11,1)='Model inputs'!B33,IF('Model inputs'!B33="","",DATE(2026,11,1)='Model inputs'!B33))="",FALSE,IF(ISERROR(DATE(2026,11,1)='Model inputs'!B33),DATE(2026,11,1)='Model inputs'!B33,IF('Model inputs'!B33="","",DATE(2026,11,1)='Model inputs'!B33))),IF('Model inputs'!B90="","",'Model inputs'!B90),IF('Low-price monthly forecast'!B84="","",'Low-price monthly forecast'!B84)))+'Low-price monthly forecast'!C83 -> 8318.12 | D84: =IF(IF(IF(IF(ISERROR(DATE(2026,12,1)='Model inputs'!B33),DATE(2026,12,1)='Model inputs'!B33,IF('Model inputs'!B33="","",DATE(2026,12,1)='Model inputs'!B33))="",FALSE,IF(ISERROR(DATE(2026,12,1)='Model inputs'!B33),DATE(2026,12,1)='Model inputs'!B33,IF('Model inputs'!B33="","",DATE(2026,12,1)='Model inputs'!B33))),IF('Model inputs'!B90="","",'Model inputs'!B90),IF('Low-price monthly forecast'!C84="","",'Low-price monthly forecast'!C84))="",0,IF(IF(IF(ISERROR(DATE(2026,12,1)='Model inputs'!B33),DATE(2026,12,1)='Model inputs'!B33,IF('Model inputs'!B33="","",DATE(2026,12,1)='Model inputs'!B33))="",FALSE,IF(ISERROR(DATE(2026,12,1)='Model inputs'!B33),DATE(2026,12,1)='Model inputs'!B33,IF('Model inputs'!B33="","",DATE(2026,12,1)='Model inputs'!B33))),IF('Model inputs'!B90="","",'Model inputs'!B90),IF('Low-price monthly forecast'!C84="","",'Low-price monthly forecast'!C84)))+'Low-price monthly forecast'!D83 -> 6216.8952 | E84: =IF(IF(IF(IF(ISERROR(DATE(2027,1,1)='Model inputs'!B33),DATE(2027,1,1)='Model inputs'!B33,IF('Model inputs'!B33="","",DATE(2027,1,1)='Model inputs'!B33))="",FALSE,IF(ISERROR(DATE(2027,1,1)='Model inputs'!B33),DATE(2027,1,1)='Model inputs'!B33,IF('Model inputs'!B33="","",DATE(2027,1,1)='Model inputs'!B33))),IF('Model inputs'!B90="","",'Model inputs'!B90),IF('Low-price monthly forecast'!D84="","",'Low-price monthly forecast'!D84))="",0,IF(IF(IF(ISERROR(DATE(2027,1,1)='Model inputs'!B33),DATE(2027,1,1)='Model inputs'!B33,IF('Model inputs'!B33="","",DATE(2027,1,1)='Model inputs'!B33))="",FALSE,IF(ISERROR(DATE(2027,1,1)='Model inputs'!B33),DATE(2027,1,1)='Model inputs'!B33,IF('Model inputs'!B33="","",DATE(2027,1,1)='Model inputs'!B33))),IF('Model inputs'!B90="","",'Model inputs'!B90),IF('Low-price monthly forecast'!D84="","",'Low-price monthly forecast'!D84)))+'Low-price monthly forecast'!E83 -> 4898.2194 | F84: =IF(IF(IF(IF(ISERROR(DATE(2027,2,1)='Model inputs'!B33),DATE(2027,2,1)='Model inputs'!B33,IF('Model inputs'!B33="","",DATE(2027,2,1)='Model inputs'!B33))="",FALSE,IF(ISERROR(DATE(2027,2,1)='Model inputs'!B33),DATE(2027,2,1)='Model inputs'!B33,IF('Model inputs'!B33="","",DATE(2027,2,1)='Model inputs'!B33))),IF('Model inputs'!B90="","",'Model inputs'!B90),IF('Low-price monthly forecast'!E84="","",'Low-price monthly forecast'!E84))="",0,IF(IF(IF(ISERROR(DATE(2027,2,1)='Model inputs'!B33),DATE(2027,2,1)='Model inputs'!B33,IF('Model inputs'!B33="","",DATE(2027,2,1)='Model inputs'!B33))="",FALSE,IF(ISERROR(DATE(2027,2,1)='Model inputs'!B33),DATE(2027,2,1)='Model inputs'!B33,IF('Model inputs'!B33="","",DATE(2027,2,1)='Model inputs'!B33))),IF('Model inputs'!B90="","",'Model inputs'!B90),IF('Low-price monthly forecast'!E84="","",'Low-price monthly forecast'!E84)))+'Low-price monthly forecast'!F83 -> 4330.7906 | G84: =IF(IF(IF(IF(ISERROR(DATE(2027,3,1)='Model inputs'!B33),DATE(2027,3,1)='Model inputs'!B33,IF('Model inputs'!B33="","",DATE(2027,3,1)='Model inputs'!B33))="",FALSE,IF(ISERROR(DATE(2027,3,1)='Model inputs'!B33),DATE(2027,3,1)='Model inputs'!B33,IF('Model inputs'!B33="","",DATE(2027,3,1)='Model inputs'!B33))),IF('Model inputs'!B90="","",'Model inputs'!B90),IF('Low-price monthly forecast'!F84="","",'Low-price monthly forecast'!F84))="",0,IF(IF(IF(ISERROR(DATE(2027,3,1)='Model inputs'!B33),DATE(2027,3,1)='Model inputs'!B33,IF('Model inputs'!B33="","",DATE(2027,3,1)='Model inputs'!B33))="",FALSE,IF(ISERROR(DATE(2027,3,1)='Model inputs'!B33),DATE(2027,3,1)='Model inputs'!B33,IF('Model inputs'!B33="","",DATE(2027,3,1)='Model inputs'!B33))),IF('Model inputs'!B90="","",'Model inputs'!B90),IF('Low-price monthly forecast'!F84="","",'Low-price monthly forecast'!F84)))+'Low-price monthly forecast'!G83 -> 4484.559 | H84: =IF(IF(IF(IF(ISERROR(DATE(2027,4,1)='Model inputs'!B33),DATE(2027,4,1)='Model inputs'!B33,IF('Model inputs'!B33="","",DATE(2027,4,1)='Model inputs'!B33))="",FALSE,IF(ISERROR(DATE(2027,4,1)='Model inputs'!B33),DATE(2027,4,1)='Model inputs'!B33,IF('Model inputs'!B33="","",DATE(2027,4,1)='Model inputs'!B33))),IF('Model inputs'!B90="","",'Model inputs'!B90),IF('Low-price monthly forecast'!G84="","",'Low-price monthly forecast'!G84))="",0,IF(IF(IF(ISERROR(DATE(2027,4,1)='Model inputs'!B33),DATE(2027,4,1)='Model inputs'!B33,IF('Model inputs'!B33="","",DATE(2027,4,1)='Model inputs'!B33))="",FALSE,IF(ISERROR(DATE(2027,4,1)='Model inputs'!B33),DATE(2027,4,1)='Model inputs'!B33,IF('Model inputs'!B33="","",DATE(2027,4,1)='Model inputs'!B33))),IF('Model inputs'!B90="","",'Model inputs'!B90),IF('Low-price monthly forecast'!G84="","",'Low-price monthly forecast'!G84)))+'Low-price monthly forecast'!H83 -> 5330.6766 | I84: =IF(IF(IF(IF(ISERROR(DATE(2027,5,1)='Model inputs'!B33),DATE(2027,5,1)='Model inputs'!B33,IF('Model inputs'!B33="","",DATE(2027,5,1)='Model inputs'!B33))="",FALSE,IF(ISERROR(DATE(2027,5,1)='Model inputs'!B33),DATE(2027,5,1)='Model inputs'!B33,IF('Model inputs'!B33="","",DATE(2027,5,1)='Model inputs'!B33))),IF('Model inputs'!B90="","",'Model inputs'!B90),IF('Low-price monthly forecast'!H84="","",'Low-price monthly forecast'!H84))="",0,IF(IF(IF(ISERROR(DATE(2027,5,1)='Model inputs'!B33),DATE(2027,5,1)='Model inputs'!B33,IF('Model inputs'!B33="","",DATE(2027,5,1)='Model inputs'!B33))="",FALSE,IF(ISERROR(DATE(2027,5,1)='Model inputs'!B33),DATE(2027,5,1)='Model inputs'!B33,IF('Model inputs'!B33="","",DATE(2027,5,1)='Model inputs'!B33))),IF('Model inputs'!B90="","",'Model inputs'!B90),IF('Low-price monthly forecast'!H84="","",'Low-price monthly forecast'!H84)))+'Low-price monthly forecast'!I83 -> 6841.4496 | J84: =IF(IF(IF(IF(ISERROR(DATE(2027,6,1)='Model inputs'!B33),DATE(2027,6,1)='Model inputs'!B33,IF('Model inputs'!B33="","",DATE(2027,6,1)='Model inputs'!B33))="",FALSE,IF(ISERROR(DATE(2027,6,1)='Model inputs'!B33),DATE(2027,6,1)='Model inputs'!B33,IF('Model inputs'!B33="","",DATE(2027,6,1)='Model inputs'!B33))),IF('Model inputs'!B90="","",'Model inputs'!B90),IF('Low-price monthly forecast'!I84="","",'Low-price monthly forecast'!I84))="",0,IF(IF(IF(ISERROR(DATE(2027,6,1)='Model inputs'!B33),DATE(2027,6,1)='Model inputs'!B33,IF('Model inputs'!B33="","",DATE(2027,6,1)='Model inputs'!B33))="",FALSE,IF(ISERROR(DATE(2027,6,1)='Model inputs'!B33),DATE(2027,6,1)='Model inputs'!B33,IF('Model inputs'!B33="","",DATE(2027,6,1)='Model inputs'!B33))),IF('Model inputs'!B90="","",'Model inputs'!B90),IF('Low-price monthly forecast'!I84="","",'Low-price monthly forecast'!I84)))+'Low-price monthly forecast'!J83 -> 8990.2916 | K84: =IF(IF(IF(IF(ISERROR(DATE(2027,7,1)='Model inputs'!B33),DATE(2027,7,1)='Model inputs'!B33,IF('Model inputs'!B33="","",DATE(2027,7,1)='Model inputs'!B33))="",FALSE,IF(ISERROR(DATE(2027,7,1)='Model inputs'!B33),DATE(2027,7,1)='Model inputs'!B33,IF('Model inputs'!B33="","",DATE(2027,7,1)='Model inputs'!B33))),IF('Model inputs'!B90="","",'Model inputs'!B90),IF('Low-price monthly forecast'!J84="","",'Low-price monthly forecast'!J84))="",0,IF(IF(IF(ISERROR(DATE(2027,7,1)='Model inputs'!B33),DATE(2027,7,1)='Model inputs'!B33,IF('Model inputs'!B33="","",DATE(2027,7,1)='Model inputs'!B33))="",FALSE,IF(ISERROR(DATE(2027,7,1)='Model inputs'!B33),DATE(2027,7,1)='Model inputs'!B33,IF('Model inputs'!B33="","",DATE(2027,7,1)='Model inputs'!B33))),IF('Model inputs'!B90="","",'Model inputs'!B90),IF('Low-price monthly forecast'!J84="","",'Low-price monthly forecast'!J84)))+'Low-price monthly forecast'!K83 -> 11751.68 | L84: =IF(IF(IF(IF(ISERROR(DATE(2027,8,1)='Model inputs'!B33),DATE(2027,8,1)='Model inputs'!B33,IF('Model inputs'!B33="","",DATE(2027,8,1)='Model inputs'!B33))="",FALSE,IF(ISERROR(DATE(2027,8,1)='Model inputs'!B33),DATE(2027,8,1)='Model inputs'!B33,IF('Model inputs'!B33="","",DATE(2027,8,1)='Model inputs'!B33))),IF('Model inputs'!B90="","",'Model inputs'!B90),IF('Low-price monthly forecast'!K84="","",'Low-price monthly forecast'!K84))="",0,IF(IF(IF(ISERROR(DATE(2027,8,1)='Model inputs'!B33),DATE(2027,8,1)='Model inputs'!B33,IF('Model inputs'!B33="","",DATE(2027,8,1)='Model inputs'!B33))="",FALSE,IF(ISERROR(DATE(2027,8,1)='Model inputs'!B33),DATE(2027,8,1)='Model inputs'!B33,IF('Model inputs'!B33="","",DATE(2027,8,1)='Model inputs'!B33))),IF('Model inputs'!B90="","",'Model inputs'!B90),IF('Low-price monthly forecast'!K84="","",'Low-price monthly forecast'!K84)))+'Low-price monthly forecast'!L83 -> 15101.113 | M84: =IF(IF(IF(IF(ISERROR(DATE(2027,9,1)='Model inputs'!B33),DATE(2027,9,1)='Model inputs'!B33,IF('Model inputs'!B33="","",DATE(2027,9,1)='Model inputs'!B33))="",FALSE,IF(ISERROR(DATE(2027,9,1)='Model inputs'!B33),DATE(2027,9,1)='Model inputs'!B33,IF('Model inputs'!B33="","",DATE(2027,9,1)='Model inputs'!B33))),IF('Model inputs'!B90="","",'Model inputs'!B90),IF('Low-price monthly forecast'!L84="","",'Low-price monthly forecast'!L84))="",0,IF(IF(IF(ISERROR(DATE(2027,9,1)='Model inputs'!B33),DATE(2027,9,1)='Model inputs'!B33,IF('Model inputs'!B33="","",DATE(2027,9,1)='Model inputs'!B33))="",FALSE,IF(ISERROR(DATE(2027,9,1)='Model inputs'!B33),DATE(2027,9,1)='Model inputs'!B33,IF('Model inputs'!B33="","",DATE(2027,9,1)='Model inputs'!B33))),IF('Model inputs'!B90="","",'Model inputs'!B90),IF('Low-price monthly forecast'!L84="","",'Low-price monthly forecast'!L84)))+'Low-price monthly forecast'!M83 -> 19015.068 | N84: =IF(IF(IF(IF(ISERROR(DATE(2027,10,1)='Model inputs'!B33),DATE(2027,10,1)='Model inputs'!B33,IF('Model inputs'!B33="","",DATE(2027,10,1)='Model inputs'!B33))="",FALSE,IF(ISERROR(DATE(2027,10,1)='Model inputs'!B33),DATE(2027,10,1)='Model inputs'!B33,IF('Model inputs'!B33="","",DATE(2027,10,1)='Model inputs'!B33))),IF('Model inputs'!B90="","",'Model inputs'!B90),IF('Low-price monthly forecast'!M84="","",'Low-price monthly forecast'!M84))="",0,IF(IF(IF(ISERROR(DATE(2027,10,1)='Model inputs'!B33),DATE(2027,10,1)='Model inputs'!B33,IF('Model inputs'!B33="","",DATE(2027,10,1)='Model inputs'!B33))="",FALSE,IF(ISERROR(DATE(2027,10,1)='Model inputs'!B33),DATE(2027,10,1)='Model inputs'!B33,IF('Model inputs'!B33="","",DATE(2027,10,1)='Model inputs'!B33))),IF('Model inputs'!B90="","",'Model inputs'!B90),IF('Low-price monthly forecast'!M84="","",'Low-price monthly forecast'!M84)))+'Low-price monthly forecast'!N83 -> 23470.965 | O84: =IF(IF(IF(IF(ISERROR(DATE(2027,11,1)='Model inputs'!B33),DATE(2027,11,1)='Model inputs'!B33,IF('Model inputs'!B33="","",DATE(2027,11,1)='Model inputs'!B33))="",FALSE,IF(ISERROR(DATE(2027,11,1)='Model inputs'!B33),DATE(2027,11,1)='Model inputs'!B33,IF('Model inputs'!B33="","",DATE(2027,11,1)='Model inputs'!B33))),IF('Model inputs'!B90="","",'Model inputs'!B90),IF('Low-price monthly forecast'!N84="","",'Low-price monthly forecast'!N84))="",0,IF(IF(IF(ISERROR(DATE(2027,11,1)='Model inputs'!B33),DATE(2027,11,1)='Model inputs'!B33,IF('Model inputs'!B33="","",DATE(2027,11,1)='Model inputs'!B33))="",FALSE,IF(ISERROR(DATE(2027,11,1)='Model inputs'!B33),DATE(2027,11,1)='Model inputs'!B33,IF('Model inputs'!B33="","",DATE(2027,11,1)='Model inputs'!B33))),IF('Model inputs'!B90="","",'Model inputs'!B90),IF('Low-price monthly forecast'!N84="","",'Low-price monthly forecast'!N84)))+'Low-price monthly forecast'!O83 -> 28447.127 | P84: =IF(IF(IF(IF(ISERROR(DATE(2027,12,1)='Model inputs'!B33),DATE(2027,12,1)='Model inputs'!B33,IF('Model inputs'!B33="","",DATE(2027,12,1)='Model inputs'!B33))="",FALSE,IF(ISERROR(DATE(2027,12,1)='Model inputs'!B33),DATE(2027,12,1)='Model inputs'!B33,IF('Model inputs'!B33="","",DATE(2027,12,1)='Model inputs'!B33))),IF('Model inputs'!B90="","",'Model inputs'!B90),IF('Low-price monthly forecast'!O84="","",'Low-price monthly forecast'!O84))="",0,IF(IF(IF(ISERROR(DATE(2027,12,1)='Model inputs'!B33),DATE(2027,12,1)='Model inputs'!B33,IF('Model inputs'!B33="","",DATE(2027,12,1)='Model inputs'!B33))="",FALSE,IF(ISERROR(DATE(2027,12,1)='Model inputs'!B33),DATE(2027,12,1)='Model inputs'!B33,IF('Model inputs'!B33="","",DATE(2027,12,1)='Model inputs'!B33))),IF('Model inputs'!B90="","",'Model inputs'!B90),IF('Low-price monthly forecast'!O84="","",'Low-price monthly forecast'!O84)))+'Low-price monthly forecast'!P83 -> 33922.742 | Q84: =IF(IF(IF(IF(ISERROR(DATE(2028,1,1)='Model inputs'!B33),DATE(2028,1,1)='Model inputs'!B33,IF('Model inputs'!B33="","",DATE(2028,1,1)='Model inputs'!B33))="",FALSE,IF(ISERROR(DATE(2028,1,1)='Model inputs'!B33),DATE(2028,1,1)='Model inputs'!B33,IF('Model inputs'!B33="","",DATE(2028,1,1)='Model inputs'!B33))),IF('Model inputs'!B90="","",'Model inputs'!B90),IF('Low-price monthly forecast'!P84="","",'Low-price monthly forecast'!P84))="",0,IF(IF(IF(ISERROR(DATE(2028,1,1)='Model inputs'!B33),DATE(2028,1,1)='Model inputs'!B33,IF('Model inputs'!B33="","",DATE(2028,1,1)='Model inputs'!B33))="",FALSE,IF(ISERROR(DATE(2028,1,1)='Model inputs'!B33),DATE(2028,1,1)='Model inputs'!B33,IF('Model inputs'!B33="","",DATE(2028,1,1)='Model inputs'!B33))),IF('Model inputs'!B90="","",'Model inputs'!B90),IF('Low-price monthly forecast'!P84="","",'Low-price monthly forecast'!P84)))+'Low-price monthly forecast'!Q83 -> 39877.832 | R84: =IF(IF(IF(IF(ISERROR(DATE(2028,2,1)='Model inputs'!B33),DATE(2028,2,1)='Model inputs'!B33,IF('Model inputs'!B33="","",DATE(2028,2,1)='Model inputs'!B33))="",FALSE,IF(ISERROR(DATE(2028,2,1)='Model inputs'!B33),DATE(2028,2,1)='Model inputs'!B33,IF('Model inputs'!B33="","",DATE(2028,2,1)='Model inputs'!B33))),IF('Model inputs'!B90="","",'Model inputs'!B90),IF('Low-price monthly forecast'!Q84="","",'Low-price monthly forecast'!Q84))="",0,IF(IF(IF(ISERROR(DATE(2028,2,1)='Model inputs'!B33),DATE(2028,2,1)='Model inputs'!B33,IF('Model inputs'!B33="","",DATE(2028,2,1)='Model inputs'!B33))="",FALSE,IF(ISERROR(DATE(2028,2,1)='Model inputs'!B33),DATE(2028,2,1)='Model inputs'!B33,IF('Model inputs'!B33="","",DATE(2028,2,1)='Model inputs'!B33))),IF('Model inputs'!B90="","",'Model inputs'!B90),IF('Low-price monthly forecast'!Q84="","",'Low-price monthly forecast'!Q84)))+'Low-price monthly forecast'!R83 -> 46293.219 | S84: =IF(IF(IF(IF(ISERROR(DATE(2028,3,1)='Model inputs'!B33),DATE(2028,3,1)='Model inputs'!B33,IF('Model inputs'!B33="","",DATE(2028,3,1)='Model inputs'!B33))="",FALSE,IF(ISERROR(DATE(2028,3,1)='Model inputs'!B33),DATE(2028,3,1)='Model inputs'!B33,IF('Model inputs'!B33="","",DATE(2028,3,1)='Model inputs'!B33))),IF('Model inputs'!B90="","",'Model inputs'!B90),IF('Low-price monthly forecast'!R84="","",'Low-price monthly forecast'!R84))="",0,IF(IF(IF(ISERROR(DATE(2028,3,1)='Model inputs'!B33),DATE(2028,3,1)='Model inputs'!B33,IF('Model inputs'!B33="","",DATE(2028,3,1)='Model inputs'!B33))="",FALSE,IF(ISERROR(DATE(2028,3,1)='Model inputs'!B33),DATE(2028,3,1)='Model inputs'!B33,IF('Model inputs'!B33="","",DATE(2028,3,1)='Model inputs'!B33))),IF('Model inputs'!B90="","",'Model inputs'!B90),IF('Low-price monthly forecast'!R84="","",'Low-price monthly forecast'!R84)))+'Low-price monthly forecast'!S83 -> 53150.49
A85: NW Customer reconciliation | B85: ='Low-price monthly forecast'!B20-'Low-price monthly forecast'!B5-'Low-price monthly forecast'!B10+'Low-price monthly forecast'!B15 -> 0 | C85: ='Low-price monthly forecast'!C20-'Low-price monthly forecast'!C5-'Low-price monthly forecast'!C10+'Low-price monthly forecast'!C15 -> 5.7731597e-15 | D85: ='Low-price monthly forecast'!D20-'Low-price monthly forecast'!D5-'Low-price monthly forecast'!D10+'Low-price monthly forecast'!D15 -> 4.4408921e-15 | E85: ='Low-price monthly forecast'!E20-'Low-price monthly forecast'!E5-'Low-price monthly forecast'!E10+'Low-price monthly forecast'!E15 -> -2.0428104e-14 | F85: ='Low-price monthly forecast'!F20-'Low-price monthly forecast'!F5-'Low-price monthly forecast'!F10+'Low-price monthly forecast'!F15 -> 1.7763568e-15 | G85: ='Low-price monthly forecast'!G20-'Low-price monthly forecast'!G5-'Low-price monthly forecast'!G10+'Low-price monthly forecast'!G15 -> 6.2172489e-15 | H85: ='Low-price monthly forecast'!H20-'Low-price monthly forecast'!H5-'Low-price monthly forecast'!H10+'Low-price monthly forecast'!H15 -> 5.3290705e-15 | I85: ='Low-price monthly forecast'!I20-'Low-price monthly forecast'!I5-'Low-price monthly forecast'!I10+'Low-price monthly forecast'!I15 -> 1.0658141e-14 | ... S85: ='Low-price monthly forecast'!S20-'Low-price monthly forecast'!S5-'Low-price monthly forecast'!S10+'Low-price monthly forecast'!S15 -> -2.4868996e-14
A86: NW Cash reconciliation | B86: ='Low-price monthly forecast'!B74-IF(IF(IF(IF(ISERROR(DATE(2026,10,1)='Model inputs'!B33),DATE(2026,10,1)='Model inputs'!B33,IF('Model inputs'!B33="","",DATE(2026,10,1)='Model inputs'!B33))="",FALSE,IF(ISERROR(DATE(2026,10,1)='Model inputs'!B33),DATE(2026,10,1)='Model inputs'!B33,IF('Model inputs'!B33="","",DATE(2026,10,1)='Model inputs'!B33))),IF('Model inputs'!B90="","",'Model inputs'!B90),IF('Model inputs'!K15="","",'Model inputs'!K15))="",0,IF(IF(IF(ISERROR(DATE(2026,10,1)='Model inputs'!B33),DATE(2026,10,1)='Model inputs'!B33,IF('Model inputs'!B33="","",DATE(2026,10,1)='Model inputs'!B33))="",FALSE,IF(ISERROR(DATE(2026,10,1)='Model inputs'!B33),DATE(2026,10,1)='Model inputs'!B33,IF('Model inputs'!B33="","",DATE(2026,10,1)='Model inputs'!B33))),IF('Model inputs'!B90="","",'Model inputs'!B90),IF('Model inputs'!K15="","",'Model inputs'!K15)))-'Low-price monthly forecast'!B73 -> 0 | C86: ='Low-price monthly forecast'!C74-IF(IF(IF(IF(ISERROR(DATE(2026,11,1)='Model inputs'!B33),DATE(2026,11,1)='Model inputs'!B33,IF('Model inputs'!B33="","",DATE(2026,11,1)='Model inputs'!B33))="",FALSE,IF(ISERROR(DATE(2026,11,1)='Model inputs'!B33),DATE(2026,11,1)='Model inputs'!B33,IF('Model inputs'!B33="","",DATE(2026,11,1)='Model inputs'!B33))),IF('Model inputs'!B90="","",'Model inputs'!B90),IF('Low-price monthly forecast'!B74="","",'Low-price monthly forecast'!B74))="",0,IF(IF(IF(ISERROR(DATE(2026,11,1)='Model inputs'!B33),DATE(2026,11,1)='Model inputs'!B33,IF('Model inputs'!B33="","",DATE(2026,11,1)='Model inputs'!B33))="",FALSE,IF(ISERROR(DATE(2026,11,1)='Model inputs'!B33),DATE(2026,11,1)='Model inputs'!B33,IF('Model inputs'!B33="","",DATE(2026,11,1)='Model inputs'!B33))),IF('Model inputs'!B90="","",'Model inputs'!B90),IF('Low-price monthly forecast'!B74="","",'Low-price monthly forecast'!B74)))-'Low-price monthly forecast'!C73 -> 0 | D86: ='Low-price monthly forecast'!D74-IF(IF(IF(IF(ISERROR(DATE(2026,12,1)='Model inputs'!B33),DATE(2026,12,1)='Model inputs'!B33,IF('Model inputs'!B33="","",DATE(2026,12,1)='Model inputs'!B33))="",FALSE,IF(ISERROR(DATE(2026,12,1)='Model inputs'!B33),DATE(2026,12,1)='Model inputs'!B33,IF('Model inputs'!B33="","",DATE(2026,12,1)='Model inputs'!B33))),IF('Model inputs'!B90="","",'Model inputs'!B90),IF('Low-price monthly forecast'!C74="","",'Low-price monthly forecast'!C74))="",0,IF(IF(IF(ISERROR(DATE(2026,12,1)='Model inputs'!B33),DATE(2026,12,1)='Model inputs'!B33,IF('Model inputs'!B33="","",DATE(2026,12,1)='Model inputs'!B33))="",FALSE,IF(ISERROR(DATE(2026,12,1)='Model inputs'!B33),DATE(2026,12,1)='Model inputs'!B33,IF('Model inputs'!B33="","",DATE(2026,12,1)='Model inputs'!B33))),IF('Model inputs'!B90="","",'Model inputs'!B90),IF('Low-price monthly forecast'!C74="","",'Low-price monthly forecast'!C74)))-'Low-price monthly forecast'!D73 -> 0 | E86: ='Low-price monthly forecast'!E74-IF(IF(IF(IF(ISERROR(DATE(2027,1,1)='Model inputs'!B33),DATE(2027,1,1)='Model inputs'!B33,IF('Model inputs'!B33="","",DATE(2027,1,1)='Model inputs'!B33))="",FALSE,IF(ISERROR(DATE(2027,1,1)='Model inputs'!B33),DATE(2027,1,1)='Model inputs'!B33,IF('Model inputs'!B33="","",DATE(2027,1,1)='Model inputs'!B33))),IF('Model inputs'!B90="","",'Model inputs'!B90),IF('Low-price monthly forecast'!D74="","",'Low-price monthly forecast'!D74))="",0,IF(IF(IF(ISERROR(DATE(2027,1,1)='Model inputs'!B33),DATE(2027,1,1)='Model inputs'!B33,IF('Model inputs'!B33="","",DATE(2027,1,1)='Model inputs'!B33))="",FALSE,IF(ISERROR(DATE(2027,1,1)='Model inputs'!B33),DATE(2027,1,1)='Model inputs'!B33,IF('Model inputs'!B33="","",DATE(2027,1,1)='Model inputs'!B33))),IF('Model inputs'!B90="","",'Model inputs'!B90),IF('Low-price monthly forecast'!D74="","",'Low-price monthly forecast'!D74)))-'Low-price monthly forecast'!E73 -> 0 | F86: ='Low-price monthly forecast'!F74-IF(IF(IF(IF(ISERROR(DATE(2027,2,1)='Model inputs'!B33),DATE(2027,2,1)='Model inputs'!B33,IF('Model inputs'!B33="","",DATE(2027,2,1)='Model inputs'!B33))="",FALSE,IF(ISERROR(DATE(2027,2,1)='Model inputs'!B33),DATE(2027,2,1)='Model inputs'!B33,IF('Model inputs'!B33="","",DATE(2027,2,1)='Model inputs'!B33))),IF('Model inputs'!B90="","",'Model inputs'!B90),IF('Low-price monthly forecast'!E74="","",'Low-price monthly forecast'!E74))="",0,IF(IF(IF(ISERROR(DATE(2027,2,1)='Model inputs'!B33),DATE(2027,2,1)='Model inputs'!B33,IF('Model inputs'!B33="","",DATE(2027,2,1)='Model inputs'!B33))="",FALSE,IF(ISERROR(DATE(2027,2,1)='Model inputs'!B33),DATE(2027,2,1)='Model inputs'!B33,IF('Model inputs'!B33="","",DATE(2027,2,1)='Model inputs'!B33))),IF('Model inputs'!B90="","",'Model inputs'!B90),IF('Low-price monthly forecast'!E74="","",'Low-price monthly forecast'!E74)))-'Low-price monthly forecast'!F73 -> 0 | G86: ='Low-price monthly forecast'!G74-IF(IF(IF(IF(ISERROR(DATE(2027,3,1)='Model inputs'!B33),DATE(2027,3,1)='Model inputs'!B33,IF('Model inputs'!B33="","",DATE(2027,3,1)='Model inputs'!B33))="",FALSE,IF(ISERROR(DATE(2027,3,1)='Model inputs'!B33),DATE(2027,3,1)='Model inputs'!B33,IF('Model inputs'!B33="","",DATE(2027,3,1)='Model inputs'!B33))),IF('Model inputs'!B90="","",'Model inputs'!B90),IF('Low-price monthly forecast'!F74="","",'Low-price monthly forecast'!F74))="",0,IF(IF(IF(ISERROR(DATE(2027,3,1)='Model inputs'!B33),DATE(2027,3,1)='Model inputs'!B33,IF('Model inputs'!B33="","",DATE(2027,3,1)='Model inputs'!B33))="",FALSE,IF(ISERROR(DATE(2027,3,1)='Model inputs'!B33),DATE(2027,3,1)='Model inputs'!B33,IF('Model inputs'!B33="","",DATE(2027,3,1)='Model inputs'!B33))),IF('Model inputs'!B90="","",'Model inputs'!B90),IF('Low-price monthly forecast'!F74="","",'Low-price monthly forecast'!F74)))-'Low-price monthly forecast'!G73 -> 0 | H86: ='Low-price monthly forecast'!H74-IF(IF(IF(IF(ISERROR(DATE(2027,4,1)='Model inputs'!B33),DATE(2027,4,1)='Model inputs'!B33,IF('Model inputs'!B33="","",DATE(2027,4,1)='Model inputs'!B33))="",FALSE,IF(ISERROR(DATE(2027,4,1)='Model inputs'!B33),DATE(2027,4,1)='Model inputs'!B33,IF('Model inputs'!B33="","",DATE(2027,4,1)='Model inputs'!B33))),IF('Model inputs'!B90="","",'Model inputs'!B90),IF('Low-price monthly forecast'!G74="","",'Low-price monthly forecast'!G74))="",0,IF(IF(IF(ISERROR(DATE(2027,4,1)='Model inputs'!B33),DATE(2027,4,1)='Model inputs'!B33,IF('Model inputs'!B33="","",DATE(2027,4,1)='Model inputs'!B33))="",FALSE,IF(ISERROR(DATE(2027,4,1)='Model inputs'!B33),DATE(2027,4,1)='Model inputs'!B33,IF('Model inputs'!B33="","",DATE(2027,4,1)='Model inputs'!B33))),IF('Model inputs'!B90="","",'Model inputs'!B90),IF('Low-price monthly forecast'!G74="","",'Low-price monthly forecast'!G74)))-'Low-price monthly forecast'!H73 -> 0 | I86: ='Low-price monthly forecast'!I74-IF(IF(IF(IF(ISERROR(DATE(2027,5,1)='Model inputs'!B33),DATE(2027,5,1)='Model inputs'!B33,IF('Model inputs'!B33="","",DATE(2027,5,1)='Model inputs'!B33))="",FALSE,IF(ISERROR(DATE(2027,5,1)='Model inputs'!B33),DATE(2027,5,1)='Model inputs'!B33,IF('Model inputs'!B33="","",DATE(2027,5,1)='Model inputs'!B33))),IF('Model inputs'!B90="","",'Model inputs'!B90),IF('Low-price monthly forecast'!H74="","",'Low-price monthly forecast'!H74))="",0,IF(IF(IF(ISERROR(DATE(2027,5,1)='Model inputs'!B33),DATE(2027,5,1)='Model inputs'!B33,IF('Model inputs'!B33="","",DATE(2027,5,1)='Model inputs'!B33))="",FALSE,IF(ISERROR(DATE(2027,5,1)='Model inputs'!B33),DATE(2027,5,1)='Model inputs'!B33,IF('Model inputs'!B33="","",DATE(2027,5,1)='Model inputs'!B33))),IF('Model inputs'!B90="","",'Model inputs'!B90),IF('Low-price monthly forecast'!H74="","",'Low-price monthly forecast'!H74)))-'Low-price monthly forecast'!I73 -> 0 | J86: ='Low-price monthly forecast'!J74-IF(IF(IF(IF(ISERROR(DATE(2027,6,1)='Model inputs'!B33),DATE(2027,6,1)='Model inputs'!B33,IF('Model inputs'!B33="","",DATE(2027,6,1)='Model inputs'!B33))="",FALSE,IF(ISERROR(DATE(2027,6,1)='Model inputs'!B33),DATE(2027,6,1)='Model inputs'!B33,IF('Model inputs'!B33="","",DATE(2027,6,1)='Model inputs'!B33))),IF('Model inputs'!B90="","",'Model inputs'!B90),IF('Low-price monthly forecast'!I74="","",'Low-price monthly forecast'!I74))="",0,IF(IF(IF(ISERROR(DATE(2027,6,1)='Model inputs'!B33),DATE(2027,6,1)='Model inputs'!B33,IF('Model inputs'!B33="","",DATE(2027,6,1)='Model inputs'!B33))="",FALSE,IF(ISERROR(DATE(2027,6,1)='Model inputs'!B33),DATE(2027,6,1)='Model inputs'!B33,IF('Model inputs'!B33="","",DATE(2027,6,1)='Model inputs'!B33))),IF('Model inputs'!B90="","",'Model inputs'!B90),IF('Low-price monthly forecast'!I74="","",'Low-price monthly forecast'!I74)))-'Low-price monthly forecast'!J73 -> 0 | K86: ='Low-price monthly forecast'!K74-IF(IF(IF(IF(ISERROR(DATE(2027,7,1)='Model inputs'!B33),DATE(2027,7,1)='Model inputs'!B33,IF('Model inputs'!B33="","",DATE(2027,7,1)='Model inputs'!B33))="",FALSE,IF(ISERROR(DATE(2027,7,1)='Model inputs'!B33),DATE(2027,7,1)='Model inputs'!B33,IF('Model inputs'!B33="","",DATE(2027,7,1)='Model inputs'!B33))),IF('Model inputs'!B90="","",'Model inputs'!B90),IF('Low-price monthly forecast'!J74="","",'Low-price monthly forecast'!J74))="",0,IF(IF(IF(ISERROR(DATE(2027,7,1)='Model inputs'!B33),DATE(2027,7,1)='Model inputs'!B33,IF('Model inputs'!B33="","",DATE(2027,7,1)='Model inputs'!B33))="",FALSE,IF(ISERROR(DATE(2027,7,1)='Model inputs'!B33),DATE(2027,7,1)='Model inputs'!B33,IF('Model inputs'!B33="","",DATE(2027,7,1)='Model inputs'!B33))),IF('Model inputs'!B90="","",'Model inputs'!B90),IF('Low-price monthly forecast'!J74="","",'Low-price monthly forecast'!J74)))-'Low-price monthly forecast'!K73 -> -9.094947e-13 | L86: ='Low-price monthly forecast'!L74-IF(IF(IF(IF(ISERROR(DATE(2027,8,1)='Model inputs'!B33),DATE(2027,8,1)='Model inputs'!B33,IF('Model inputs'!B33="","",DATE(2027,8,1)='Model inputs'!B33))="",FALSE,IF(ISERROR(DATE(2027,8,1)='Model inputs'!B33),DATE(2027,8,1)='Model inputs'!B33,IF('Model inputs'!B33="","",DATE(2027,8,1)='Model inputs'!B33))),IF('Model inputs'!B90="","",'Model inputs'!B90),IF('Low-price monthly forecast'!K74="","",'Low-price monthly forecast'!K74))="",0,IF(IF(IF(ISERROR(DATE(2027,8,1)='Model inputs'!B33),DATE(2027,8,1)='Model inputs'!B33,IF('Model inputs'!B33="","",DATE(2027,8,1)='Model inputs'!B33))="",FALSE,IF(ISERROR(DATE(2027,8,1)='Model inputs'!B33),DATE(2027,8,1)='Model inputs'!B33,IF('Model inputs'!B33="","",DATE(2027,8,1)='Model inputs'!B33))),IF('Model inputs'!B90="","",'Model inputs'!B90),IF('Low-price monthly forecast'!K74="","",'Low-price monthly forecast'!K74)))-'Low-price monthly forecast'!L73 -> 0 | M86: ='Low-price monthly forecast'!M74-IF(IF(IF(IF(ISERROR(DATE(2027,9,1)='Model inputs'!B33),DATE(2027,9,1)='Model inputs'!B33,IF('Model inputs'!B33="","",DATE(2027,9,1)='Model inputs'!B33))="",FALSE,IF(ISERROR(DATE(2027,9,1)='Model inputs'!B33),DATE(2027,9,1)='Model inputs'!B33,IF('Model inputs'!B33="","",DATE(2027,9,1)='Model inputs'!B33))),IF('Model inputs'!B90="","",'Model inputs'!B90),IF('Low-price monthly forecast'!L74="","",'Low-price monthly forecast'!L74))="",0,IF(IF(IF(ISERROR(DATE(2027,9,1)='Model inputs'!B33),DATE(2027,9,1)='Model inputs'!B33,IF('Model inputs'!B33="","",DATE(2027,9,1)='Model inputs'!B33))="",FALSE,IF(ISERROR(DATE(2027,9,1)='Model inputs'!B33),DATE(2027,9,1)='Model inputs'!B33,IF('Model inputs'!B33="","",DATE(2027,9,1)='Model inputs'!B33))),IF('Model inputs'!B90="","",'Model inputs'!B90),IF('Low-price monthly forecast'!L74="","",'Low-price monthly forecast'!L74)))-'Low-price monthly forecast'!M73 -> 0 | N86: ='Low-price monthly forecast'!N74-IF(IF(IF(IF(ISERROR(DATE(2027,10,1)='Model inputs'!B33),DATE(2027,10,1)='Model inputs'!B33,IF('Model inputs'!B33="","",DATE(2027,10,1)='Model inputs'!B33))="",FALSE,IF(ISERROR(DATE(2027,10,1)='Model inputs'!B33),DATE(2027,10,1)='Model inputs'!B33,IF('Model inputs'!B33="","",DATE(2027,10,1)='Model inputs'!B33))),IF('Model inputs'!B90="","",'Model inputs'!B90),IF('Low-price monthly forecast'!M74="","",'Low-price monthly forecast'!M74))="",0,IF(IF(IF(ISERROR(DATE(2027,10,1)='Model inputs'!B33),DATE(2027,10,1)='Model inputs'!B33,IF('Model inputs'!B33="","",DATE(2027,10,1)='Model inputs'!B33))="",FALSE,IF(ISERROR(DATE(2027,10,1)='Model inputs'!B33),DATE(2027,10,1)='Model inputs'!B33,IF('Model inputs'!B33="","",DATE(2027,10,1)='Model inputs'!B33))),IF('Model inputs'!B90="","",'Model inputs'!B90),IF('Low-price monthly forecast'!M74="","",'Low-price monthly forecast'!M74)))-'Low-price monthly forecast'!N73 -> 0 | O86: ='Low-price monthly forecast'!O74-IF(IF(IF(IF(ISERROR(DATE(2027,11,1)='Model inputs'!B33),DATE(2027,11,1)='Model inputs'!B33,IF('Model inputs'!B33="","",DATE(2027,11,1)='Model inputs'!B33))="",FALSE,IF(ISERROR(DATE(2027,11,1)='Model inputs'!B33),DATE(2027,11,1)='Model inputs'!B33,IF('Model inputs'!B33="","",DATE(2027,11,1)='Model inputs'!B33))),IF('Model inputs'!B90="","",'Model inputs'!B90),IF('Low-price monthly forecast'!N74="","",'Low-price monthly forecast'!N74))="",0,IF(IF(IF(ISERROR(DATE(2027,11,1)='Model inputs'!B33),DATE(2027,11,1)='Model inputs'!B33,IF('Model inputs'!B33="","",DATE(2027,11,1)='Model inputs'!B33))="",FALSE,IF(ISERROR(DATE(2027,11,1)='Model inputs'!B33),DATE(2027,11,1)='Model inputs'!B33,IF('Model inputs'!B33="","",DATE(2027,11,1)='Model inputs'!B33))),IF('Model inputs'!B90="","",'Model inputs'!B90),IF('Low-price monthly forecast'!N74="","",'Low-price monthly forecast'!N74)))-'Low-price monthly forecast'!O73 -> 0 | P86: ='Low-price monthly forecast'!P74-IF(IF(IF(IF(ISERROR(DATE(2027,12,1)='Model inputs'!B33),DATE(2027,12,1)='Model inputs'!B33,IF('Model inputs'!B33="","",DATE(2027,12,1)='Model inputs'!B33))="",FALSE,IF(ISERROR(DATE(2027,12,1)='Model inputs'!B33),DATE(2027,12,1)='Model inputs'!B33,IF('Model inputs'!B33="","",DATE(2027,12,1)='Model inputs'!B33))),IF('Model inputs'!B90="","",'Model inputs'!B90),IF('Low-price monthly forecast'!O74="","",'Low-price monthly forecast'!O74))="",0,IF(IF(IF(ISERROR(DATE(2027,12,1)='Model inputs'!B33),DATE(2027,12,1)='Model inputs'!B33,IF('Model inputs'!B33="","",DATE(2027,12,1)='Model inputs'!B33))="",FALSE,IF(ISERROR(DATE(2027,12,1)='Model inputs'!B33),DATE(2027,12,1)='Model inputs'!B33,IF('Model inputs'!B33="","",DATE(2027,12,1)='Model inputs'!B33))),IF('Model inputs'!B90="","",'Model inputs'!B90),IF('Low-price monthly forecast'!O74="","",'Low-price monthly forecast'!O74)))-'Low-price monthly forecast'!P73 -> 0 | Q86: ='Low-price monthly forecast'!Q74-IF(IF(IF(IF(ISERROR(DATE(2028,1,1)='Model inputs'!B33),DATE(2028,1,1)='Model inputs'!B33,IF('Model inputs'!B33="","",DATE(2028,1,1)='Model inputs'!B33))="",FALSE,IF(ISERROR(DATE(2028,1,1)='Model inputs'!B33),DATE(2028,1,1)='Model inputs'!B33,IF('Model inputs'!B33="","",DATE(2028,1,1)='Model inputs'!B33))),IF('Model inputs'!B90="","",'Model inputs'!B90),IF('Low-price monthly forecast'!P74="","",'Low-price monthly forecast'!P74))="",0,IF(IF(IF(ISERROR(DATE(2028,1,1)='Model inputs'!B33),DATE(2028,1,1)='Model inputs'!B33,IF('Model inputs'!B33="","",DATE(2028,1,1)='Model inputs'!B33))="",FALSE,IF(ISERROR(DATE(2028,1,1)='Model inputs'!B33),DATE(2028,1,1)='Model inputs'!B33,IF('Model inputs'!B33="","",DATE(2028,1,1)='Model inputs'!B33))),IF('Model inputs'!B90="","",'Model inputs'!B90),IF('Low-price monthly forecast'!P74="","",'Low-price monthly forecast'!P74)))-'Low-price monthly forecast'!Q73 -> -1.8189894e-12 | R86: ='Low-price monthly forecast'!R74-IF(IF(IF(IF(ISERROR(DATE(2028,2,1)='Model inputs'!B33),DATE(2028,2,1)='Model inputs'!B33,IF('Model inputs'!B33="","",DATE(2028,2,1)='Model inputs'!B33))="",FALSE,IF(ISERROR(DATE(2028,2,1)='Model inputs'!B33),DATE(2028,2,1)='Model inputs'!B33,IF('Model inputs'!B33="","",DATE(2028,2,1)='Model inputs'!B33))),IF('Model inputs'!B90="","",'Model inputs'!B90),IF('Low-price monthly forecast'!Q74="","",'Low-price monthly forecast'!Q74))="",0,IF(IF(IF(ISERROR(DATE(2028,2,1)='Model inputs'!B33),DATE(2028,2,1)='Model inputs'!B33,IF('Model inputs'!B33="","",DATE(2028,2,1)='Model inputs'!B33))="",FALSE,IF(ISERROR(DATE(2028,2,1)='Model inputs'!B33),DATE(2028,2,1)='Model inputs'!B33,IF('Model inputs'!B33="","",DATE(2028,2,1)='Model inputs'!B33))),IF('Model inputs'!B90="","",'Model inputs'!B90),IF('Low-price monthly forecast'!Q74="","",'Low-price monthly forecast'!Q74)))-'Low-price monthly forecast'!R73 -> 1.8189894e-12 | S86: ='Low-price monthly forecast'!S74-IF(IF(IF(IF(ISERROR(DATE(2028,3,1)='Model inputs'!B33),DATE(2028,3,1)='Model inputs'!B33,IF('Model inputs'!B33="","",DATE(2028,3,1)='Model inputs'!B33))="",FALSE,IF(ISERROR(DATE(2028,3,1)='Model inputs'!B33),DATE(2028,3,1)='Model inputs'!B33,IF('Model inputs'!B33="","",DATE(2028,3,1)='Model inputs'!B33))),IF('Model inputs'!B90="","",'Model inputs'!B90),IF('Low-price monthly forecast'!R74="","",'Low-price monthly forecast'!R74))="",0,IF(IF(IF(ISERROR(DATE(2028,3,1)='Model inputs'!B33),DATE(2028,3,1)='Model inputs'!B33,IF('Model inputs'!B33="","",DATE(2028,3,1)='Model inputs'!B33))="",FALSE,IF(ISERROR(DATE(2028,3,1)='Model inputs'!B33),DATE(2028,3,1)='Model inputs'!B33,IF('Model inputs'!B33="","",DATE(2028,3,1)='Model inputs'!B33))),IF('Model inputs'!B90="","",'Model inputs'!B90),IF('Low-price monthly forecast'!R74="","",'Low-price monthly forecast'!R74)))-'Low-price monthly forecast'!S73 -> 1.8189894e-12

Sheet Low-price monthly milestones
A1: Low-price monthly milestones
A2: NightWatch — Forecast · Base
A4: Variable / dimension | B4: 2026-10 | C4: 2026-11 | D4: 2026-12 | E4: 2027-01 | F4: 2027-02 | G4: 2027-03 | H4: 2027-04 | I4: 2027-05 | J4: 2027-06 | K4: 2027-07 | L4: 2027-08 | M4: 2027-09 | N4: 2027-10 | O4: 2027-11 | P4: 2027-12 | Q4: 2028-01 | R4: 2028-02 | S4: 2028-03
A5: NW Break-even marker | B5: =IF(IF(IF(ISERROR('Low-price monthly forecast'!B73>=0),'Low-price monthly forecast'!B73>=0,IF('Low-price monthly forecast'!B73="","",'Low-price monthly forecast'!B73>=0))="",FALSE,IF(ISERROR('Low-price monthly forecast'!B73>=0),'Low-price monthly forecast'!B73>=0,IF('Low-price monthly forecast'!B73="","",'Low-price monthly forecast'!B73>=0))),DATE(2026,10,1),"") | C5: =IF(IF(IF(ISERROR('Low-price monthly forecast'!C73>=0),'Low-price monthly forecast'!C73>=0,IF('Low-price monthly forecast'!C73="","",'Low-price monthly forecast'!C73>=0))="",FALSE,IF(ISERROR('Low-price monthly forecast'!C73>=0),'Low-price monthly forecast'!C73>=0,IF('Low-price monthly forecast'!C73="","",'Low-price monthly forecast'!C73>=0))),DATE(2026,11,1),"") | D5: =IF(IF(IF(ISERROR('Low-price monthly forecast'!D73>=0),'Low-price monthly forecast'!D73>=0,IF('Low-price monthly forecast'!D73="","",'Low-price monthly forecast'!D73>=0))="",FALSE,IF(ISERROR('Low-price monthly forecast'!D73>=0),'Low-price monthly forecast'!D73>=0,IF('Low-price monthly forecast'!D73="","",'Low-price monthly forecast'!D73>=0))),DATE(2026,12,1),"") | E5: =IF(IF(IF(ISERROR('Low-price monthly forecast'!E73>=0),'Low-price monthly forecast'!E73>=0,IF('Low-price monthly forecast'!E73="","",'Low-price monthly forecast'!E73>=0))="",FALSE,IF(ISERROR('Low-price monthly forecast'!E73>=0),'Low-price monthly forecast'!E73>=0,IF('Low-price monthly forecast'!E73="","",'Low-price monthly forecast'!E73>=0))),DATE(2027,1,1),"") | F5: =IF(IF(IF(ISERROR('Low-price monthly forecast'!F73>=0),'Low-price monthly forecast'!F73>=0,IF('Low-price monthly forecast'!F73="","",'Low-price monthly forecast'!F73>=0))="",FALSE,IF(ISERROR('Low-price monthly forecast'!F73>=0),'Low-price monthly forecast'!F73>=0,IF('Low-price monthly forecast'!F73="","",'Low-price monthly forecast'!F73>=0))),DATE(2027,2,1),"") | G5: =IF(IF(IF(ISERROR('Low-price monthly forecast'!G73>=0),'Low-price monthly forecast'!G73>=0,IF('Low-price monthly forecast'!G73="","",'Low-price monthly forecast'!G73>=0))="",FALSE,IF(ISERROR('Low-price monthly forecast'!G73>=0),'Low-price monthly forecast'!G73>=0,IF('Low-price monthly forecast'!G73="","",'Low-price monthly forecast'!G73>=0))),DATE(2027,3,1),"") | H5: =IF(IF(IF(ISERROR('Low-price monthly forecast'!H73>=0),'Low-price monthly forecast'!H73>=0,IF('Low-price monthly forecast'!H73="","",'Low-price monthly forecast'!H73>=0))="",FALSE,IF(ISERROR('Low-price monthly forecast'!H73>=0),'Low-price monthly forecast'!H73>=0,IF('Low-price monthly forecast'!H73="","",'Low-price monthly forecast'!H73>=0))),DATE(2027,4,1),"") -> 46478 | I5: =IF(IF(IF(ISERROR('Low-price monthly forecast'!I73>=0),'Low-price monthly forecast'!I73>=0,IF('Low-price monthly forecast'!I73="","",'Low-price monthly forecast'!I73>=0))="",FALSE,IF(ISERROR('Low-price monthly forecast'!I73>=0),'Low-price monthly forecast'!I73>=0,IF('Low-price monthly forecast'!I73="","",'Low-price monthly forecast'!I73>=0))),DATE(2027,5,1),"") -> 46508 | J5: =IF(IF(IF(ISERROR('Low-price monthly forecast'!J73>=0),'Low-price monthly forecast'!J73>=0,IF('Low-price monthly forecast'!J73="","",'Low-price monthly forecast'!J73>=0))="",FALSE,IF(ISERROR('Low-price monthly forecast'!J73>=0),'Low-price monthly forecast'!J73>=0,IF('Low-price monthly forecast'!J73="","",'Low-price monthly forecast'!J73>=0))),DATE(2027,6,1),"") -> 46539 | K5: =IF(IF(IF(ISERROR('Low-price monthly forecast'!K73>=0),'Low-price monthly forecast'!K73>=0,IF('Low-price monthly forecast'!K73="","",'Low-price monthly forecast'!K73>=0))="",FALSE,IF(ISERROR('Low-price monthly forecast'!K73>=0),'Low-price monthly forecast'!K73>=0,IF('Low-price monthly forecast'!K73="","",'Low-price monthly forecast'!K73>=0))),DATE(2027,7,1),"") -> 46569 | L5: =IF(IF(IF(ISERROR('Low-price monthly forecast'!L73>=0),'Low-price monthly forecast'!L73>=0,IF('Low-price monthly forecast'!L73="","",'Low-price monthly forecast'!L73>=0))="",FALSE,IF(ISERROR('Low-price monthly forecast'!L73>=0),'Low-price monthly forecast'!L73>=0,IF('Low-price monthly forecast'!L73="","",'Low-price monthly forecast'!L73>=0))),DATE(2027,8,1),"") -> 46600 | M5: =IF(IF(IF(ISERROR('Low-price monthly forecast'!M73>=0),'Low-price monthly forecast'!M73>=0,IF('Low-price monthly forecast'!M73="","",'Low-price monthly forecast'!M73>=0))="",FALSE,IF(ISERROR('Low-price monthly forecast'!M73>=0),'Low-price monthly forecast'!M73>=0,IF('Low-price monthly forecast'!M73="","",'Low-price monthly forecast'!M73>=0))),DATE(2027,9,1),"") -> 46631 | N5: =IF(IF(IF(ISERROR('Low-price monthly forecast'!N73>=0),'Low-price monthly forecast'!N73>=0,IF('Low-price monthly forecast'!N73="","",'Low-price monthly forecast'!N73>=0))="",FALSE,IF(ISERROR('Low-price monthly forecast'!N73>=0),'Low-price monthly forecast'!N73>=0,IF('Low-price monthly forecast'!N73="","",'Low-price monthly forecast'!N73>=0))),DATE(2027,10,1),"") -> 46661 | O5: =IF(IF(IF(ISERROR('Low-price monthly forecast'!O73>=0),'Low-price monthly forecast'!O73>=0,IF('Low-price monthly forecast'!O73="","",'Low-price monthly forecast'!O73>=0))="",FALSE,IF(ISERROR('Low-price monthly forecast'!O73>=0),'Low-price monthly forecast'!O73>=0,IF('Low-price monthly forecast'!O73="","",'Low-price monthly forecast'!O73>=0))),DATE(2027,11,1),"") -> 46692 | P5: =IF(IF(IF(ISERROR('Low-price monthly forecast'!P73>=0),'Low-price monthly forecast'!P73>=0,IF('Low-price monthly forecast'!P73="","",'Low-price monthly forecast'!P73>=0))="",FALSE,IF(ISERROR('Low-price monthly forecast'!P73>=0),'Low-price monthly forecast'!P73>=0,IF('Low-price monthly forecast'!P73="","",'Low-price monthly forecast'!P73>=0))),DATE(2027,12,1),"") -> 46722 | Q5: =IF(IF(IF(ISERROR('Low-price monthly forecast'!Q73>=0),'Low-price monthly forecast'!Q73>=0,IF('Low-price monthly forecast'!Q73="","",'Low-price monthly forecast'!Q73>=0))="",FALSE,IF(ISERROR('Low-price monthly forecast'!Q73>=0),'Low-price monthly forecast'!Q73>=0,IF('Low-price monthly forecast'!Q73="","",'Low-price monthly forecast'!Q73>=0))),DATE(2028,1,1),"") -> 46753 | R5: =IF(IF(IF(ISERROR('Low-price monthly forecast'!R73>=0),'Low-price monthly forecast'!R73>=0,IF('Low-price monthly forecast'!R73="","",'Low-price monthly forecast'!R73>=0))="",FALSE,IF(ISERROR('Low-price monthly forecast'!R73>=0),'Low-price monthly forecast'!R73>=0,IF('Low-price monthly forecast'!R73="","",'Low-price monthly forecast'!R73>=0))),DATE(2028,2,1),"") -> 46784 | S5: =IF(IF(IF(ISERROR('Low-price monthly forecast'!S73>=0),'Low-price monthly forecast'!S73>=0,IF('Low-price monthly forecast'!S73="","",'Low-price monthly forecast'!S73>=0))="",FALSE,IF(ISERROR('Low-price monthly forecast'!S73>=0),'Low-price monthly forecast'!S73>=0,IF('Low-price monthly forecast'!S73="","",'Low-price monthly forecast'!S73>=0))),DATE(2028,3,1),"") -> 46813
